Workbook
Name NombreIntervalo1: 'PRECIO PROVEEDORES'!$A$3:$A$543

Sheet COCINA TUESTE
A1: vega
B2: YOGURT GRIEGO | G2: HUEVOS REVUELTOS | L2: PANCAKES | Q2: TOSTADAS FRANCESAS | V2: SANDWICH POLLO TERIYAKI | AA2: TOSTADO JAMON Y QUESO | AF2: HAMBURGUESA VEGAN
C3: Kg/Lt/Uni | D3: $ | E3: Total $ | H3: Kg/Lt/Uni | I3: $ | J3: Total $ | M3: Kg/Lt/Uni | N3: $ | O3: Total $ | R3: Kg/Lt/Uni | S3: $ | T3: Total $ | W3: Kg/Lt/Uni | X3: $ | Y3: Total $ | AB3: Kg/Lt/Uni | AC3: $ | AD3: Total $ | AG3: Kg/Lt/Uni | AH3: $ | AI3: Total $
B4: yogurt griego | C4: 0.15 | D4: =+VLOOKUP(B4,'PRECIO PROVEEDORES'!$A$2:$B$716,2,0) -> 7449.2 | E4: =+C4*D4 -> 1117.38 | G4: tostada en pan de campo xl | H4: 1 | I4: =+VLOOKUP(G4,'PRECIO PROVEEDORES'!$A$2:$B$716,2,0) -> 243.1 | J4: =+H4*I4 -> 243.1 | L4: pancakes | M4: 2 | N4: =+VLOOKUP(L4,'PRECIO PROVEEDORES'!$A$2:$B$716,2,0) -> 391.805 | O4: =+M4*N4 -> 783.61 | Q4: uva | R4: 0.04 | S4: =+VLOOKUP(Q4,'PRECIO PROVEEDORES'!$A$2:$B$716,2,0) -> 2332 | T4: =+R4*S4 -> 93.28 | V4: tostada en pan de campo xl | W4: 2 | X4: =+VLOOKUP(V4,'PRECIO PROVEEDORES'!$A$2:$B$716,2,0) -> 243.1 | Y4: =+W4*X4 -> 486.2 | AA4: tostada en pan de campo xl | AB4: 2 | AC4: =+VLOOKUP(AA4,'PRECIO PROVEEDORES'!$A$2:$B$716,2,0) -> 243.1 | AD4: =+AB4*AC4 -> 486.2 | AF4: pan burger vegano | AG4: 1 | AH4: =+VLOOKUP(AF4,'PRECIO PROVEEDORES'!$A$2:$B$716,2,0) -> 992.2 | AI4: =+AG4*AH4 -> 992.2
B5: granola | C5: 0.05 | D5: =+VLOOKUP(B5,'PRECIO PROVEEDORES'!$A$2:$B$716,2,0) -> 8954.3189 | E5: =+C5*D5 -> 447.71595 | G5: huevos | H5: 3 | I5: =+VLOOKUP(G5,'PRECIO PROVEEDORES'!$A$2:$B$716,2,0) -> 192 | J5: =+H5*I5 -> 576 | L5: salsa de chocolate | M5: 0.01 | N5: =+VLOOKUP(L5,'PRECIO PROVEEDORES'!$A$2:$B$716,2,0) -> 9542 | O5: =+M5*N5 -> 95.42 | Q5: Brioche para tostadas francesas | R5: 1 | S5: =+VLOOKUP(Q5,'PRECIO PROVEEDORES'!$A$2:$B$716,2,0) -> 1650 | T5: =+R5*S5 -> 1650 | V5: pollo | W5: 0.12 | X5: =+VLOOKUP(V5,'PRECIO PROVEEDORES'!$A$2:$B$716,2,0) -> 7700 | Y5: =+W5*X5 -> 924 | AA5: Fiambre, Jamon cocido | AB5: 0.06 | AC5: =+VLOOKUP(AA5,'PRECIO PROVEEDORES'!$A$2:$B$716,2,0) -> 11881 | AD5: =+AB5*AC5 -> 712.86 | AF5: Aji colorado | AG5: 0.03 | AH5: =+VLOOKUP(AF5,'PRECIO PROVEEDORES'!$A$2:$B$716,2,0) -> 4788 | AI5: =+AG5*AH5 -> 143.64
B6: banana | C6: 0.05 | D6: =+VLOOKUP(B6,'PRECIO PROVEEDORES'!$A$2:$B$716,2,0) -> 3360 | E6: =+C6*D6 -> 168 | G6: Palta hass | H6: 0.08 | I6: =+VLOOKUP(G6,'PRECIO PROVEEDORES'!$A$2:$B$716,2,0) -> 9316 | J6: =+H6*I6 -> 745.28 | L6: Banana | M6: 0.08 | N6: =+VLOOKUP(L6,'PRECIO PROVEEDORES'!$A$2:$B$716,2,0) -> 3360 | O6: =+M6*N6 -> 268.8 | Q6: queso crema paulina | R6: 0.03 | S6: =+VLOOKUP(Q6,'PRECIO PROVEEDORES'!$A$2:$B$716,2,0) -> 6000 | T6: =+R6*S6 -> 180 | V6: Lechuga, francesa | W6: 0.02 | X6: =+VLOOKUP(V6,'PRECIO PROVEEDORES'!$A$2:$B$716,2,0) -> 6440 | Y6: =+W6*X6 -> 128.8 | AA6: queso danbo tregar | AB6: 0.09 | AC6: =+VLOOKUP(AA6,'PRECIO PROVEEDORES'!$A$2:$B$716,2,0) -> 10697 | AD6: =+AB6*AC6 -> 962.73 | AF6: Hoja amarga, Rucula selvatica | AG6: 0.05 | AH6: =+VLOOKUP(AF6,'PRECIO PROVEEDORES'!$A$2:$B$716,2,0) -> 9900 | AI6: =+AG6*AH6 -> 495
B7: frutilla | C7: 0.04 | D7: =+VLOOKUP(B7,'PRECIO PROVEEDORES'!$A$2:$B$716,2,0) -> 26000 | E7: =+C7*D7 -> 1040 | G7: queso crema paulina | H7: 0.035 | I7: =+VLOOKUP(G7,'PRECIO PROVEEDORES'!$A$2:$B$716,2,0) -> 6000 | J7: =+H7*I7 -> 210 | L7: frutilla | M7: 0.05 | N7: =+VLOOKUP(L7,'PRECIO PROVEEDORES'!$A$2:$B$716,2,0) -> 26000 | O7: =+M7*N7 -> 1300 | Q7: frutilla | R7: 0.05 | S7: =+VLOOKUP(Q7,'PRECIO PROVEEDORES'!$A$2:$B$716,2,0) -> 26000 | T7: =+R7*S7 -> 1300 | V7: palta hass | W7: 0.04 | X7: =+VLOOKUP(V7,'PRECIO PROVEEDORES'!$A$2:$B$716,2,0) -> 9316 | Y7: =+W7*X7 -> 372.64 | AA7: manteca tueste alyser | AB7: 0.02 | AC7: =+VLOOKUP(AA7,'PRECIO PROVEEDORES'!$A$2:$B$716,2,0) -> 12206 | AD7: =+AB7*AC7 -> 244.12 | AF7: pesto de albahaca | AG7: 0.01 | AH7: =+VLOOKUP(AF7,'PRECIO PROVEEDORES'!$A$2:$B$716,2,0) -> 0 | AI7: =+AG7*AH7 -> 0
B8: miel alyser | C8: 0.01 | D8: =+VLOOKUP(B8,'PRECIO PROVEEDORES'!$A$2:$B$716,2,0) -> 5917 | E8: =+C8*D8 -> 59.17 | G8: Tomate cherry rojo | H8: 0.05 | I8: =+VLOOKUP(G8,'PRECIO PROVEEDORES'!$A$2:$B$716,2,0) -> 4095 | J8: =+H8*I8 -> 204.75 | L8: nutella | M8: 0.02 | N8: =+VLOOKUP(L8,'PRECIO PROVEEDORES'!$A$2:$B$716,2,0) -> 35691.97 | O8: =+M8*N8 -> 713.8394 | Q8: miel alyser | R8: 0.015 | S8: =+VLOOKUP(Q8,'PRECIO PROVEEDORES'!$A$2:$B$716,2,0) -> 5917 | T8: =+R8*S8 -> 88.755 | V8: tomate seco | W8: 0.05 | X8: =+VLOOKUP(V8,'PRECIO PROVEEDORES'!$A$2:$B$716,2,0) -> 17587.35 | Y8: =+W8*X8 -> 879.3675 | AF8: Garbanzos | AG8: 0.1 | AH8: =+VLOOKUP(AF8,'PRECIO PROVEEDORES'!$A$2:$B$716,2,0) -> 3330 | AI8: =+AG8*AH8 -> 333
B9: arandano | C9: 0.01 | D9: =+VLOOKUP(B9,'PRECIO PROVEEDORES'!$A$2:$B$716,2,0) -> 56000 | E9: =+C9*D9 -> 560 | G9: Fiambre, Panceta ahumada | H9: 0.02 | I9: =+VLOOKUP(G9,'PRECIO PROVEEDORES'!$A$2:$B$716,2,0) -> 18256.35 | J9: =+H9*I9 -> 365.127 | Q9: Hierbas frescas, Menta bariada | R9: 0.002 | S9: =+VLOOKUP(Q9,'PRECIO PROVEEDORES'!$A$2:$B$716,2,0) -> 18304 | T9: =+R9*S9 -> 36.608 | V9: salsa teriyaki | W9: 0.05 | X9: =+VLOOKUP(V9,'PRECIO PROVEEDORES'!$A$2:$B$716,2,0) -> 2910.45 | Y9: =+W9*X9 -> 145.5225 | AF9: cebolla | AG9: 0.06 | AH9: =+VLOOKUP(AF9,'PRECIO PROVEEDORES'!$A$2:$B$716,2,0) -> 1092.5 | AI9: =+AG9*AH9 -> 65.55
Q10: manteca tueste alyser | R10: 0.01 | S10: =+VLOOKUP(Q10,'PRECIO PROVEEDORES'!$A$2:$B$716,2,0) -> 12206 | T10: =+R10*S10 -> 122.06 | V10: queso danbo tregar | W10: 0.02 | X10: =+VLOOKUP(V10,'PRECIO PROVEEDORES'!$A$2:$B$716,2,0) -> 10697 | Y10: =+W10*X10 -> 213.94 | AF10: Hierbas frescas, Menta bariada | AG10: 0.1 | AH10: =+VLOOKUP(AF10,'PRECIO PROVEEDORES'!$A$2:$B$716,2,0) -> 18304 | AI10: =+AG10*AH10 -> 1830.4
Q11: kiwi | R11: 0.05 | S11: =+VLOOKUP(Q11,'PRECIO PROVEEDORES'!$A$2:$B$716,2,0) -> 10450 | T11: =+R11*S11 -> 522.5 | V11: queso reggianito | W11: 0.015 | X11: =+VLOOKUP(V11,'PRECIO PROVEEDORES'!$A$2:$B$716,2,0) -> 17376 | Y11: =+W11*X11 -> 260.64 | AF11: comino | AG11: 0.002 | AH11: =+VLOOKUP(AF11,'PRECIO PROVEEDORES'!$A$2:$B$716,2,0) -> 10164 | AI11: =+AG11*AH11 -> 20.328
Q12: ciruela | R12: 0.05 | S12: =+VLOOKUP(Q12,'PRECIO PROVEEDORES'!$A$2:$B$716,2,0) -> 4860 | T12: =+R12*S12 -> 243 | V12: papas asadas | W12: 0.15 | X12: =+VLOOKUP(V12,'PRECIO PROVEEDORES'!$A$2:$B$716,2,0) -> 1685.0215 | Y12: =+W12*X12 -> 252.75322 | AF12: sal fina | AG12: 0.002 | AH12: =+VLOOKUP(AF12,'PRECIO PROVEEDORES'!$A$2:$B$716,2,0) -> 1633 | AI12: =+AG12*AH12 -> 3.266
V13: mayonesa de pimiento | W13: 0.04 | X13: =+VLOOKUP(V13,'PRECIO PROVEEDORES'!$A$2:$B$716,2,0) -> 3891.911 | Y13: =+W13*X13 -> 155.67644 | AF13: Pimienta negra en granos | AG13: 0.002 | AH13: =+VLOOKUP(AF13,'PRECIO PROVEEDORES'!$A$2:$B$716,2,0) -> 22269 | AI13: =+AG13*AH13 -> 44.538
AF14: papas asadas | AG14: 0.15 | AH14: =+VLOOKUP(AF14,'PRECIO PROVEEDORES'!$A$2:$B$716,2,0) -> 1685.0215 | AI14: =+AG14*AH14 -> 252.75322
AF15: mayonesa de pimiento | AG15: 0.04 | AH15: =+VLOOKUP(AF15,'PRECIO PROVEEDORES'!$A$2:$B$716,2,0) -> 3891.911 | AI15: =+AG15*AH15 -> 155.67644
B19: Costo Total de la materia prima | E19: =SUM(E4:E18) -> 3392.2659 | G19: Costo Total de la materia prima | J19: =SUM(J4:J18) -> 2344.257 | L19: Costo Total de la materia prima | O19: =SUM(O4:O18) -> 3161.6694 | Q19: Costo Total de la materia prima | T19: =SUM(T4:T18) -> 4236.203 | V19: Costo Total de la materia prima | Y19: =SUM(Y4:Y18) -> 3819.5397 | AA19: Costo Total de la materia prima | AD19: =SUM(AD4:AD18) -> 2405.91 | AF19: Costo Total de la materia prima | AI19: =SUM(AI4:AI18) -> 4336.3517
B20: Costo total de la preparación | E20: =SUM(E19) -> 3392.2659 | G20: Costo total de la preparación | J20: =SUM(J19) -> 2344.257 | L20: Costo total de la preparación | O20: =SUM(O19) -> 3161.6694 | Q20: Costo total de la preparación | T20: =SUM(T19) -> 4236.203 | V20: Costo total de la preparación | Y20: =SUM(Y19) -> 3819.5397 | AA20: Costo total de la preparación | AD20: =SUM(AD19) -> 2405.91 | AF20: Costo total de la preparación | AI20: =SUM(AI19) -> 4336.3517
B21: Costo porción | E21: =+E20 -> 3392.2659 | G21: Costo porción | J21: =+J20 -> 2344.257 | L21: Costo porción | O21: =+O20 -> 3161.6694 | Q21: Costo porción | T21: =+T20 -> 4236.203 | V21: Costo porción | Y21: =+Y20 -> 3819.5397 | AA21: Costo porción | AD21: =+AD20 -> 2405.91 | AF21: Costo porción | AI21: =+AI20 -> 4336.3517
B22: Porcentaje costo materia prima establecida | D22: 0.3 | G22: Porcentaje costo materia prima establecida | I22: 0.3 | L22: Porcentaje costo materia prima establecida | N22: 0.3 | Q22: Porcentaje costo materia prima establecida | S22: 0.3 | V22: Porcentaje costo materia prima establecida | X22: 0.3 | AA22: Porcentaje costo materia prima establecida | AC22: 0.3 | AF22: Porcentaje costo materia prima establecida | AH22: 0.3
B23: Precio potencial de venta | E23: =+E21*3.33333333333333 -> 11307.553 | G23: Precio potencial de venta | J23: =+J21*3.33333333333333 -> 7814.19 | L23: Precio potencial de venta | O23: =+O21*3.33333333333333 -> 10538.898 | Q23: Precio potencial de venta | T23: =+T21*3.33333333333333 -> 14120.677 | V23: Precio potencial de venta | Y23: =+Y21*3.33333333333333 -> 12731.799 | AA23: Precio potencial de venta | AD23: =+AD21*3.33333333333333 -> 8019.7 | AF23: Precio potencial de venta | AI23: =+AI21*3.33333333333333 -> 14454.506
B24: Precio de Venta | E24: 15000 | G24: Precio de Venta | J24: 15000 | L24: Precio de Venta | O24: 17000 | Q24: Precio de Venta | T24: 17500 | V24: Precio de Venta | Y24: 19000 | AA24: Precio de Venta | AD24: 14000 | AF24: Precio de Venta | AH24: 15000 | AI24: 17000
E25: =+E24-E23 -> 3692.4468 | J25: =+J24-J23 -> 7185.81 | O25: =+O24-O23 -> 6461.102 | T25: =+T24-T23 -> 3379.3233 | Y25: =+Y24-Y23 -> 6268.2011 | AD25: =+AD24-AD23 -> 5980.3 | AI25: =+AI24-AI23 -> 2545.4945
B26: Costo Real MP | E26: =E21/E24 -> 0.22615106 | G26: Costo Real MP | J26: =J21/J24 -> 0.1562838 | L26: Costo Real MP | O26: =O21/O24 -> 0.18598055 | Q26: Costo Real MP | T26: =T21/T24 -> 0.24206874 | V26: Costo Real MP | Y26: =Y21/Y24 -> 0.2010284 | AA26: Costo Real MP | AD26: =AD21/AD24 -> 0.17185071 | AF26: Costo Real MP | AI26: =AI21/AI24 -> 0.25507951
B29: TOSTON TUESTE | G29: TOSTON PALTA | L29: TOSTADO PAN CHIPA | Q29: TAPA DE ASADO | V29: SANDWICH BRIE | AA29: TOSTADO LOMITO Y CHEDAR | AF29: CHIPA CLASICO
C30: Kg/Lt/Uni | D30: $ | E30: Total $ | H30: Kg/Lt/Uni | I30: $ | J30: Total $ | M30: Kg/Lt/Uni | N30: $ | O30: Total $ | R30: Kg/Lt/Uni | S30: $ | T30: Total $ | W30: Kg/Lt/Uni | X30: $ | Y30: Total $ | AB30: Kg/Lt/Uni | AC30: $ | AD30: Total $ | AG30: Kg/Lt/Uni | AH30: $ | AI30: Total $
B31: rodaja pan masa madre | C31: 1 | D31: =+VLOOKUP(B31,'PRECIO PROVEEDORES'!$A$2:$B$716,2,0) -> 1252.8 | E31: =+C31*D31 -> 1252.8 | G31: rodaja pan masa madre | H31: 1 | I31: =+VLOOKUP(G31,'PRECIO PROVEEDORES'!$A$2:$B$716,2,0) -> 1252.8 | J31: =+H31*I31 -> 1252.8 | L31: pan de chipa | M31: 0.18 | N31: =+VLOOKUP(L31,'PRECIO PROVEEDORES'!$A$2:$B$716,2,0) -> 8843.4185 | O31: =+M31*N31 -> 1591.8153 | Q31: tapa de asado | R31: 0.15 | S31: =+VLOOKUP(Q31,'PRECIO PROVEEDORES'!$A$2:$B$716,2,0) -> 17289 | T31: =+R31*S31 -> 2593.35 | V31: pan ciabatta | W31: 1 | X31: =+VLOOKUP(V31,'PRECIO PROVEEDORES'!$A$2:$B$716,2,0) -> 168.4551 | Y31: =+W31*X31 -> 168.4551 | AA31: pan de papa | AB31: 1 | AC31: =+VLOOKUP(AA31,'PRECIO PROVEEDORES'!$A$2:$B$716,2,0) -> 675 | AD31: =+AB31*AC31 -> 675 | AF31: chipa clasico | AG31: 1 | AH31: =+VLOOKUP(AF31,'PRECIO PROVEEDORES'!$A$2:$B$716,2,0) -> 8843.4185 | AI31: =+AG31*AH31 -> 8843.4185
B32: Hoja amarga, Rucula selvatica | C32: 0.03 | D32: =+VLOOKUP(B32,'PRECIO PROVEEDORES'!$A$2:$B$716,2,0) -> 9900 | E32: =+C32*D32 -> 297 | G32: queso crema paulina | H32: 0.05 | I32: =+VLOOKUP(G32,'PRECIO PROVEEDORES'!$A$2:$B$716,2,0) -> 6000 | J32: =+H32*I32 -> 300 | L32: Fiambre, Jamon cocido | M32: 0.06 | N32: =+VLOOKUP(L32,'PRECIO PROVEEDORES'!$A$2:$B$716,2,0) -> 11881 | O32: =+M32*N32 -> 712.86 | Q32: pan pretzalej | R32: 1 | S32: =+VLOOKUP(Q32,'PRECIO PROVEEDORES'!$A$2:$B$716,2,0) -> 531 | T32: =+R32*S32 -> 531 | V32: Hoja amarga, Rucula selvatica | W32: 0.04 | X32: =+VLOOKUP(V32,'PRECIO PROVEEDORES'!$A$2:$B$716,2,0) -> 9900 | Y32: =+W32*X32 -> 396 | AA32: Cheddar feteado | AB32: 0.05 | AC32: =+VLOOKUP(AA32,'PRECIO PROVEEDORES'!$A$2:$B$716,2,0) -> 16343 | AD32: =+AB32*AC32 -> 817.15
B33: frutilla | C33: 0.04 | D33: =+VLOOKUP(B33,'PRECIO PROVEEDORES'!$A$2:$B$716,2,0) -> 26000 | E33: =+C33*D33 -> 1040 | G33: palta hass | H33: 0.08 | I33: =+VLOOKUP(G33,'PRECIO PROVEEDORES'!$A$2:$B$716,2,0) -> 9316 | J33: =+H33*I33 -> 745.28 | L33: queso danbo tregar | M33: 0.09 | N33: =+VLOOKUP(L33,'PRECIO PROVEEDORES'!$A$2:$B$716,2,0) -> 10697 | O33: =+M33*N33 -> 962.73 | Q33: barbacoa | R33: 0.03 | S33: =+VLOOKUP(Q33,'PRECIO PROVEEDORES'!$A$2:$B$716,2,0) -> 4800 | T33: =+R33*S33 -> 144 | V33: tomate seco | W33: 0.02 | X33: =+VLOOKUP(V33,'PRECIO PROVEEDORES'!$A$2:$B$716,2,0) -> 17587.35 | Y33: =+W33*X33 -> 351.747 | AA33: Fiambre, Lomito ahumado | AB33: 0.06 | AC33: =+VLOOKUP(AA33,'PRECIO PROVEEDORES'!$A$2:$B$716,2,0) -> 15813 | AD33: =+AB33*AC33 -> 948.78
B34: garrapiñada zapallo | C34: 0.015 | D34: =+VLOOKUP(B34,'PRECIO PROVEEDORES'!$A$2:$B$716,2,0) -> 16260 | E34: =+C34*D34 -> 243.9 | G34: Alcaparras | H34: 0.007 | I34: =+VLOOKUP(G34,'PRECIO PROVEEDORES'!$A$2:$B$716,2,0) -> 24435.611 | J34: =+H34*I34 -> 171.04928 | L34: pesto de tomate | M34: 0.025 | N34: =+VLOOKUP(L34,'PRECIO PROVEEDORES'!$A$2:$B$716,2,0) -> 37116.005 | O34: =+M34*N34 -> 927.90013 | Q34: cebollas encurtidas | R34: 0.01 | S34: =+VLOOKUP(Q34,'PRECIO PROVEEDORES'!$A$2:$B$716,2,0) -> 2381.6561 | T34: =+R34*S34 -> 23.816561 | V34: queso brie | W34: 0.08 | X34: =+VLOOKUP(V34,'PRECIO PROVEEDORES'!$A$2:$B$716,2,0) -> 20535 | Y34: =+W34*X34 -> 1642.8
B35: queso brie | C35: 0.04 | D35: =+VLOOKUP(B35,'PRECIO PROVEEDORES'!$A$2:$B$716,2,0) -> 20535 | E35: =+C35*D35 -> 821.4 | G35: Aceto balsamico reduccion | H35: 0.003 | I35: =+VLOOKUP(G35,'PRECIO PROVEEDORES'!$A$2:$B$716,2,0) -> 10601.56 | J35: =+H35*I35 -> 31.80468 | L35: pesto de albahaca | M35: 0.01 | N35: =+VLOOKUP(L35,'PRECIO PROVEEDORES'!$A$2:$B$716,2,0) -> 0 | O35: =+M35*N35 -> 0 | Q35: papas asadas | R35: 0.15 | S35: =+VLOOKUP(Q35,'PRECIO PROVEEDORES'!$A$2:$B$716,2,0) -> 1685.0215 | T35: =+R35*S35 -> 252.75322 | V35: mermelada de morron | W35: 0.03 | X35: =+VLOOKUP(V35,'PRECIO PROVEEDORES'!$A$2:$B$716,2,0) -> 4622.4709 | Y35: =+W35*X35 -> 138.67413
B36: miel alyser | C36: 0.01 | D36: =+VLOOKUP(B36,'PRECIO PROVEEDORES'!$A$2:$B$716,2,0) -> 5917 | E36: =+C36*D36 -> 59.17 | G36: Mix de semillas | H36: 0.003 | I36: =+VLOOKUP(G36,'PRECIO PROVEEDORES'!$A$2:$B$716,2,0) -> 5952.89 | J36: =+H36*I36 -> 17.85867 | Q36: mayonesa de pimiento | R36: 0.04 | S36: =+VLOOKUP(Q36,'PRECIO PROVEEDORES'!$A$2:$B$716,2,0) -> 3891.911 | T36: =+R36*S36 -> 155.67644 | V36: papas asadas | W36: 0.15 | X36: =+VLOOKUP(V36,'PRECIO PROVEEDORES'!$A$2:$B$716,2,0) -> 1685.0215 | Y36: =+W36*X36 -> 252.75322
G37: flores comestibles | H37: 0.001 | I37: =+VLOOKUP(G37,'PRECIO PROVEEDORES'!$A$2:$B$716,2,0) -> 5033.6 | J37: =+H37*I37 -> 5.0336 | V37: mayonesa de pimiento | W37: 0.04 | X37: =+VLOOKUP(V37,'PRECIO PROVEEDORES'!$A$2:$B$716,2,0) -> 3891.911 | Y37: =+W37*X37 -> 155.67644
B46: Costo Total de la materia prima | E46: =SUM(E31:E45) -> 3714.27 | G46: Costo Total de la materia prima | J46: =SUM(J31:J45) -> 2523.8262 | L46: Costo Total de la materia prima | O46: =SUM(O31:O45) -> 4195.3055 | Q46: Costo Total de la materia prima | T46: =SUM(T31:T45) -> 3700.5962 | V46: Costo Total de la materia prima | Y46: =SUM(Y31:Y45) -> 3106.1059 | AA46: Costo Total de la materia prima | AD46: =SUM(AD31:AD45) -> 2440.93 | AF46: Costo Total de la materia prima | AI46: =SUM(AI31:AI45) -> 8843.4185
B47: Costo total de la preparación | E47: =SUM(E46) -> 3714.27 | G47: Costo total de la preparación | J47: =SUM(J46) -> 2523.8262 | L47: Costo total de la preparación | O47: =SUM(O46) -> 4195.3055 | Q47: Costo total de la preparación | T47: =SUM(T46) -> 3700.5962 | V47: Costo total de la preparación | Y47: =SUM(Y46) -> 3106.1059 | AA47: Costo total de la preparación | AD47: =SUM(AD46) -> 2440.93 | AF47: Costo total de la preparación | AI47: =SUM(AI46) -> 8843.4185
B48: Costo porción | E48: =+E47 -> 3714.27 | G48: Costo porción | J48: =+J47 -> 2523.8262 | L48: Costo porción | O48: =+O47 -> 4195.3055 | Q48: Costo porción | T48: =+T47 -> 3700.5962 | V48: Costo porción | Y48: =+Y47 -> 3106.1059 | AA48: Costo porción | AD48: =+AD47 -> 2440.93 | AF48: Costo porción | AI48: =+AI47 -> 8843.4185
B49: Porcentaje costo materia prima establecida | D49: 0.3 | G49: Porcentaje costo materia prima establecida | I49: 0.3 | L49: Porcentaje costo materia prima establecida | N49: 0.3 | Q49: Porcentaje costo materia prima establecida | S49: 0.3 | V49: Porcentaje costo materia prima establecida | X49: 0.3 | AA49: Porcentaje costo materia prima establecida | AC49: 0.3 | AF49: Porcentaje costo materia prima establecida | AH49: 0.3
B50: Precio potencial de venta | E50: =+E48*3.33333333333333 -> 12380.9 | G50: Precio potencial de venta | J50: =+J48*3.33333333333333 -> 8412.7541 | L50: Precio potencial de venta | O50: =+O48*3.33333333333333 -> 13984.352 | Q50: Precio potencial de venta | T50: =+T48*3.33333333333333 -> 12335.321 | V50: Precio potencial de venta | Y50: =+Y48*3.33333333333333 -> 10353.686 | AA50: Precio potencial de venta | AD50: =+AD48*3.33333333333333 -> 8136.4333 | AF50: Precio potencial de venta | AI50: =+AI48*3.33333333333333 -> 29478.062
B51: Precio de Venta | E51: 16000 | G51: Precio de Venta | J51: 15000 | L51: Precio de Venta | O51: 17000 | Q51: Precio de Venta | T51: 18500 | V51: Precio de Venta | Y51: 16500 | AA51: Precio de Venta | AD51: 12500 | AF51: Precio de Venta | AI51: 4200
E52: =+E51-E50 -> 3619.1 | J52: =+J51-J50 -> 6587.2459 | O52: =+O51-O50 -> 3015.6485 | T52: =+T51-T50 -> 6164.6792 | Y52: =+Y51-Y50 -> 6146.3137 | AD52: =+AD51-AD50 -> 4363.5667 | AI52: =+AI51-AI50 -> -25278.062
B53: Costo Real MP | E53: =E48/E51 -> 0.23214188 | G53: Costo Real MP | J53: =J48/J51 -> 0.16825508 | L53: Costo Real MP | O53: =O48/O51 -> 0.24678267 | Q53: Costo Real MP | T53: =T48/T51 -> 0.20003223 | V53: Costo Real MP | Y53: =Y48/Y51 -> 0.18824884 | AA53: Costo Real MP | AD53: =AD48/AD51 -> 0.1952744 | AF53: Costo Real MP | AI53: =AI48/AI51 -> 2.1055758
B56: MEDIALUNA JAMON Y QUESO | G56: MEDIALUNA TOMATE Y QUESO | L56: CROISSANT DE PALTA | Q56: CROISSANT CRUDO | V56: ENSALADA CLASICA | AA56: BONDIOLA DE CANCHA | AF56: SANDWICH CLASICO CRUDO
C57: Kg/Lt/Uni | D57: $ | E57: Total $ | H57: Kg/Lt/Uni | I57: $ | J57: Total $ | M57: Kg/Lt/Uni | N57: $ | O57: Total $ | R57: Kg/Lt/Uni | S57: $ | T57: Total $ | W57: Kg/Lt/Uni | X57: $ | Y57: Total $ | AB57: Kg/Lt/Uni | AC57: $ | AD57: Total $ | AG57: Kg/Lt/Uni | AH57: $ | AI57: Total $
B58: medialuna 90 gramos | C58: 1 | D58: =+VLOOKUP(B58,'PRECIO PROVEEDORES'!$A$2:$B$716,2,0) -> 1350 | E58: =+C58*D58 -> 1350 | G58: medialuna 90 gramos | H58: 1 | I58: =+VLOOKUP(G58,'PRECIO PROVEEDORES'!$A$2:$B$716,2,0) -> 1350 | J58: =+H58*I58 -> 1350 | L58: croissant 145 gramos | M58: 1 | N58: =+VLOOKUP(L58,'PRECIO PROVEEDORES'!$A$2:$B$716,2,0) -> 1307 | O58: =+M58*N58 -> 1307 | Q58: croissant 145 gramos | R58: 1 | S58: =+VLOOKUP(Q58,'PRECIO PROVEEDORES'!$A$2:$B$716,2,0) -> 1307 | T58: =+R58*S58 -> 1307 | V58: Lechuga, francesa | W58: 0.04 | X58: =+VLOOKUP(V58,'PRECIO PROVEEDORES'!$A$2:$B$716,2,0) -> 6440 | Y58: =+W58*X58 -> 257.6 | AA58: bondiola braseada | AB58: 0.15 | AC58: =+VLOOKUP(AA58,'PRECIO PROVEEDORES'!$A$2:$B$716,2,0) -> 7748.899 | AD58: =+AB58*AC58 -> 1162.3348 | AF58: baguetin rustico | AG58: 1 | AH58: =+VLOOKUP(AF58,'PRECIO PROVEEDORES'!$A$2:$B$716,2,0) -> 1574 | AI58: =+AG58*AH58 -> 1574
B59: Fiambre, Jamon cocido | C59: 0.025 | D59: =+VLOOKUP(B59,'PRECIO PROVEEDORES'!$A$2:$B$716,2,0) -> 11881 | E59: =+C59*D59 -> 297.025 | G59: tomate redondo | H59: 0.035 | I59: =+VLOOKUP(G59,'PRECIO PROVEEDORES'!$A$2:$B$716,2,0) -> 1800 | J59: =+H59*I59 -> 63 | L59: palta hass | M59: 0.08 | N59: =+VLOOKUP(L59,'PRECIO PROVEEDORES'!$A$2:$B$716,2,0) -> 9316 | O59: =+M59*N59 -> 745.28 | Q59: Hoja amarga, Rucula selvatica | R59: 0.03 | S59: =+VLOOKUP(Q59,'PRECIO PROVEEDORES'!$A$2:$B$716,2,0) -> 9900 | T59: =+R59*S59 -> 297 | V59: Hoja amarga, Rucula selvatica | W59: 0.03 | X59: =+VLOOKUP(V59,'PRECIO PROVEEDORES'!$A$2:$B$716,2,0) -> 9900 | Y59: =+W59*X59 -> 297 | AA59: Huevos | AB59: 2 | AC59: =+VLOOKUP(AA59,'PRECIO PROVEEDORES'!$A$2:$B$716,2,0) -> 192 | AD59: =+AB59*AC59 -> 384 | AF59: Fiambre, Jamon crudo | AG59: 0.08 | AH59: =+VLOOKUP(AF59,'PRECIO PROVEEDORES'!$A$2:$B$716,2,0) -> 20000 | AI59: =+AG59*AH59 -> 1600
B60: queso danbo tregar | C60: 0.03 | D60: =+VLOOKUP(B60,'PRECIO PROVEEDORES'!$A$2:$B$716,2,0) -> 10697 | E60: =+C60*D60 -> 320.91 | G60: queso danbo tregar | H60: 0.03 | I60: =+VLOOKUP(G60,'PRECIO PROVEEDORES'!$A$2:$B$716,2,0) -> 10697 | J60: =+H60*I60 -> 320.91 | L60: queso crema paulina | M60: 0.02 | N60: =+VLOOKUP(L60,'PRECIO PROVEEDORES'!$A$2:$B$716,2,0) -> 6000 | O60: =+M60*N60 -> 120 | Q60: Fiambre, Jamon crudo | R60: 0.045 | S60: =+VLOOKUP(Q60,'PRECIO PROVEEDORES'!$A$2:$B$716,2,0) -> 20000 | T60: =+R60*S60 -> 900 | V60: frutos secos | W60: 0.03 | X60: =+VLOOKUP(V60,'PRECIO PROVEEDORES'!$A$2:$B$716,2,0) -> 19455.208 | Y60: =+W60*X60 -> 583.65625 | AA60: cebolla caramelizada | AB60: 0.03 | AC60: =+VLOOKUP(AA60,'PRECIO PROVEEDORES'!$A$2:$B$716,2,0) -> 1690.495 | AD60: =+AB60*AC60 -> 50.71485 | AF60: queso danbo tregar | AG60: 0.08 | AH60: =+VLOOKUP(AF60,'PRECIO PROVEEDORES'!$A$2:$B$716,2,0) -> 10697 | AI60: =+AG60*AH60 -> 855.76
L61: alcaparras | M61: 0.007 | N61: =+VLOOKUP(L61,'PRECIO PROVEEDORES'!$A$2:$B$716,2,0) -> 24435.611 | O61: =+M61*N61 -> 171.04928 | Q61: queso brie | R61: 0.05 | S61: =+VLOOKUP(Q61,'PRECIO PROVEEDORES'!$A$2:$B$716,2,0) -> 20535 | T61: =+R61*S61 -> 1026.75 | V61: cherrys confitados | W61: 0.05 | X61: =+VLOOKUP(V61,'PRECIO PROVEEDORES'!$A$2:$B$716,2,0) -> 6130.5564 | Y61: =+W61*X61 -> 306.52782 | AA61: pan ciabatta | AB61: 1 | AC61: =+VLOOKUP(AA61,'PRECIO PROVEEDORES'!$A$2:$B$716,2,0) -> 168.4551 | AD61: =+AB61*AC61 -> 168.4551 | AF61: tomate seco | AG61: 0.02 | AH61: =+VLOOKUP(AF61,'PRECIO PROVEEDORES'!$A$2:$B$716,2,0) -> 17587.35 | AI61: =+AG61*AH61 -> 351.747
Q62: tomate seco | R62: 0.02 | S62: =+VLOOKUP(Q62,'PRECIO PROVEEDORES'!$A$2:$B$716,2,0) -> 17587.35 | T62: =+R62*S62 -> 351.747 | V62: palta hass | W62: 0.04 | X62: =+VLOOKUP(V62,'PRECIO PROVEEDORES'!$A$2:$B$716,2,0) -> 9316 | Y62: =+W62*X62 -> 372.64 | AA62: Fiambre, Panceta ahumada | AB62: 0.01 | AC62: =+VLOOKUP(AA62,'PRECIO PROVEEDORES'!$A$2:$B$716,2,0) -> 18256.35 | AD62: =+AB62*AC62 -> 182.5635 | AF62: manteca tueste alyser | AG62: 0.01 | AH62: =+VLOOKUP(AF62,'PRECIO PROVEEDORES'!$A$2:$B$716,2,0) -> 12206 | AI62: =+AG62*AH62 -> 122.06
Q63: aceto balsamico reduccion | R63: 0.005 | S63: =+VLOOKUP(Q63,'PRECIO PROVEEDORES'!$A$2:$B$716,2,0) -> 10601.56 | T63: =+R63*S63 -> 53.0078 | V63: mix de vegetales asados | W63: 0.035 | X63: =+VLOOKUP(V63,'PRECIO PROVEEDORES'!$A$2:$B$716,2,0) -> 2972.2273 | Y63: =+W63*X63 -> 104.02795 | AA63: papas asadas | AB63: 0.15 | AC63: =+VLOOKUP(AA63,'PRECIO PROVEEDORES'!$A$2:$B$716,2,0) -> 1685.0215 | AD63: =+AB63*AC63 -> 252.75322 | AF63: papas asadas | AG63: 0.15 | AH63: =+VLOOKUP(AF63,'PRECIO PROVEEDORES'!$A$2:$B$716,2,0) -> 1685.0215 | AI63: =+AG63*AH63 -> 252.75322
V64: pollo | W64: 0.15 | X64: =+VLOOKUP(V64,'PRECIO PROVEEDORES'!$A$2:$B$716,2,0) -> 7700 | Y64: =+W64*X64 -> 1155 | AA64: mayonesa de pimiento | AB64: 0.04 | AC64: =+VLOOKUP(AA64,'PRECIO PROVEEDORES'!$A$2:$B$716,2,0) -> 3891.911 | AD64: =+AB64*AC64 -> 155.67644 | AF64: mayonesa de pimiento | AG64: 0.04 | AH64: =+VLOOKUP(AF64,'PRECIO PROVEEDORES'!$A$2:$B$716,2,0) -> 3891.911 | AI64: =+AG64*AH64 -> 155.67644
B73: Costo Total de la materia prima | E73: =SUM(E58:E72) -> 1967.935 | G73: Costo Total de la materia prima | J73: =SUM(J58:J72) -> 1733.91 | L73: Costo Total de la materia prima | O73: =SUM(O58:O72) -> 2343.3293 | Q73: Costo Total de la materia prima | T73: =SUM(T58:T72) -> 3935.5048 | V73: Costo Total de la materia prima | Y73: =SUM(Y58:Y72) -> 3076.452 | AA73: Costo Total de la materia prima | AD73: =SUM(AD58:AD72) -> 2356.498 | AF73: Costo Total de la materia prima | AI73: =SUM(AI58:AI72) -> 4911.9967
B74: Costo total de la preparación | E74: =SUM(E73) -> 1967.935 | G74: Costo total de la preparación | J74: =SUM(J73) -> 1733.91 | L74: Costo total de la preparación | O74: =SUM(O73) -> 2343.3293 | Q74: Costo total de la preparación | T74: =SUM(T73) -> 3935.5048 | V74: Costo total de la preparación | Y74: =SUM(Y73) -> 3076.452 | AA74: Costo total de la preparación | AD74: =SUM(AD73) -> 2356.498 | AF74: Costo total de la preparación | AI74: =SUM(AI73) -> 4911.9967
B75: Costo porción | E75: =+E74 -> 1967.935 | G75: Costo porción | J75: =+J74 -> 1733.91 | L75: Costo porción | O75: =+O74 -> 2343.3293 | Q75: Costo porción | T75: =+T74 -> 3935.5048 | V75: Costo porción | Y75: =+Y74 -> 3076.452 | AA75: Costo porción | AD75: =+AD74 -> 2356.498 | AF75: Costo porción | AI75: =+AI74 -> 4911.9967
B76: Porcentaje costo materia prima establecida | D76: 0.3 | G76: Porcentaje costo materia prima establecida | I76: 0.3 | L76: Porcentaje costo materia prima establecida | N76: 0.3 | Q76: Porcentaje costo materia prima establecida | S76: 0.3 | V76: Porcentaje costo materia prima establecida | X76: 0.3 | AA76: Porcentaje costo materia prima establecida | AC76: 0.3 | AF76: Porcentaje costo materia prima establecida | AH76: 0.3
B77: Precio potencial de venta | E77: =+E75*3.33333333333333 -> 6559.7833 | G77: Precio potencial de venta | J77: =+J75*3.33333333333333 -> 5779.7 | L77: Precio potencial de venta | O77: =+O75*3.33333333333333 -> 7811.0976 | Q77: Precio potencial de venta | T77: =+T75*3.33333333333333 -> 13118.349 | V77: Precio potencial de venta | Y77: =+Y75*3.33333333333333 -> 10254.84 | AA77: Precio potencial de venta | AD77: =+AD75*3.33333333333333 -> 7854.9932 | AF77: Precio potencial de venta | AI77: =+AI75*3.33333333333333 -> 16373.322
B78: Precio de Venta | E78: 9000 | G78: Precio de Venta | J78: 9000 | L78: Precio de Venta | O78: 12000 | Q78: Precio de Venta | T78: 16000 | V78: Precio de Venta | Y78: 14000 | AA78: Precio de Venta | AD78: 15500 | AF78: Precio de Venta | AI78: 20000
E79: =+E78-E77 -> 2440.2167 | J79: =+J78-J77 -> 3220.3 | O79: =+O78-O77 -> 4188.9024 | T79: =+T78-T77 -> 2881.6507 | Y79: =+Y78-Y77 -> 3745.1599 | AD79: =+AD78-AD77 -> 7645.0068 | AI79: =+AI78-AI77 -> 3626.6778
B80: Costo Real MP | E80: =E75/E78 -> 0.21865944 | G80: Costo Real MP | J80: =J75/J78 -> 0.19265667 | L80: Costo Real MP | O80: =O75/O78 -> 0.19527744 | Q80: Costo Real MP | T80: =T75/T78 -> 0.24596905 | V80: Costo Real MP | Y80: =Y75/Y78 -> 0.21974657 | AA80: Costo Real MP | AD80: =AD75/AD78 -> 0.15203213 | AF80: Costo Real MP | AI80: =AI75/AI78 -> 0.24559983
B83: PLATO DE FRUTAS | G83: TOSTADAS | L83: ACAI | Q83: CROISSANT J Y Q | V83: CROISSANT TOMATE Y QUESO | AA83: TOSTON DE HONGOS | AF83: GRANOLA 300 GRS
C84: Kg/Lt/Uni | D84: $ | E84: Total $ | H84: Kg/Lt/Uni | I84: $ | J84: Total $ | M84: Kg/Lt/Uni | N84: $ | O84: Total $ | R84: Kg/Lt/Uni | S84: $ | T84: Total $ | W84: Kg/Lt/Uni | X84: $ | Y84: Total $ | AB84: Kg/Lt/Uni | AC84: $ | AD84: Total $ | AG84: Kg/Lt/Uni | AH84: $ | AI84: Total $
B85: banana | C85: 0.1 | D85: =+VLOOKUP(B85,'PRECIO PROVEEDORES'!$A$2:$B$716,2,0) -> 3360 | E85: =+C85*D85 -> 336 | G85: brioche molde para tostadas | H85: 1 | I85: =+VLOOKUP(G85,'PRECIO PROVEEDORES'!$A$2:$B$716,2,0) -> 1100 | J85: =+H85*I85 -> 1100 | L85: acai | M85: 0.15 | N85: =+VLOOKUP(L85,'PRECIO PROVEEDORES'!$A$2:$B$716,2,0) -> 15760 | O85: =+M85*N85 -> 2364 | Q85: croissant 145 gramos | R85: 1 | S85: =+VLOOKUP(Q85,'PRECIO PROVEEDORES'!$A$2:$B$716,2,0) -> 1307 | T85: =+R85*S85 -> 1307 | V85: croissant 145 gramos | W85: 1 | X85: =+VLOOKUP(V85,'PRECIO PROVEEDORES'!$A$2:$B$716,2,0) -> 1307 | Y85: =+W85*X85 -> 1307 | AA85: rodaja pan masa madre | AB85: 1 | AC85: =+VLOOKUP(AA85,'PRECIO PROVEEDORES'!$A$2:$B$716,2,0) -> 1252.8 | AD85: =+AB85*AC85 -> 1252.8 | AF85: granola | AG85: 0.3 | AH85: =+VLOOKUP(AF85,'PRECIO PROVEEDORES'!$A$2:$B$716,2,0) -> 8954.3189 | AI85: =+AG85*AH85 -> 2686.2957
B86: kiwi | C86: 0.05 | D86: =+VLOOKUP(B86,'PRECIO PROVEEDORES'!$A$2:$B$716,2,0) -> 10450 | E86: =+C86*D86 -> 522.5 | G86: tostada en pan de campo xl | H86: 1 | I86: =+VLOOKUP(G86,'PRECIO PROVEEDORES'!$A$2:$B$716,2,0) -> 243.1 | J86: =+H86*I86 -> 243.1 | L86: granola | M86: 0.05 | N86: =+VLOOKUP(L86,'PRECIO PROVEEDORES'!$A$2:$B$716,2,0) -> 8954.3189 | O86: =+M86*N86 -> 447.71595 | Q86: Fiambre, Jamon cocido | R86: 0.08 | S86: =+VLOOKUP(Q86,'PRECIO PROVEEDORES'!$A$2:$B$716,2,0) -> 11881 | T86: =+R86*S86 -> 950.48 | V86: queso danbo tregar | W86: 0.08 | X86: =+VLOOKUP(V86,'PRECIO PROVEEDORES'!$A$2:$B$716,2,0) -> 10697 | Y86: =+W86*X86 -> 855.76 | AA86: Hongo, pino | AB86: 0.02 | AC86: =+VLOOKUP(AA86,'PRECIO PROVEEDORES'!$A$2:$B$716,2,0) -> 28695 | AD86: =+AB86*AC86 -> 573.9
B87: frutilla | C87: 0.05 | D87: =+VLOOKUP(B87,'PRECIO PROVEEDORES'!$A$2:$B$716,2,0) -> 26000 | E87: =+C87*D87 -> 1300 | G87: rodaja pan masa madre | H87: 1 | I87: =+VLOOKUP(G87,'PRECIO PROVEEDORES'!$A$2:$B$716,2,0) -> 1252.8 | J87: =+H87*I87 -> 1252.8 | L87: banana | M87: 0.05 | N87: =+VLOOKUP(L87,'PRECIO PROVEEDORES'!$A$2:$B$716,2,0) -> 3360 | O87: =+M87*N87 -> 168 | Q87: queso danbo tregar | R87: 0.08 | S87: =+VLOOKUP(Q87,'PRECIO PROVEEDORES'!$A$2:$B$716,2,0) -> 10697 | T87: =+R87*S87 -> 855.76 | V87: tomate redondo | W87: 0.06 | X87: =+VLOOKUP(V87,'PRECIO PROVEEDORES'!$A$2:$B$716,2,0) -> 1800 | Y87: =+W87*X87 -> 108 | AA87: aceite de girasol | AB87: 0.06 | AC87: =+VLOOKUP(AA87,'PRECIO PROVEEDORES'!$A$2:$B$716,2,0) -> 4299.01 | AD87: =+AB87*AC87 -> 257.9406
B88: uva | C88: 0.02 | D88: =+VLOOKUP(B88,'PRECIO PROVEEDORES'!$A$2:$B$716,2,0) -> 2332 | E88: =+C88*D88 -> 46.64 | G88: mermelada | H88: 0.04 | I88: =+VLOOKUP(G88,'PRECIO PROVEEDORES'!$A$2:$B$716,2,0) -> 14000 | J88: =+H88*I88 -> 560 | L88: frutilla | M88: 0.04 | N88: =+VLOOKUP(L88,'PRECIO PROVEEDORES'!$A$2:$B$716,2,0) -> 26000 | O88: =+M88*N88 -> 1040 | AA88: Hongo, Portobello | AB88: 0.04 | AC88: =+VLOOKUP(AA88,'PRECIO PROVEEDORES'!$A$2:$B$716,2,0) -> 26900 | AD88: =+AB88*AC88 -> 1076
B89: miel alyser | C89: 0.015 | D89: =+VLOOKUP(B89,'PRECIO PROVEEDORES'!$A$2:$B$716,2,0) -> 5917 | E89: =+C89*D89 -> 88.755 | G89: queso crema paulina | H89: 0.04 | I89: =+VLOOKUP(G89,'PRECIO PROVEEDORES'!$A$2:$B$716,2,0) -> 6000 | J89: =+H89*I89 -> 240 | L89: miel alyser | M89: 0.01 | N89: =+VLOOKUP(L89,'PRECIO PROVEEDORES'!$A$2:$B$716,2,0) -> 5917 | O89: =+M89*N89 -> 59.17 | AA89: cherrys confitados | AB89: 0.05 | AC89: =+VLOOKUP(AA89,'PRECIO PROVEEDORES'!$A$2:$B$716,2,0) -> 6130.5564 | AD89: =+AB89*AC89 -> 306.52782
B90: frutos secos | C90: 0.03 | D90: =+VLOOKUP(B90,'PRECIO PROVEEDORES'!$A$2:$B$716,2,0) -> 19455.208 | E90: =+C90*D90 -> 583.65625 | AA90: garrapiñada zapallo | AB90: 0.015 | AC90: =+VLOOKUP(AA90,'PRECIO PROVEEDORES'!$A$2:$B$716,2,0) -> 16260 | AD90: =+AB90*AC90 -> 243.9
B91: pasta de mani | C91: 0.03 | D91: =+VLOOKUP(B91,'PRECIO PROVEEDORES'!$A$2:$B$716,2,0) -> 5595 | E91: =+C91*D91 -> 167.85 | AA91: Hierbas frescas, Albahaca | AB91: 0.1 | AC91: =+VLOOKUP(AA91,'PRECIO PROVEEDORES'!$A$2:$B$716,2,0) -> 4160 | AD91: =+AB91*AC91 -> 416
B92: pomelo rosado | C92: 0.05 | D92: =+VLOOKUP(B92,'PRECIO PROVEEDORES'!$A$2:$B$716,2,0) -> 2185 | E92: =+C92*D92 -> 109.25
B100: Costo Total de la materia prima | E100: =SUM(E85:E99) -> 3154.6512 | G100: Costo Total de la materia prima | J100: =SUM(J85:J99) -> 3395.9 | L100: Costo Total de la materia prima | O100: =SUM(O85:O99) -> 4078.8859 | Q100: Costo Total de la materia prima | T100: =SUM(T85:T99) -> 3113.24 | V100: Costo Total de la materia prima | Y100: =SUM(Y85:Y99) -> 2270.76 | AA100: Costo Total de la materia prima | AD100: =SUM(AD85:AD99) -> 4127.0684 | AF100: Costo Total de la materia prima | AI100: =SUM(AI85:AI99) -> 2686.2957
B101: Costo total de la preparación | E101: =SUM(E100) -> 3154.6512 | G101: Costo total de la preparación | J101: =SUM(J100) -> 3395.9 | L101: Costo total de la preparación | O101: =SUM(O100) -> 4078.8859 | Q101: Costo total de la preparación | T101: =SUM(T100) -> 3113.24 | V101: Costo total de la preparación | Y101: =SUM(Y100) -> 2270.76 | AA101: Costo total de la preparación | AD101: =SUM(AD100) -> 4127.0684 | AF101: Costo total de la preparación | AI101: =SUM(AI100) -> 2686.2957
B102: Costo porción | E102: =+E101 -> 3154.6512 | G102: Costo porción | J102: =+J101 -> 3395.9 | L102: Costo porción | O102: =+O101 -> 4078.8859 | Q102: Costo porción | T102: =+T101 -> 3113.24 | V102: Costo porción | Y102: =+Y101 -> 2270.76 | AA102: Costo porción | AD102: =+AD101 -> 4127.0684 | AF102: Costo porción | AI102: =+AI101 -> 2686.2957
B103: Porcentaje costo materia prima establecida | D103: 0.3 | G103: Porcentaje costo materia prima establecida | I103: 0.3 | L103: Porcentaje costo materia prima establecida | N103: 0.3 | Q103: Porcentaje costo materia prima establecida | S103: 0.3 | V103: Porcentaje costo materia prima establecida | X103: 0.3 | AA103: Porcentaje costo materia prima establecida | AC103: 0.3 | AF103: Porcentaje costo materia prima establecida | AH103: 0.3
B104: Precio potencial de venta | E104: =+E102*3.33333333333333 -> 10515.504 | G104: Precio potencial de venta | J104: =+J102*3.33333333333333 -> 11319.667 | L104: Precio potencial de venta | O104: =+O102*3.33333333333333 -> 13596.286 | Q104: Precio potencial de venta | T104: =+T102*3.33333333333333 -> 10377.467 | V104: Precio potencial de venta | Y104: =+Y102*3.33333333333333 -> 7569.2 | AA104: Precio potencial de venta | AD104: =+AD102*3.33333333333333 -> 13756.895 | AF104: Precio potencial de venta | AI104: =+AI102*3.33333333333333 -> 8954.3189
B105: Precio de Venta | E105: 13000 | G105: Precio de Venta | J105: 12500 | L105: Precio de Venta | O105: 17500 | Q105: Precio de Venta | T105: 13000 | V105: Precio de Venta | Y105: 13000 | AA105: Precio de Venta | AD105: 16500 | AF105: Precio de Venta | AI105: 10000
E106: =+E105-E104 -> 2484.4958 | J106: =+J105-J104 -> 1180.3333 | O106: =+O105-O104 -> 3903.7135 | T106: =+T105-T104 -> 2622.5333 | Y106: =+Y105-Y104 -> 5430.8 | AD106: =+AD105-AD104 -> 2743.1053 | AI106: =+AI105-AI104 -> 1045.6811
B107: Costo Real MP | E107: =E102/E105 -> 0.24266548 | G107: Costo Real MP | J107: =J102/J105 -> 0.271672 | L107: Costo Real MP | O107: =O102/O105 -> 0.2330792 | Q107: Costo Real MP | T107: =T102/T105 -> 0.23948 | V107: Costo Real MP | Y107: =Y102/Y105 -> 0.17467385 | AA107: Costo Real MP | AD107: =AD102/AD105 -> 0.25012536 | AF107: Costo Real MP | AI107: =AI102/AI105 -> 0.26862957
B110: PROMO EJECUTIVA | G110: PAN CHIPA MAYORISTA | L110: FOSFORITO JYQ | Q110: FOSFORITO CAPRESE | V110: SANDWICH ALBONDIGA NUEVO | AA110: WRAP DE POLLO | AF110: SANDWICH DE ATUN
C111: Kg/Lt/Uni | D111: $ | E111: Total $ | H111: Kg/Lt/Uni | I111: $ | J111: Total $ | M111: Kg/Lt/Uni | N111: $ | O111: Total $ | R111: Kg/Lt/Uni | S111: $ | T111: Total $ | W111: Kg/Lt/Uni | X111: $ | Y111: Total $ | AB111: Kg/Lt/Uni | AC111: $ | AD111: Total $ | AG111: Kg/Lt/Uni | AH111: $ | AI111: Total $
B112: sandwich tapa de asado | C112: 1 | D112: =+VLOOKUP(B112,'PRECIO PROVEEDORES'!$A$2:$B$716,2,0) -> 3700.5962 | E112: =+C112*D112 -> 3700.5962 | G112: pan de chipa | H112: 0.18 | I112: =+VLOOKUP(G112,'PRECIO PROVEEDORES'!$A$2:$B$716,2,0) -> 8843.4185 | J112: =+H112*I112 -> 1591.8153 | L112: fosforito | M112: 1 | N112: =+VLOOKUP(L112,'PRECIO PROVEEDORES'!$A$2:$B$716,2,0) -> 447.7276 | O112: =+M112*N112 -> 447.7276 | Q112: fosforito | R112: 1 | S112: =+VLOOKUP(Q112,'PRECIO PROVEEDORES'!$A$2:$B$716,2,0) -> 447.7276 | T112: =+R112*S112 -> 447.7276 | V112: albondigas | W112: 0.14 | X112: =+VLOOKUP(V112,'PRECIO PROVEEDORES'!$A$2:$B$716,2,0) -> 15378.581 | Y112: =+W112*X112 -> 2153.0013 | AA112: pollo | AB112: 0.15 | AC112: =+VLOOKUP(AA112,'PRECIO PROVEEDORES'!$A$2:$B$716,2,0) -> 7700 | AD112: =+AB112*AC112 -> 1155 | AF112: brioche molde para tostadas | AG112: 2 | AH112: =+VLOOKUP(AF112,'PRECIO PROVEEDORES'!$A$2:$B$716,2,0) -> 1100 | AI112: =+AG112*AH112 -> 2200
B113: cortado tueste | C113: 1 | D113: =+VLOOKUP(B113,'PRECIO PROVEEDORES'!$A$2:$B$716,2,0) -> 664.93 | E113: =+C113*D113 -> 664.93 | L113: queso danbo tregar | M113: 0.07 | N113: =+VLOOKUP(L113,'PRECIO PROVEEDORES'!$A$2:$B$716,2,0) -> 10697 | O113: =+M113*N113 -> 748.79 | Q113: queso danbo tregar | R113: 0.07 | S113: =+VLOOKUP(Q113,'PRECIO PROVEEDORES'!$A$2:$B$716,2,0) -> 10697 | T113: =+R113*S113 -> 748.79 | V113: queso Reggianito | W113: 0.1 | X113: =+VLOOKUP(V113,'PRECIO PROVEEDORES'!$A$2:$B$716,2,0) -> 17376 | Y113: =+W113*X113 -> 1737.6 | AA113: Repollo blanco | AB113: 0.05 | AC113: =+VLOOKUP(AA113,'PRECIO PROVEEDORES'!$A$2:$B$716,2,0) -> 2025 | AD113: =+AB113*AC113 -> 101.25 | AF113: relleno sandwich de atun | AG113: 0.31 | AH113: =+VLOOKUP(AF113,'PRECIO PROVEEDORES'!$A$2:$B$716,2,0) -> 11952.355 | AI113: =+AG113*AH113 -> 3705.23
B114: medialuna 90 gramos | E114: =+C114*D114 -> 0 | F114: no tomar de ref | L114: Fiambre, Jamon cocido | M114: 0.07 | N114: =+VLOOKUP(L114,'PRECIO PROVEEDORES'!$A$2:$B$716,2,0) -> 11881 | O114: =+M114*N114 -> 831.67 | Q114: Hierbas frescas, Albahaca | R114: 0.02 | S114: =+VLOOKUP(Q114,'PRECIO PROVEEDORES'!$A$2:$B$716,2,0) -> 4160 | T114: =+R114*S114 -> 83.2 | V114: salsa tomate albondigas | W114: 0.15 | X114: =+VLOOKUP(V114,'PRECIO PROVEEDORES'!$A$2:$B$716,2,0) -> 2112.0856 | Y114: =+W114*X114 -> 316.81284 | AA114: Repollo rojo | AB114: 0.05 | AC114: =+VLOOKUP(AA114,'PRECIO PROVEEDORES'!$A$2:$B$716,2,0) -> 2700 | AD114: =+AB114*AC114 -> 135 | AF114: Hoja amarga, Rucula selvatica | AG114: 0.03 | AH114: =+VLOOKUP(AF114,'PRECIO PROVEEDORES'!$A$2:$B$716,2,0) -> 9900 | AI114: =+AG114*AH114 -> 297
B115: limonada | C115: 1 | D115: =+VLOOKUP(B115,'PRECIO PROVEEDORES'!$A$2:$B$716,2,0) -> 861.152 | E115: =+C115*D115 -> 861.152 | Q115: tomate redondo | R115: 0.04 | S115: =+VLOOKUP(Q115,'PRECIO PROVEEDORES'!$A$2:$B$716,2,0) -> 1800 | T115: =+R115*S115 -> 72 | V115: baguetin de leche | W115: 1 | X115: =+VLOOKUP(V115,'PRECIO PROVEEDORES'!$A$2:$B$716,2,0) -> 1574 | Y115: =+W115*X115 -> 1574 | AA115: Hoja amarga, Rucula selvatica | AB115: 0.03 | AC115: =+VLOOKUP(AA115,'PRECIO PROVEEDORES'!$A$2:$B$716,2,0) -> 9900 | AD115: =+AB115*AC115 -> 297 | AF115: papas asadas | AG115: 0.15 | AH115: =+VLOOKUP(AF115,'PRECIO PROVEEDORES'!$A$2:$B$716,2,0) -> 1685.0215 | AI115: =+AG115*AH115 -> 252.75322
V116: papas asadas | W116: 0.15 | X116: =+VLOOKUP(V116,'PRECIO PROVEEDORES'!$A$2:$B$716,2,0) -> 1685.0215 | Y116: =+W116*X116 -> 252.75322 | AA116: yogurt griego | AB116: 0.08 | AC116: =+VLOOKUP(AA116,'PRECIO PROVEEDORES'!$A$2:$B$716,2,0) -> 7449.2 | AD116: =+AB116*AC116 -> 595.936 | AF116: mayonesa de pimiento | AG116: 0.04 | AH116: =+VLOOKUP(AF116,'PRECIO PROVEEDORES'!$A$2:$B$716,2,0) -> 3891.911 | AI116: =+AG116*AH116 -> 155.67644
V117: mayonesa de pimiento | W117: 0.04 | X117: =+VLOOKUP(V117,'PRECIO PROVEEDORES'!$A$2:$B$716,2,0) -> 3891.911 | Y117: =+W117*X117 -> 155.67644 | AA117: queso Reggianito | AB117: 0.1 | AC117: =+VLOOKUP(AA117,'PRECIO PROVEEDORES'!$A$2:$B$716,2,0) -> 17376 | AD117: =+AB117*AC117 -> 1737.6
AA118: wrap | AB118: 1 | AC118: =+VLOOKUP(AA118,'PRECIO PROVEEDORES'!$A$2:$B$716,2,0) -> 253 | AD118: =+AB118*AC118 -> 253
AA119: papas asadas | AB119: 0.15 | AC119: =+VLOOKUP(AA119,'PRECIO PROVEEDORES'!$A$2:$B$716,2,0) -> 1685.0215 | AD119: =+AB119*AC119 -> 252.75322
AA120: mayonesa de pimiento | AB120: 0.04 | AC120: =+VLOOKUP(AA120,'PRECIO PROVEEDORES'!$A$2:$B$716,2,0) -> 3891.911 | AD120: =+AB120*AC120 -> 155.67644
B127: Costo Total de la materia prima | E127: =SUM(E112:E126) -> 5226.6782 | G127: Costo Total de la materia prima | J127: =SUM(J112:J126) -> 1591.8153 | L127: Costo Total de la materia prima | O127: =SUM(O112:O126) -> 2028.1876 | Q127: Costo Total de la materia prima | T127: =SUM(T112:T126) -> 1351.7176 | V127: Costo Total de la materia prima | Y127: =SUM(Y112:Y126) -> 6189.8438 | AA127: Costo Total de la materia prima | AD127: =SUM(AD112:AD126) -> 4683.2157 | AF127: Costo Total de la materia prima | AI127: =SUM(AI112:AI126) -> 6610.6597
B128: Costo total de la preparación | E128: =SUM(E127) -> 5226.6782 | G128: Costo total de la preparación | J128: =SUM(J127) -> 1591.8153 | L128: Costo total de la preparación | O128: =SUM(O127) -> 2028.1876 | Q128: Costo total de la preparación | T128: =SUM(T127) -> 1351.7176 | V128: Costo total de la preparación | Y128: =SUM(Y127) -> 6189.8438 | AA128: Costo total de la preparación | AD128: =SUM(AD127) -> 4683.2157 | AF128: Costo total de la preparación | AI128: =SUM(AI127) -> 6610.6597
B129: Costo porción | E129: =+E128 -> 5226.6782 | G129: Costo porción | J129: =+J128 -> 1591.8153 | L129: Costo porción | O129: =+O128 -> 2028.1876 | Q129: Costo porción | T129: =+T128 -> 1351.7176 | V129: Costo porción | Y129: =+Y128 -> 6189.8438 | AA129: Costo porción | AD129: =+AD128 -> 4683.2157 | AF129: Costo porción | AI129: =+AI128 -> 6610.6597
B130: Porcentaje costo materia prima establecida | D130: 0.3 | G130: Porcentaje costo materia prima establecida | I130: 0.3 | L130: Porcentaje costo materia prima establecida | N130: 0.3 | Q130: Porcentaje costo materia prima establecida | S130: 0.3 | V130: Porcentaje costo materia prima establecida | X130: 0.3 | AA130: Porcentaje costo materia prima establecida | AC130: 0.3 | AF130: Porcentaje costo materia prima establecida | AH130: 0.3
B131: Precio potencial de venta | E131: =+E129*3.33333333333333 -> 17422.261 | G131: Precio potencial de venta | J131: =+J129*3.33333333333333 -> 5306.0511 | L131: Precio potencial de venta | O131: =+O129*3.33333333333333 -> 6760.6253 | Q131: Precio potencial de venta | T131: =+T129*3.33333333333333 -> 4505.7253 | V131: Precio potencial de venta | Y131: =+Y129*3.33333333333333 -> 20632.813 | AA131: Precio potencial de venta | AD131: =+AD129*3.33333333333333 -> 15610.719 | AF131: Precio potencial de venta | AI131: =+AI129*3.33333333333333 -> 22035.532
B132: Precio de Venta | E132: 21500 | G132: Precio de Venta | J132: =SUM(J131) -> 5306.0511 | L132: Precio de Venta | O132: 9200 | Q132: Precio de Venta | T132: 9200 | V132: Precio de Venta | X132: 23000 | Y132: 23000 | AA132: Precio de Venta | AD132: 18000 | AF132: Precio de Venta | AI132: 23000
E133: =+E132-E131 -> 4077.7392 | J133: =+J132-J131 -> 0 | O133: =+O132-O131 -> 2439.3747 | T133: =+T132-T131 -> 4694.2747 | Y133: =+Y132-Y131 -> 2367.1872 | AD133: =+AD132-AD131 -> 2389.2811 | AI133: =+AI132-AI131 -> 964.46778
B134: Costo Real MP | E134: =E129/E132 -> 0.24310131 | G134: Costo Real MP | J134: =J129/J132 -> 0.3 | L134: Costo Real MP | O134: =O129/O132 -> 0.22045517 | Q134: Costo Real MP | T134: =T129/T132 -> 0.14692583 | V134: Costo Real MP | Y134: =Y129/Y132 -> 0.26912365 | AA134: Costo Real MP | AD134: =AD129/AD132 -> 0.26017865 | AF134: Costo Real MP | AI134: =AI129/AI132 -> 0.28741999
B137: WRAP DE FALAFEL | G137: SANDWICH DE FOCACCIA | L137: WRAP DE POLLO CESAR | Q137: ENSALADA CESAR CON POLLO
C138: Kg/Lt/Uni | D138: $ | E138: Total $ | H138: Kg/Lt/Uni | I138: $ | J138: Total $ | M138: Kg/Lt/Uni | N138: $ | O138: Total $ | R138: Kg/Lt/Uni | S138: $ | T138: Total $ | W138: Kg/Lt/Uni | X138: $ | Y138: Total $ | AB138: Kg/Lt/Uni | AC138: $ | AD138: Total $
B139: falafel | C139: 0.09 | D139: =+VLOOKUP(B139,'PRECIO PROVEEDORES'!$A$2:$B$716,2,0) -> 5953.4143 | E139: =+C139*D139 -> 535.80729 | G139: focaccia | H139: 0.25 | I139: =+VLOOKUP(G139,'PRECIO PROVEEDORES'!$A$2:$B$716,2,0) -> 9771 | J139: =+H139*I139 -> 2442.75 | L139: wrap | M139: 1 | N139: =+VLOOKUP(L139,'PRECIO PROVEEDORES'!$A$2:$B$716,2,0) -> 253 | O139: =+M139*N139 -> 253 | Q139: Lechuga, francesa | R139: 0.04 | S139: =+VLOOKUP(Q139,'PRECIO PROVEEDORES'!$A$2:$B$716,2,0) -> 6440 | T139: =+R139*S139 -> 257.6 | X139: =+VLOOKUP(V139,'PRECIO PROVEEDORES'!$A$2:$B$716,2,0) -> #N/A | Y139: =+W139*X139 -> #N/A | AC139: =+VLOOKUP(AA139,'PRECIO PROVEEDORES'!$A$2:$B$716,2,0) -> #N/A | AD139: =+AB139*AC139 -> #N/A
B140: mix de vegetales asados | C140: 0.15 | D140: =+VLOOKUP(B140,'PRECIO PROVEEDORES'!$A$2:$B$716,2,0) -> 2972.2273 | E140: =+C140*D140 -> 445.83409 | G140: queso danbo tregar | H140: 0.13 | I140: =+VLOOKUP(G140,'PRECIO PROVEEDORES'!$A$2:$B$716,2,0) -> 10697 | J140: =+H140*I140 -> 1390.61 | L140: Lechuga, francesa | M140: 0.04 | N140: =+VLOOKUP(L140,'PRECIO PROVEEDORES'!$A$2:$B$716,2,0) -> 6440 | O140: =+M140*N140 -> 257.6 | Q140: queso Reggianito | R140: 0.035 | S140: =+VLOOKUP(Q140,'PRECIO PROVEEDORES'!$A$2:$B$716,2,0) -> 17376 | T140: =+R140*S140 -> 608.16 | X140: =+VLOOKUP(V140,'PRECIO PROVEEDORES'!$A$2:$B$716,2,0) -> #N/A | Y140: =+W140*X140 -> #N/A | AC140: =+VLOOKUP(AA140,'PRECIO PROVEEDORES'!$A$2:$B$716,2,0) -> #N/A | AD140: =+AB140*AC140 -> #N/A
B141: Hoja amarga, Rucula selvatica | C141: 0.03 | D141: =+VLOOKUP(B141,'PRECIO PROVEEDORES'!$A$2:$B$716,2,0) -> 9900 | E141: =+C141*D141 -> 297 | G141: Fiambre, Panceta ahumada | H141: 0.045 | I141: =+VLOOKUP(G141,'PRECIO PROVEEDORES'!$A$2:$B$716,2,0) -> 18256.35 | J141: =+H141*I141 -> 821.53575 | L141: Pollo | M141: 0.15 | N141: =+VLOOKUP(L141,'PRECIO PROVEEDORES'!$A$2:$B$716,2,0) -> 7700 | O141: =+M141*N141 -> 1155 | Q141: Pollo | R141: 0.15 | S141: =+VLOOKUP(Q141,'PRECIO PROVEEDORES'!$A$2:$B$716,2,0) -> 7700 | T141: =+R141*S141 -> 1155 | X141: =+VLOOKUP(V141,'PRECIO PROVEEDORES'!$A$2:$B$716,2,0) -> #N/A | Y141: =+W141*X141 -> #N/A | AC141: =+VLOOKUP(AA141,'PRECIO PROVEEDORES'!$A$2:$B$716,2,0) -> #N/A | AD141: =+AB141*AC141 -> #N/A
B142: cherrys confitados | C142: 0.04 | D142: =+VLOOKUP(B142,'PRECIO PROVEEDORES'!$A$2:$B$716,2,0) -> 6130.5564 | E142: =+C142*D142 -> 245.22226 | G142: Aji colorado | H142: 0.06 | I142: =+VLOOKUP(G142,'PRECIO PROVEEDORES'!$A$2:$B$716,2,0) -> 4788 | J142: =+H142*I142 -> 287.28 | L142: salsa cesar | M142: 0.05 | N142: =+VLOOKUP(L142,'PRECIO PROVEEDORES'!$A$2:$B$716,2,0) -> 9725 | O142: =+M142*N142 -> 486.25 | Q142: tostada en pan de campo xl | R142: 0.1 | S142: =+VLOOKUP(Q142,'PRECIO PROVEEDORES'!$A$2:$B$716,2,0) -> 243.1 | T142: =+R142*S142 -> 24.31 | X142: =+VLOOKUP(V142,'PRECIO PROVEEDORES'!$A$2:$B$716,2,0) -> #N/A | Y142: =+W142*X142 -> #N/A | AC142: =+VLOOKUP(AA142,'PRECIO PROVEEDORES'!$A$2:$B$716,2,0) -> #N/A | AD142: =+AB142*AC142 -> #N/A
...

Sheet PRECIOS RAPPI
A1: vega
B2: YOGURT GRIEGO | G2: HUEVOS REVUELTOS | L2: PANCAKES | Q2: TOSTADAS FRANCESAS | V2: SANDWICH POLLO TERIYAKI | AA2: TOSTADO JAMON Y QUESO
C3: Kg/Lt/Uni | D3: $ | E3: Total $ | H3: Kg/Lt/Uni | I3: $ | J3: Total $ | M3: Kg/Lt/Uni | N3: $ | O3: Total $ | R3: Kg/Lt/Uni | S3: $ | T3: Total $ | W3: Kg/Lt/Uni | X3: $ | Y3: Total $ | AB3: Kg/Lt/Uni | AC3: $ | AD3: Total $
B4: yogurt griego | C4: 0.15 | D4: =+VLOOKUP(B4,'PRECIO PROVEEDORES'!$A$2:$B$716,2,0) -> 7449.2 | E4: =+C4*D4 -> 1117.38 | G4: tostada en pan de campo xl | H4: 1 | I4: =+VLOOKUP(G4,'PRECIO PROVEEDORES'!$A$2:$B$716,2,0) -> 243.1 | J4: =+H4*I4 -> 243.1 | L4: pancakes | M4: 2 | N4: =+VLOOKUP(L4,'PRECIO PROVEEDORES'!$A$2:$B$716,2,0) -> 391.805 | O4: =+M4*N4 -> 783.61 | Q4: uva | R4: 0.04 | S4: =+VLOOKUP(Q4,'PRECIO PROVEEDORES'!$A$2:$B$716,2,0) -> 2332 | T4: =+R4*S4 -> 93.28 | V4: tostada en pan de campo xl | W4: 2 | X4: =+VLOOKUP(V4,'PRECIO PROVEEDORES'!$A$2:$B$716,2,0) -> 243.1 | Y4: =+W4*X4 -> 486.2 | AA4: tostada en pan de campo xl | AB4: 2 | AC4: =+VLOOKUP(AA4,'PRECIO PROVEEDORES'!$A$2:$B$716,2,0) -> 243.1 | AD4: =+AB4*AC4 -> 486.2
B5: granola | C5: 0.05 | D5: =+VLOOKUP(B5,'PRECIO PROVEEDORES'!$A$2:$B$716,2,0) -> 8954.3189 | E5: =+C5*D5 -> 447.71595 | G5: huevos | H5: 3 | I5: =+VLOOKUP(G5,'PRECIO PROVEEDORES'!$A$2:$B$716,2,0) -> 192 | J5: =+H5*I5 -> 576 | L5: salsa de chocolate | M5: 0.01 | N5: =+VLOOKUP(L5,'PRECIO PROVEEDORES'!$A$2:$B$716,2,0) -> 9542 | O5: =+M5*N5 -> 95.42 | Q5: Brioche para tostadas francesas | R5: 1 | S5: =+VLOOKUP(Q5,'PRECIO PROVEEDORES'!$A$2:$B$716,2,0) -> 1650 | T5: =+R5*S5 -> 1650 | V5: pollo | W5: 0.12 | X5: =+VLOOKUP(V5,'PRECIO PROVEEDORES'!$A$2:$B$716,2,0) -> 7700 | Y5: =+W5*X5 -> 924 | AA5: Fiambre, Jamon cocido | AB5: 0.06 | AC5: =+VLOOKUP(AA5,'PRECIO PROVEEDORES'!$A$2:$B$716,2,0) -> 11881 | AD5: =+AB5*AC5 -> 712.86
B6: banana | C6: 0.05 | D6: =+VLOOKUP(B6,'PRECIO PROVEEDORES'!$A$2:$B$716,2,0) -> 3360 | E6: =+C6*D6 -> 168 | G6: Palta hass | H6: 0.08 | I6: =+VLOOKUP(G6,'PRECIO PROVEEDORES'!$A$2:$B$716,2,0) -> 9316 | J6: =+H6*I6 -> 745.28 | L6: Banana | M6: 0.08 | N6: =+VLOOKUP(L6,'PRECIO PROVEEDORES'!$A$2:$B$716,2,0) -> 3360 | O6: =+M6*N6 -> 268.8 | Q6: queso crema paulina | R6: 0.03 | S6: =+VLOOKUP(Q6,'PRECIO PROVEEDORES'!$A$2:$B$716,2,0) -> 6000 | T6: =+R6*S6 -> 180 | V6: Lechuga, francesa | W6: 0.02 | X6: =+VLOOKUP(V6,'PRECIO PROVEEDORES'!$A$2:$B$716,2,0) -> 6440 | Y6: =+W6*X6 -> 128.8 | AA6: queso danbo tregar | AB6: 0.09 | AC6: =+VLOOKUP(AA6,'PRECIO PROVEEDORES'!$A$2:$B$716,2,0) -> 10697 | AD6: =+AB6*AC6 -> 962.73
B7: frutilla | C7: 0.04 | D7: =+VLOOKUP(B7,'PRECIO PROVEEDORES'!$A$2:$B$716,2,0) -> 26000 | E7: =+C7*D7 -> 1040 | G7: queso crema paulina | H7: 0.035 | I7: =+VLOOKUP(G7,'PRECIO PROVEEDORES'!$A$2:$B$716,2,0) -> 6000 | J7: =+H7*I7 -> 210 | L7: frutilla | M7: 0.05 | N7: =+VLOOKUP(L7,'PRECIO PROVEEDORES'!$A$2:$B$716,2,0) -> 26000 | O7: =+M7*N7 -> 1300 | Q7: frutilla | R7: 0.05 | S7: =+VLOOKUP(Q7,'PRECIO PROVEEDORES'!$A$2:$B$716,2,0) -> 26000 | T7: =+R7*S7 -> 1300 | V7: palta hass | W7: 0.04 | X7: =+VLOOKUP(V7,'PRECIO PROVEEDORES'!$A$2:$B$716,2,0) -> 9316 | Y7: =+W7*X7 -> 372.64 | AA7: manteca tueste alyser | AB7: 0.02 | AC7: =+VLOOKUP(AA7,'PRECIO PROVEEDORES'!$A$2:$B$716,2,0) -> 12206 | AD7: =+AB7*AC7 -> 244.12
B8: miel alyser | C8: 0.01 | D8: =+VLOOKUP(B8,'PRECIO PROVEEDORES'!$A$2:$B$716,2,0) -> 5917 | E8: =+C8*D8 -> 59.17 | G8: Tomate cherry rojo | H8: 0.05 | I8: =+VLOOKUP(G8,'PRECIO PROVEEDORES'!$A$2:$B$716,2,0) -> 4095 | J8: =+H8*I8 -> 204.75 | L8: nutella | M8: 0.02 | N8: =+VLOOKUP(L8,'PRECIO PROVEEDORES'!$A$2:$B$716,2,0) -> 35691.97 | O8: =+M8*N8 -> 713.8394 | Q8: miel alyser | R8: 0.015 | S8: =+VLOOKUP(Q8,'PRECIO PROVEEDORES'!$A$2:$B$716,2,0) -> 5917 | T8: =+R8*S8 -> 88.755 | V8: tomate seco | W8: 0.05 | X8: =+VLOOKUP(V8,'PRECIO PROVEEDORES'!$A$2:$B$716,2,0) -> 17587.35 | Y8: =+W8*X8 -> 879.3675 | AA8: Papel de aluminio por lamina | AB8: 0.5 | AC8: =+VLOOKUP(AA8,'PRECIO PROVEEDORES'!$A$2:$B$716,2,0) -> 160.5 | AD8: =+AB8*AC8 -> 80.25
B9: arandano | C9: 0.01 | D9: =+VLOOKUP(B9,'PRECIO PROVEEDORES'!$A$2:$B$716,2,0) -> 56000 | E9: =+C9*D9 -> 560 | G9: Fiambre, Panceta ahumada | H9: 0.02 | I9: =+VLOOKUP(G9,'PRECIO PROVEEDORES'!$A$2:$B$716,2,0) -> 18256.35 | J9: =+H9*I9 -> 365.127 | L9: caja torta individual | M9: 0.5 | N9: =+VLOOKUP(L9,'PRECIO PROVEEDORES'!$A$2:$B$716,2,0) -> 620 | O9: =+M9*N9 -> 310 | Q9: Hierbas frescas, Menta bariada | R9: 0.002 | S9: =+VLOOKUP(Q9,'PRECIO PROVEEDORES'!$A$2:$B$716,2,0) -> 18304 | T9: =+R9*S9 -> 36.608 | V9: salsa teriyaki | W9: 0.05 | X9: =+VLOOKUP(V9,'PRECIO PROVEEDORES'!$A$2:$B$716,2,0) -> 2910.45 | Y9: =+W9*X9 -> 145.5225
B10: Bowl con tapa | C10: 0.5 | D10: =+VLOOKUP(B10,'PRECIO PROVEEDORES'!$A$2:$B$716,2,0) -> 974 | E10: =+C10*D10 -> 487 | G10: Bowl con tapa | H10: 0.5 | I10: =+VLOOKUP(G10,'PRECIO PROVEEDORES'!$A$2:$B$716,2,0) -> 974 | J10: =+H10*I10 -> 487 | Q10: manteca tueste alyser | R10: 0.01 | S10: =+VLOOKUP(Q10,'PRECIO PROVEEDORES'!$A$2:$B$716,2,0) -> 12206 | T10: =+R10*S10 -> 122.06 | V10: queso danbo tregar | W10: 0.02 | X10: =+VLOOKUP(V10,'PRECIO PROVEEDORES'!$A$2:$B$716,2,0) -> 10697 | Y10: =+W10*X10 -> 213.94
Q11: kiwi | R11: 0.05 | S11: =+VLOOKUP(Q11,'PRECIO PROVEEDORES'!$A$2:$B$716,2,0) -> 10450 | T11: =+R11*S11 -> 522.5 | V11: queso reggianito | W11: 0.015 | X11: =+VLOOKUP(V11,'PRECIO PROVEEDORES'!$A$2:$B$716,2,0) -> 17376 | Y11: =+W11*X11 -> 260.64
Q12: ciruela | R12: 0.05 | S12: =+VLOOKUP(Q12,'PRECIO PROVEEDORES'!$A$2:$B$716,2,0) -> 4860 | T12: =+R12*S12 -> 243 | V12: papas asadas | W12: 0.15 | X12: =+VLOOKUP(V12,'PRECIO PROVEEDORES'!$A$2:$B$716,2,0) -> 1685.0215 | Y12: =+W12*X12 -> 252.75322
Q13: caja torta individual | R13: 0.5 | S13: =+VLOOKUP(Q13,'PRECIO PROVEEDORES'!$A$2:$B$716,2,0) -> 620 | T13: =+R13*S13 -> 310 | V13: mayonesa de pimiento | W13: 0.04 | X13: =+VLOOKUP(V13,'PRECIO PROVEEDORES'!$A$2:$B$716,2,0) -> 3891.911 | Y13: =+W13*X13 -> 155.67644
V14: Papel de aluminio por lamina | W14: 0.5 | X14: =+VLOOKUP(V14,'PRECIO PROVEEDORES'!$A$2:$B$716,2,0) -> 160.5 | Y14: =+W14*X14 -> 80.25
V15: dip 55 cc | W15: 0.5 | X15: =+VLOOKUP(V15,'PRECIO PROVEEDORES'!$A$2:$B$716,2,0) -> 155 | Y15: =+W15*X15 -> 77.5
V16: bandeja food track n 11 | W16: 0.5 | X16: =+VLOOKUP(V16,'PRECIO PROVEEDORES'!$A$2:$B$716,2,0) -> 86 | Y16: =+W16*X16 -> 43
B19: Costo Total de la materia prima | E19: =SUM(E4:E18) -> 3879.2659 | G19: Costo Total de la materia prima | J19: =SUM(J4:J18) -> 2831.257 | L19: Costo Total de la materia prima | O19: =SUM(O4:O18) -> 3471.6694 | Q19: Costo Total de la materia prima | T19: =SUM(T4:T18) -> 4546.203 | V19: Costo Total de la materia prima | Y19: =SUM(Y4:Y18) -> 4020.2897 | AA19: Costo Total de la materia prima | AD19: =SUM(AD4:AD18) -> 2486.16
B20: Costo total de la preparación | E20: =SUM(E19) -> 3879.2659 | G20: Costo total de la preparación | J20: =SUM(J19) -> 2831.257 | L20: Costo total de la preparación | O20: =SUM(O19) -> 3471.6694 | Q20: Costo total de la preparación | T20: =SUM(T19) -> 4546.203 | V20: Costo total de la preparación | Y20: =SUM(Y19) -> 4020.2897 | AA20: Costo total de la preparación | AD20: =SUM(AD19) -> 2486.16
B21: Costo porción | E21: =+E20 -> 3879.2659 | G21: Costo porción | J21: =+J20 -> 2831.257 | L21: Costo porción | O21: =+O20 -> 3471.6694 | Q21: Costo porción | T21: =+T20 -> 4546.203 | V21: Costo porción | Y21: =+Y20 -> 4020.2897 | AA21: Costo porción | AD21: =+AD20 -> 2486.16
B22: Porcentaje costo materia prima establecida | D22: 0.3 | G22: Porcentaje costo materia prima establecida | I22: 0.3 | L22: Porcentaje costo materia prima establecida | N22: 0.3 | Q22: Porcentaje costo materia prima establecida | S22: 0.3 | V22: Porcentaje costo materia prima establecida | X22: 0.3 | AA22: Porcentaje costo materia prima establecida | AC22: 0.3
B23: Precio potencial de venta | E23: =+E21*3.33333333333333 -> 12930.886 | G23: Precio potencial de venta | J23: =+J21*3.33333333333333 -> 9437.5233 | L23: Precio potencial de venta | O23: =+O21*3.33333333333333 -> 11572.231 | Q23: Precio potencial de venta | T23: =+T21*3.33333333333333 -> 15154.01 | V23: Precio potencial de venta | Y23: =+Y21*3.33333333333333 -> 13400.966 | AA23: Precio potencial de venta | AD23: =+AD21*3.33333333333333 -> 8287.2
B24: Precio de Venta rappi | C24: 13500 | D24: 0.35 | E24: 18225 | G24: Precio de Venta rappi | H24: 12000 | I24: 0.35 | J24: 16200 | L24: Precio de Venta rappi | M24: 13000 | N24: 0.35 | O24: 17550 | Q24: Precio de Venta rappi | R24: 16000 | S24: 0.35 | T24: 21600 | V24: Precio de Venta rappi | W24: 15500 | X24: 0.35 | Y24: 21000 | AA24: Precio de Venta rappi | AB24: 11000 | AC24: 0.35 | AD24: 15000
E25: =+E24-E23 -> 5294.1135 | J25: =+J24-J23 -> 6762.4767 | O25: =+O24-O23 -> 5977.7687 | T25: =+T24-T23 -> 6445.99 | Y25: =+Y24-Y23 -> 7599.0345 | AD25: =+AD24-AD23 -> 6712.8
B26: Costo Real MP | E26: =E21/E24 -> 0.2128541 | G26: Costo Real MP | J26: =J21/J24 -> 0.17476895 | L26: Costo Real MP | O26: =O21/O24 -> 0.19781592 | Q26: Costo Real MP | T26: =T21/T24 -> 0.21047236 | V26: Costo Real MP | Y26: =Y21/Y24 -> 0.19144237 | AA26: Costo Real MP | AD26: =AD21/AD24 -> 0.165744
B29: TOSTON TUESTE | G29: TOSTON PALTA | L29: TOSTADO PAN CHIPA | Q29: TAPA DE ASADO | V29: SANDWICH BRIE | AA29: TOSTADO LOMITO Y CHEDAR | AF29: CHIPA CLASICO
C30: Kg/Lt/Uni | D30: $ | E30: Total $ | H30: Kg/Lt/Uni | I30: $ | J30: Total $ | M30: Kg/Lt/Uni | N30: $ | O30: Total $ | R30: Kg/Lt/Uni | S30: $ | T30: Total $ | W30: Kg/Lt/Uni | X30: $ | Y30: Total $ | AB30: Kg/Lt/Uni | AC30: $ | AD30: Total $ | AG30: Kg/Lt/Uni | AH30: $ | AI30: Total $
B31: rodaja pan masa madre | C31: 1 | D31: =+VLOOKUP(B31,'PRECIO PROVEEDORES'!$A$2:$B$716,2,0) -> 1252.8 | E31: =+C31*D31 -> 1252.8 | G31: rodaja pan masa madre | H31: 1 | I31: =+VLOOKUP(G31,'PRECIO PROVEEDORES'!$A$2:$B$716,2,0) -> 1252.8 | J31: =+H31*I31 -> 1252.8 | L31: pan de chipa | M31: 0.18 | N31: =+VLOOKUP(L31,'PRECIO PROVEEDORES'!$A$2:$B$716,2,0) -> 8843.4185 | O31: =+M31*N31 -> 1591.8153 | Q31: tapa de asado | R31: 0.15 | S31: =+VLOOKUP(Q31,'PRECIO PROVEEDORES'!$A$2:$B$716,2,0) -> 17289 | T31: =+R31*S31 -> 2593.35 | V31: pan ciabatta | W31: 1 | X31: =+VLOOKUP(V31,'PRECIO PROVEEDORES'!$A$2:$B$716,2,0) -> 168.4551 | Y31: =+W31*X31 -> 168.4551 | AA31: pan de papa | AB31: 1 | AC31: =+VLOOKUP(AA31,'PRECIO PROVEEDORES'!$A$2:$B$716,2,0) -> 675 | AD31: =+AB31*AC31 -> 675 | AF31: chipa clasico | AG31: 0.09 | AH31: =+VLOOKUP(AF31,'PRECIO PROVEEDORES'!$A$2:$B$716,2,0) -> 8843.4185 | AI31: =+AG31*AH31 -> 795.90767
B32: Hoja amarga, Rucula selvatica | C32: 0.03 | D32: =+VLOOKUP(B32,'PRECIO PROVEEDORES'!$A$2:$B$716,2,0) -> 9900 | E32: =+C32*D32 -> 297 | G32: queso crema paulina | H32: 0.05 | I32: =+VLOOKUP(G32,'PRECIO PROVEEDORES'!$A$2:$B$716,2,0) -> 6000 | J32: =+H32*I32 -> 300 | L32: Fiambre, Jamon cocido | M32: 0.06 | N32: =+VLOOKUP(L32,'PRECIO PROVEEDORES'!$A$2:$B$716,2,0) -> 11881 | O32: =+M32*N32 -> 712.86 | Q32: pan pretzalej | R32: 1 | S32: =+VLOOKUP(Q32,'PRECIO PROVEEDORES'!$A$2:$B$716,2,0) -> 531 | T32: =+R32*S32 -> 531 | V32: Hoja amarga, Rucula selvatica | W32: 0.04 | X32: =+VLOOKUP(V32,'PRECIO PROVEEDORES'!$A$2:$B$716,2,0) -> 9900 | Y32: =+W32*X32 -> 396 | AA32: Cheddar feteado | AB32: 0.05 | AC32: =+VLOOKUP(AA32,'PRECIO PROVEEDORES'!$A$2:$B$716,2,0) -> 16343 | AD32: =+AB32*AC32 -> 817.15
B33: frutilla | C33: 0.04 | D33: =+VLOOKUP(B33,'PRECIO PROVEEDORES'!$A$2:$B$716,2,0) -> 26000 | E33: =+C33*D33 -> 1040 | G33: palta hass | H33: 0.08 | I33: =+VLOOKUP(G33,'PRECIO PROVEEDORES'!$A$2:$B$716,2,0) -> 9316 | J33: =+H33*I33 -> 745.28 | L33: queso danbo tregar | M33: 0.09 | N33: =+VLOOKUP(L33,'PRECIO PROVEEDORES'!$A$2:$B$716,2,0) -> 10697 | O33: =+M33*N33 -> 962.73 | Q33: barbacoa | R33: 0.03 | S33: =+VLOOKUP(Q33,'PRECIO PROVEEDORES'!$A$2:$B$716,2,0) -> 4800 | T33: =+R33*S33 -> 144 | V33: tomate seco | W33: 0.02 | X33: =+VLOOKUP(V33,'PRECIO PROVEEDORES'!$A$2:$B$716,2,0) -> 17587.35 | Y33: =+W33*X33 -> 351.747 | AA33: Fiambre, Lomito ahumado | AB33: 0.06 | AC33: =+VLOOKUP(AA33,'PRECIO PROVEEDORES'!$A$2:$B$716,2,0) -> 15813 | AD33: =+AB33*AC33 -> 948.78
B34: garrapiñada zapallo | C34: 0.015 | D34: =+VLOOKUP(B34,'PRECIO PROVEEDORES'!$A$2:$B$716,2,0) -> 16260 | E34: =+C34*D34 -> 243.9 | G34: Alcaparras | H34: 0.007 | I34: =+VLOOKUP(G34,'PRECIO PROVEEDORES'!$A$2:$B$716,2,0) -> 24435.611 | J34: =+H34*I34 -> 171.04928 | L34: pesto de tomate | M34: 0.025 | N34: =+VLOOKUP(L34,'PRECIO PROVEEDORES'!$A$2:$B$716,2,0) -> 37116.005 | O34: =+M34*N34 -> 927.90013 | Q34: cebollas encurtidas | R34: 0.01 | S34: =+VLOOKUP(Q34,'PRECIO PROVEEDORES'!$A$2:$B$716,2,0) -> 2381.6561 | T34: =+R34*S34 -> 23.816561 | V34: queso brie | W34: 0.08 | X34: =+VLOOKUP(V34,'PRECIO PROVEEDORES'!$A$2:$B$716,2,0) -> 20535 | Y34: =+W34*X34 -> 1642.8 | AA34: Papel de aluminio por lamina | AB34: 0.5 | AC34: =+VLOOKUP(AA34,'PRECIO PROVEEDORES'!$A$2:$B$716,2,0) -> 160.5 | AD34: =+AB34*AC34 -> 80.25
B35: queso brie | C35: 0.04 | D35: =+VLOOKUP(B35,'PRECIO PROVEEDORES'!$A$2:$B$716,2,0) -> 20535 | E35: =+C35*D35 -> 821.4 | G35: Aceto balsamico reduccion | H35: 0.003 | I35: =+VLOOKUP(G35,'PRECIO PROVEEDORES'!$A$2:$B$716,2,0) -> 10601.56 | J35: =+H35*I35 -> 31.80468 | L35: pesto de albahaca | M35: 0.01 | N35: =+VLOOKUP(L35,'PRECIO PROVEEDORES'!$A$2:$B$716,2,0) -> 0 | O35: =+M35*N35 -> 0 | Q35: papas asadas | R35: 0.15 | S35: =+VLOOKUP(Q35,'PRECIO PROVEEDORES'!$A$2:$B$716,2,0) -> 1685.0215 | T35: =+R35*S35 -> 252.75322 | V35: mermelada de morron | W35: 0.03 | X35: =+VLOOKUP(V35,'PRECIO PROVEEDORES'!$A$2:$B$716,2,0) -> 4622.4709 | Y35: =+W35*X35 -> 138.67413
B36: miel alyser | C36: 0.01 | D36: =+VLOOKUP(B36,'PRECIO PROVEEDORES'!$A$2:$B$716,2,0) -> 5917 | E36: =+C36*D36 -> 59.17 | G36: Mix de semillas | H36: 0.003 | I36: =+VLOOKUP(G36,'PRECIO PROVEEDORES'!$A$2:$B$716,2,0) -> 5952.89 | J36: =+H36*I36 -> 17.85867 | L36: Papel de aluminio por lamina | M36: 0.5 | N36: =+VLOOKUP(L36,'PRECIO PROVEEDORES'!$A$2:$B$716,2,0) -> 160.5 | O36: =+M36*N36 -> 80.25 | Q36: mayonesa de pimiento | R36: 0.04 | S36: =+VLOOKUP(Q36,'PRECIO PROVEEDORES'!$A$2:$B$716,2,0) -> 3891.911 | T36: =+R36*S36 -> 155.67644 | V36: papas asadas | W36: 0.15 | X36: =+VLOOKUP(V36,'PRECIO PROVEEDORES'!$A$2:$B$716,2,0) -> 1685.0215 | Y36: =+W36*X36 -> 252.75322
B37: bandeja food track n 11 | C37: 0.5 | D37: =+VLOOKUP(B37,'PRECIO PROVEEDORES'!$A$2:$B$716,2,0) -> 86 | E37: =+C37*D37 -> 43 | G37: flores comestibles | H37: 0.001 | I37: =+VLOOKUP(G37,'PRECIO PROVEEDORES'!$A$2:$B$716,2,0) -> 5033.6 | J37: =+H37*I37 -> 5.0336 | Q37: Papel de aluminio por lamina | R37: 0.5 | S37: =+VLOOKUP(Q37,'PRECIO PROVEEDORES'!$A$2:$B$716,2,0) -> 160.5 | T37: =+R37*S37 -> 80.25 | V37: mayonesa de pimiento | W37: 0.04 | X37: =+VLOOKUP(V37,'PRECIO PROVEEDORES'!$A$2:$B$716,2,0) -> 3891.911 | Y37: =+W37*X37 -> 155.67644
G38: bandeja food track n 11 | H38: 0.5 | I38: =+VLOOKUP(G38,'PRECIO PROVEEDORES'!$A$2:$B$716,2,0) -> 86 | J38: =+H38*I38 -> 43 | Q38: dip 55 cc | R38: 0.5 | S38: =+VLOOKUP(Q38,'PRECIO PROVEEDORES'!$A$2:$B$716,2,0) -> 155 | T38: =+R38*S38 -> 77.5 | V38: Papel de aluminio por lamina | W38: 0.5 | X38: =+VLOOKUP(V38,'PRECIO PROVEEDORES'!$A$2:$B$716,2,0) -> 160.5 | Y38: =+W38*X38 -> 80.25
Q39: bandeja food track n 11 | R39: 0.5 | S39: =+VLOOKUP(Q39,'PRECIO PROVEEDORES'!$A$2:$B$716,2,0) -> 86 | T39: =+R39*S39 -> 43 | V39: dip 55 cc | W39: 0.5 | X39: =+VLOOKUP(V39,'PRECIO PROVEEDORES'!$A$2:$B$716,2,0) -> 155 | Y39: =+W39*X39 -> 77.5
V40: bandeja food track n 11 | W40: 0.5 | X40: =+VLOOKUP(V40,'PRECIO PROVEEDORES'!$A$2:$B$716,2,0) -> 86 | Y40: =+W40*X40 -> 43
B46: Costo Total de la materia prima | E46: =SUM(E31:E45) -> 3757.27 | G46: Costo Total de la materia prima | J46: =SUM(J31:J45) -> 2566.8262 | L46: Costo Total de la materia prima | O46: =SUM(O31:O45) -> 4275.5555 | Q46: Costo Total de la materia prima | T46: =SUM(T31:T45) -> 3901.3462 | V46: Costo Total de la materia prima | Y46: =SUM(Y31:Y45) -> 3306.8559 | AA46: Costo Total de la materia prima | AD46: =SUM(AD31:AD45) -> 2521.18 | AF46: Costo Total de la materia prima | AI46: =SUM(AI31:AI45) -> 795.90767
B47: Costo total de la preparación | E47: =SUM(E46) -> 3757.27 | G47: Costo total de la preparación | J47: =SUM(J46) -> 2566.8262 | L47: Costo total de la preparación | O47: =SUM(O46) -> 4275.5555 | Q47: Costo total de la preparación | T47: =SUM(T46) -> 3901.3462 | V47: Costo total de la preparación | Y47: =SUM(Y46) -> 3306.8559 | AA47: Costo total de la preparación | AD47: =SUM(AD46) -> 2521.18 | AF47: Costo total de la preparación | AI47: =SUM(AI46) -> 795.90767
B48: Costo porción | E48: =+E47 -> 3757.27 | G48: Costo porción | J48: =+J47 -> 2566.8262 | L48: Costo porción | O48: =+O47 -> 4275.5555 | Q48: Costo porción | T48: =+T47 -> 3901.3462 | V48: Costo porción | Y48: =+Y47 -> 3306.8559 | AA48: Costo porción | AD48: =+AD47 -> 2521.18 | AF48: Costo porción | AI48: =+AI47 -> 795.90767
B49: Porcentaje costo materia prima establecida | D49: 0.3 | G49: Porcentaje costo materia prima establecida | I49: 0.3 | L49: Porcentaje costo materia prima establecida | N49: 0.3 | Q49: Porcentaje costo materia prima establecida | S49: 0.3 | V49: Porcentaje costo materia prima establecida | X49: 0.3 | AA49: Porcentaje costo materia prima establecida | AC49: 0.3 | AF49: Porcentaje costo materia prima establecida | AH49: 0.3
B50: Precio potencial de venta | E50: =+E48*3.33333333333333 -> 12524.233 | G50: Precio potencial de venta | J50: =+J48*3.33333333333333 -> 8556.0874 | L50: Precio potencial de venta | O50: =+O48*3.33333333333333 -> 14251.852 | Q50: Precio potencial de venta | T50: =+T48*3.33333333333333 -> 13004.487 | V50: Precio potencial de venta | Y50: =+Y48*3.33333333333333 -> 11022.853 | AA50: Precio potencial de venta | AD50: =+AD48*3.33333333333333 -> 8403.9333 | AF50: Precio potencial de venta | AI50: =+AI48*3.33333333333333 -> 2653.0256
B51: Precio de Venta rappi | C51: 13500 | D51: 0.35 | E51: 18900 | G51: Precio de Venta rappi | H51: 12000 | I51: 0.35 | J51: 16200 | L51: Precio de Venta rappi | M51: 15300 | N51: 0.35 | O51: 20700 | Q51: Precio de Venta rappi | R51: 15000 | S51: 0.35 | T51: 20500 | V51: Precio de Venta rappi | W51: 13000 | X51: 0.35 | Y51: 18000 | AA51: Precio de Venta rappi | AB51: 9300 | AC51: 0.35 | AD51: 13000 | AF51: Precio de Venta rappi | AG51: 3500 | AH51: 0.35 | AI51: 4700
E52: =+E51-E50 -> 6375.7667 | J52: =+J51-J50 -> 7643.9126 | O52: =+O51-O50 -> 6448.1485 | T52: =+T51-T50 -> 7495.5126 | Y52: =+Y51-Y50 -> 6977.147 | AD52: =+AD51-AD50 -> 4596.0667 | AI52: =+AI51-AI50 -> 2046.9744
B53: Costo Real MP | E53: =E48/E51 -> 0.19879735 | G53: Costo Real MP | J53: =J48/J51 -> 0.15844606 | L53: Costo Real MP | O53: =O48/O51 -> 0.20654857 | Q53: Costo Real MP | T53: =T48/T51 -> 0.19030957 | V53: Costo Real MP | Y53: =Y48/Y51 -> 0.18371422 | AA53: Costo Real MP | AD53: =AD48/AD51 -> 0.19393692 | AF53: Costo Real MP | AI53: =AI48/AI51 -> 0.16934206
B56: MEDIALUNA JAMON Y QUESO | G56: MEDIALUNA TOMATE Y QUESO | L56: CROISSANT DE PALTA | Q56: CROISSANT CRUDO | V56: ENSALADA CLASICA | AA56: BONDIOLA DE CANCHA | AF56: SANDWICH CLASICO CRUDO
C57: Kg/Lt/Uni | D57: $ | E57: Total $ | H57: Kg/Lt/Uni | I57: $ | J57: Total $ | M57: Kg/Lt/Uni | N57: $ | O57: Total $ | R57: Kg/Lt/Uni | S57: $ | T57: Total $ | W57: Kg/Lt/Uni | X57: $ | Y57: Total $ | AB57: Kg/Lt/Uni | AC57: $ | AD57: Total $ | AG57: Kg/Lt/Uni | AH57: $ | AI57: Total $
B58: medialuna 90 gramos | C58: 1 | D58: =+VLOOKUP(B58,'PRECIO PROVEEDORES'!$A$2:$B$716,2,0) -> 1350 | E58: =+C58*D58 -> 1350 | G58: medialuna 90 gramos | H58: 1 | I58: =+VLOOKUP(G58,'PRECIO PROVEEDORES'!$A$2:$B$716,2,0) -> 1350 | J58: =+H58*I58 -> 1350 | L58: croissant 145 gramos | M58: 1 | N58: =+VLOOKUP(L58,'PRECIO PROVEEDORES'!$A$2:$B$716,2,0) -> 1307 | O58: =+M58*N58 -> 1307 | Q58: croissant 145 gramos | R58: 1 | S58: =+VLOOKUP(Q58,'PRECIO PROVEEDORES'!$A$2:$B$716,2,0) -> 1307 | T58: =+R58*S58 -> 1307 | V58: Lechuga, francesa | W58: 0.04 | X58: =+VLOOKUP(V58,'PRECIO PROVEEDORES'!$A$2:$B$716,2,0) -> 6440 | Y58: =+W58*X58 -> 257.6 | AA58: bondiola braseada | AB58: 0.15 | AC58: =+VLOOKUP(AA58,'PRECIO PROVEEDORES'!$A$2:$B$716,2,0) -> 7748.899 | AD58: =+AB58*AC58 -> 1162.3348 | AF58: baguetin rustico | AG58: 1 | AH58: =+VLOOKUP(AF58,'PRECIO PROVEEDORES'!$A$2:$B$716,2,0) -> 1574 | AI58: =+AG58*AH58 -> 1574
B59: Fiambre, Jamon cocido | C59: 0.025 | D59: =+VLOOKUP(B59,'PRECIO PROVEEDORES'!$A$2:$B$716,2,0) -> 11881 | E59: =+C59*D59 -> 297.025 | G59: tomate redondo | H59: 0.035 | I59: =+VLOOKUP(G59,'PRECIO PROVEEDORES'!$A$2:$B$716,2,0) -> 1800 | J59: =+H59*I59 -> 63 | L59: palta hass | M59: 0.08 | N59: =+VLOOKUP(L59,'PRECIO PROVEEDORES'!$A$2:$B$716,2,0) -> 9316 | O59: =+M59*N59 -> 745.28 | Q59: Hoja amarga, Rucula selvatica | R59: 0.03 | S59: =+VLOOKUP(Q59,'PRECIO PROVEEDORES'!$A$2:$B$716,2,0) -> 9900 | T59: =+R59*S59 -> 297 | V59: Hoja amarga, Rucula selvatica | W59: 0.03 | X59: =+VLOOKUP(V59,'PRECIO PROVEEDORES'!$A$2:$B$716,2,0) -> 9900 | Y59: =+W59*X59 -> 297 | AA59: Huevos | AB59: 2 | AC59: =+VLOOKUP(AA59,'PRECIO PROVEEDORES'!$A$2:$B$716,2,0) -> 192 | AD59: =+AB59*AC59 -> 384 | AF59: Fiambre, Jamon crudo | AG59: 0.08 | AH59: =+VLOOKUP(AF59,'PRECIO PROVEEDORES'!$A$2:$B$716,2,0) -> 20000 | AI59: =+AG59*AH59 -> 1600
B60: queso danbo tregar | C60: 0.03 | D60: =+VLOOKUP(B60,'PRECIO PROVEEDORES'!$A$2:$B$716,2,0) -> 10697 | E60: =+C60*D60 -> 320.91 | G60: queso danbo tregar | H60: 0.03 | I60: =+VLOOKUP(G60,'PRECIO PROVEEDORES'!$A$2:$B$716,2,0) -> 10697 | J60: =+H60*I60 -> 320.91 | L60: queso crema paulina | M60: 0.02 | N60: =+VLOOKUP(L60,'PRECIO PROVEEDORES'!$A$2:$B$716,2,0) -> 6000 | O60: =+M60*N60 -> 120 | Q60: Fiambre, Jamon crudo | R60: 0.045 | S60: =+VLOOKUP(Q60,'PRECIO PROVEEDORES'!$A$2:$B$716,2,0) -> 20000 | T60: =+R60*S60 -> 900 | V60: frutos secos | W60: 0.03 | X60: =+VLOOKUP(V60,'PRECIO PROVEEDORES'!$A$2:$B$716,2,0) -> 19455.208 | Y60: =+W60*X60 -> 583.65625 | AA60: cebolla caramelizada | AB60: 0.03 | AC60: =+VLOOKUP(AA60,'PRECIO PROVEEDORES'!$A$2:$B$716,2,0) -> 1690.495 | AD60: =+AB60*AC60 -> 50.71485 | AF60: queso danbo tregar | AG60: 0.08 | AH60: =+VLOOKUP(AF60,'PRECIO PROVEEDORES'!$A$2:$B$716,2,0) -> 10697 | AI60: =+AG60*AH60 -> 855.76
B61: Papel de aluminio por lamina | C61: 0.5 | D61: =+VLOOKUP(B61,'PRECIO PROVEEDORES'!$A$2:$B$716,2,0) -> 160.5 | E61: =+C61*D61 -> 80.25 | G61: Papel de aluminio por lamina | H61: 0.5 | I61: =+VLOOKUP(G61,'PRECIO PROVEEDORES'!$A$2:$B$716,2,0) -> 160.5 | J61: =+H61*I61 -> 80.25 | L61: alcaparras | M61: 0.007 | N61: =+VLOOKUP(L61,'PRECIO PROVEEDORES'!$A$2:$B$716,2,0) -> 24435.611 | O61: =+M61*N61 -> 171.04928 | Q61: queso brie | R61: 0.05 | S61: =+VLOOKUP(Q61,'PRECIO PROVEEDORES'!$A$2:$B$716,2,0) -> 20535 | T61: =+R61*S61 -> 1026.75 | V61: cherrys confitados | W61: 0.05 | X61: =+VLOOKUP(V61,'PRECIO PROVEEDORES'!$A$2:$B$716,2,0) -> 6130.5564 | Y61: =+W61*X61 -> 306.52782 | AA61: pan ciabatta | AB61: 1 | AC61: =+VLOOKUP(AA61,'PRECIO PROVEEDORES'!$A$2:$B$716,2,0) -> 168.4551 | AD61: =+AB61*AC61 -> 168.4551 | AF61: tomate seco | AG61: 0.02 | AH61: =+VLOOKUP(AF61,'PRECIO PROVEEDORES'!$A$2:$B$716,2,0) -> 17587.35 | AI61: =+AG61*AH61 -> 351.747
L62: Papel de aluminio por lamina | M62: 0.5 | N62: =+VLOOKUP(L62,'PRECIO PROVEEDORES'!$A$2:$B$716,2,0) -> 160.5 | O62: =+M62*N62 -> 80.25 | Q62: tomate seco | R62: 0.02 | S62: =+VLOOKUP(Q62,'PRECIO PROVEEDORES'!$A$2:$B$716,2,0) -> 17587.35 | T62: =+R62*S62 -> 351.747 | V62: palta hass | W62: 0.04 | X62: =+VLOOKUP(V62,'PRECIO PROVEEDORES'!$A$2:$B$716,2,0) -> 9316 | Y62: =+W62*X62 -> 372.64 | AA62: Fiambre, Panceta ahumada | AB62: 0.01 | AC62: =+VLOOKUP(AA62,'PRECIO PROVEEDORES'!$A$2:$B$716,2,0) -> 18256.35 | AD62: =+AB62*AC62 -> 182.5635 | AF62: manteca tueste alyser | AG62: 0.01 | AH62: =+VLOOKUP(AF62,'PRECIO PROVEEDORES'!$A$2:$B$716,2,0) -> 12206 | AI62: =+AG62*AH62 -> 122.06
Q63: aceto balsamico reduccion | R63: 0.005 | S63: =+VLOOKUP(Q63,'PRECIO PROVEEDORES'!$A$2:$B$716,2,0) -> 10601.56 | T63: =+R63*S63 -> 53.0078 | V63: mix de vegetales asados | W63: 0.035 | X63: =+VLOOKUP(V63,'PRECIO PROVEEDORES'!$A$2:$B$716,2,0) -> 2972.2273 | Y63: =+W63*X63 -> 104.02795 | AA63: papas asadas | AB63: 0.15 | AC63: =+VLOOKUP(AA63,'PRECIO PROVEEDORES'!$A$2:$B$716,2,0) -> 1685.0215 | AD63: =+AB63*AC63 -> 252.75322 | AF63: papas asadas | AG63: 0.15 | AH63: =+VLOOKUP(AF63,'PRECIO PROVEEDORES'!$A$2:$B$716,2,0) -> 1685.0215 | AI63: =+AG63*AH63 -> 252.75322
Q64: Papel de aluminio por lamina | R64: 0.5 | S64: =+VLOOKUP(Q64,'PRECIO PROVEEDORES'!$A$2:$B$716,2,0) -> 160.5 | T64: =+R64*S64 -> 80.25 | V64: pollo | W64: 0.15 | X64: =+VLOOKUP(V64,'PRECIO PROVEEDORES'!$A$2:$B$716,2,0) -> 7700 | Y64: =+W64*X64 -> 1155 | AA64: mayonesa de pimiento | AB64: 0.04 | AC64: =+VLOOKUP(AA64,'PRECIO PROVEEDORES'!$A$2:$B$716,2,0) -> 3891.911 | AD64: =+AB64*AC64 -> 155.67644 | AF64: mayonesa de pimiento | AG64: 0.04 | AH64: =+VLOOKUP(AF64,'PRECIO PROVEEDORES'!$A$2:$B$716,2,0) -> 3891.911 | AI64: =+AG64*AH64 -> 155.67644
V65: Bowl con tapa | W65: 0.5 | X65: =+VLOOKUP(V65,'PRECIO PROVEEDORES'!$A$2:$B$716,2,0) -> 974 | Y65: =+W65*X65 -> 487 | AF65: Papel de aluminio por lamina | AG65: 0.5 | AH65: =+VLOOKUP(AF65,'PRECIO PROVEEDORES'!$A$2:$B$716,2,0) -> 160.5 | AI65: =+AG65*AH65 -> 80.25
AF66: dip 55 cc | AG66: 0.5 | AH66: =+VLOOKUP(AF66,'PRECIO PROVEEDORES'!$A$2:$B$716,2,0) -> 155 | AI66: =+AG66*AH66 -> 77.5
AF67: bandeja food track n 11 | AG67: 0.5 | AH67: =+VLOOKUP(AF67,'PRECIO PROVEEDORES'!$A$2:$B$716,2,0) -> 86 | AI67: =+AG67*AH67 -> 43
B73: Costo Total de la materia prima | E73: =SUM(E58:E72) -> 2048.185 | G73: Costo Total de la materia prima | J73: =SUM(J58:J72) -> 1814.16 | L73: Costo Total de la materia prima | O73: =SUM(O58:O72) -> 2423.5793 | Q73: Costo Total de la materia prima | T73: =SUM(T58:T72) -> 4015.7548 | V73: Costo Total de la materia prima | Y73: =SUM(Y58:Y72) -> 3563.452 | AA73: Costo Total de la materia prima | AD73: =SUM(AD58:AD72) -> 2356.498 | AF73: Costo Total de la materia prima | AI73: =SUM(AI58:AI72) -> 5112.7467
B74: Costo total de la preparación | E74: =SUM(E73) -> 2048.185 | G74: Costo total de la preparación | J74: =SUM(J73) -> 1814.16 | L74: Costo total de la preparación | O74: =SUM(O73) -> 2423.5793 | Q74: Costo total de la preparación | T74: =SUM(T73) -> 4015.7548 | V74: Costo total de la preparación | Y74: =SUM(Y73) -> 3563.452 | AA74: Costo total de la preparación | AD74: =SUM(AD73) -> 2356.498 | AF74: Costo total de la preparación | AI74: =SUM(AI73) -> 5112.7467
B75: Costo porción | E75: =+E74 -> 2048.185 | G75: Costo porción | J75: =+J74 -> 1814.16 | L75: Costo porción | O75: =+O74 -> 2423.5793 | Q75: Costo porción | T75: =+T74 -> 4015.7548 | V75: Costo porción | Y75: =+Y74 -> 3563.452 | AA75: Costo porción | AD75: =+AD74 -> 2356.498 | AF75: Costo porción | AI75: =+AI74 -> 5112.7467
B76: Porcentaje costo materia prima establecida | D76: 0.3 | G76: Porcentaje costo materia prima establecida | I76: 0.3 | L76: Porcentaje costo materia prima establecida | N76: 0.3 | Q76: Porcentaje costo materia prima establecida | S76: 0.3 | V76: Porcentaje costo materia prima establecida | X76: 0.3 | AA76: Porcentaje costo materia prima establecida | AC76: 0.3 | AF76: Porcentaje costo materia prima establecida | AH76: 0.3
B77: Precio potencial de venta | E77: =+E75*3.33333333333333 -> 6827.2833 | G77: Precio potencial de venta | J77: =+J75*3.33333333333333 -> 6047.2 | L77: Precio potencial de venta | O77: =+O75*3.33333333333333 -> 8078.5976 | Q77: Precio potencial de venta | T77: =+T75*3.33333333333333 -> 13385.849 | V77: Precio potencial de venta | Y77: =+Y75*3.33333333333333 -> 11878.173 | AA77: Precio potencial de venta | AD77: =+AD75*3.33333333333333 -> 7854.9932 | AF77: Precio potencial de venta | AI77: =+AI75*3.33333333333333 -> 17042.489
B78: Precio de Venta rappi | C78: 7800 | D78: 0.35 | E78: 10500 | G78: Precio de Venta rappi | H78: 7800 | I78: 0.35 | J78: 10500 | L78: Precio de Venta rappi | M78: 10000 | N78: 0.35 | O78: 13500 | Q78: Precio de Venta rappi | R78: 13500 | S78: 0.35 | T78: 18225 | V78: Precio de Venta rappi | W78: 13000 | X78: 0.35 | Y78: 18000 | AA78: Precio de Venta rappi | AC78: 0.35 | AD78: 15500 | AF78: Precio de Venta rappi | AG78: 17800 | AH78: 0.35 | AI78: 24000
E79: =+E78-E77 -> 3672.7167 | J79: =+J78-J77 -> 4452.8 | O79: =+O78-O77 -> 5421.4024 | T79: =+T78-T77 -> 4839.1507 | Y79: =+Y78-Y77 -> 6121.8266 | AD79: =+AD78-AD77 -> 7645.0068 | AI79: =+AI78-AI77 -> 6957.5111
B80: Costo Real MP | E80: =E75/E78 -> 0.19506524 | G80: Costo Real MP | J80: =J75/J78 -> 0.17277714 | L80: Costo Real MP | O80: =O75/O78 -> 0.17952439 | Q80: Costo Real MP | T80: =T75/T78 -> 0.2203432 | V80: Costo Real MP | Y80: =Y75/Y78 -> 0.19796956 | AA80: Costo Real MP | AD80: =AD75/AD78 -> 0.15203213 | AF80: Costo Real MP | AI80: =AI75/AI78 -> 0.21303111
B83: PLATO DE FRUTAS | G83: TOSTADAS | L83: ACAI | Q83: CROISSANT J Y Q | V83: CROISSANT TOMATE Y QUESO | AA83: TOSTON DE HONGOS | AF83: GRANOLA 300 GRS
C84: Kg/Lt/Uni | D84: $ | E84: Total $ | H84: Kg/Lt/Uni | I84: $ | J84: Total $ | M84: Kg/Lt/Uni | N84: $ | O84: Total $ | R84: Kg/Lt/Uni | S84: $ | T84: Total $ | W84: Kg/Lt/Uni | X84: $ | Y84: Total $ | AB84: Kg/Lt/Uni | AC84: $ | AD84: Total $ | AG84: Kg/Lt/Uni | AH84: $ | AI84: Total $
B85: banana | C85: 0.1 | D85: =+VLOOKUP(B85,'PRECIO PROVEEDORES'!$A$2:$B$716,2,0) -> 3360 | E85: =+C85*D85 -> 336 | G85: brioche molde para tostadas | H85: 1 | I85: =+VLOOKUP(G85,'PRECIO PROVEEDORES'!$A$2:$B$716,2,0) -> 1100 | J85: =+H85*I85 -> 1100 | L85: acai | M85: 0.15 | N85: =+VLOOKUP(L85,'PRECIO PROVEEDORES'!$A$2:$B$716,2,0) -> 15760 | O85: =+M85*N85 -> 2364 | Q85: croissant 145 gramos | R85: 1 | S85: =+VLOOKUP(Q85,'PRECIO PROVEEDORES'!$A$2:$B$716,2,0) -> 1307 | T85: =+R85*S85 -> 1307 | V85: croissant 145 gramos | W85: 1 | X85: =+VLOOKUP(V85,'PRECIO PROVEEDORES'!$A$2:$B$716,2,0) -> 1307 | Y85: =+W85*X85 -> 1307 | AA85: rodaja pan masa madre | AB85: 1 | AC85: =+VLOOKUP(AA85,'PRECIO PROVEEDORES'!$A$2:$B$716,2,0) -> 1252.8 | AD85: =+AB85*AC85 -> 1252.8 | AF85: granola | AG85: 0.3 | AH85: =+VLOOKUP(AF85,'PRECIO PROVEEDORES'!$A$2:$B$716,2,0) -> 8954.3189 | AI85: =+AG85*AH85 -> 2686.2957
B86: kiwi | C86: 0.05 | D86: =+VLOOKUP(B86,'PRECIO PROVEEDORES'!$A$2:$B$716,2,0) -> 10450 | E86: =+C86*D86 -> 522.5 | G86: tostada en pan de campo xl | H86: 1 | I86: =+VLOOKUP(G86,'PRECIO PROVEEDORES'!$A$2:$B$716,2,0) -> 243.1 | J86: =+H86*I86 -> 243.1 | L86: granola | M86: 0.05 | N86: =+VLOOKUP(L86,'PRECIO PROVEEDORES'!$A$2:$B$716,2,0) -> 8954.3189 | O86: =+M86*N86 -> 447.71595 | Q86: Fiambre, Jamon cocido | R86: 0.08 | S86: =+VLOOKUP(Q86,'PRECIO PROVEEDORES'!$A$2:$B$716,2,0) -> 11881 | T86: =+R86*S86 -> 950.48 | V86: queso danbo tregar | W86: 0.08 | X86: =+VLOOKUP(V86,'PRECIO PROVEEDORES'!$A$2:$B$716,2,0) -> 10697 | Y86: =+W86*X86 -> 855.76 | AA86: Hongo, pino | AB86: 0.02 | AC86: =+VLOOKUP(AA86,'PRECIO PROVEEDORES'!$A$2:$B$716,2,0) -> 28695 | AD86: =+AB86*AC86 -> 573.9 | AF86: bolsa ziploc | AG86: 0.5 | AH86: =+VLOOKUP(AF86,'PRECIO PROVEEDORES'!$A$2:$B$716,2,0) -> 392 | AI86: =+AG86*AH86 -> 196
B87: frutilla | C87: 0.05 | D87: =+VLOOKUP(B87,'PRECIO PROVEEDORES'!$A$2:$B$716,2,0) -> 26000 | E87: =+C87*D87 -> 1300 | G87: rodaja pan masa madre | H87: 1 | I87: =+VLOOKUP(G87,'PRECIO PROVEEDORES'!$A$2:$B$716,2,0) -> 1252.8 | J87: =+H87*I87 -> 1252.8 | L87: banana | M87: 0.05 | N87: =+VLOOKUP(L87,'PRECIO PROVEEDORES'!$A$2:$B$716,2,0) -> 3360 | O87: =+M87*N87 -> 168 | Q87: queso danbo tregar | R87: 0.08 | S87: =+VLOOKUP(Q87,'PRECIO PROVEEDORES'!$A$2:$B$716,2,0) -> 10697 | T87: =+R87*S87 -> 855.76 | V87: tomate redondo | W87: 0.06 | X87: =+VLOOKUP(V87,'PRECIO PROVEEDORES'!$A$2:$B$716,2,0) -> 1800 | Y87: =+W87*X87 -> 108 | AA87: aceite de girasol | AB87: 0.06 | AC87: =+VLOOKUP(AA87,'PRECIO PROVEEDORES'!$A$2:$B$716,2,0) -> 4299.01 | AD87: =+AB87*AC87 -> 257.9406
B88: uva | C88: 0.02 | D88: =+VLOOKUP(B88,'PRECIO PROVEEDORES'!$A$2:$B$716,2,0) -> 2332 | E88: =+C88*D88 -> 46.64 | G88: mermelada | H88: 0.04 | I88: =+VLOOKUP(G88,'PRECIO PROVEEDORES'!$A$2:$B$716,2,0) -> 14000 | J88: =+H88*I88 -> 560 | L88: frutilla | M88: 0.04 | N88: =+VLOOKUP(L88,'PRECIO PROVEEDORES'!$A$2:$B$716,2,0) -> 26000 | O88: =+M88*N88 -> 1040 | Q88: Papel de aluminio por lamina | R88: 0.5 | S88: =+VLOOKUP(Q88,'PRECIO PROVEEDORES'!$A$2:$B$716,2,0) -> 160.5 | T88: =+R88*S88 -> 80.25 | V88: Papel de aluminio por lamina | W88: 0.5 | X88: =+VLOOKUP(V88,'PRECIO PROVEEDORES'!$A$2:$B$716,2,0) -> 160.5 | Y88: =+W88*X88 -> 80.25 | AA88: Hongo, Portobello | AB88: 0.04 | AC88: =+VLOOKUP(AA88,'PRECIO PROVEEDORES'!$A$2:$B$716,2,0) -> 26900 | AD88: =+AB88*AC88 -> 1076
B89: miel alyser | C89: 0.015 | D89: =+VLOOKUP(B89,'PRECIO PROVEEDORES'!$A$2:$B$716,2,0) -> 5917 | E89: =+C89*D89 -> 88.755 | G89: queso crema paulina | H89: 0.04 | I89: =+VLOOKUP(G89,'PRECIO PROVEEDORES'!$A$2:$B$716,2,0) -> 6000 | J89: =+H89*I89 -> 240 | L89: miel alyser | M89: 0.01 | N89: =+VLOOKUP(L89,'PRECIO PROVEEDORES'!$A$2:$B$716,2,0) -> 5917 | O89: =+M89*N89 -> 59.17 | AA89: cherrys confitados | AB89: 0.05 | AC89: =+VLOOKUP(AA89,'PRECIO PROVEEDORES'!$A$2:$B$716,2,0) -> 6130.5564 | AD89: =+AB89*AC89 -> 306.52782
B90: frutos secos | C90: 0.03 | D90: =+VLOOKUP(B90,'PRECIO PROVEEDORES'!$A$2:$B$716,2,0) -> 19455.208 | E90: =+C90*D90 -> 583.65625 | G90: dip 55 cc | H90: 1 | I90: =+VLOOKUP(G90,'PRECIO PROVEEDORES'!$A$2:$B$716,2,0) -> 155 | J90: =+H90*I90 -> 155 | L90: Bowl con tapa | M90: 0.5 | N90: =+VLOOKUP(L90,'PRECIO PROVEEDORES'!$A$2:$B$716,2,0) -> 974 | O90: =+M90*N90 -> 487 | AA90: garrapiñada zapallo | AB90: 0.015 | AC90: =+VLOOKUP(AA90,'PRECIO PROVEEDORES'!$A$2:$B$716,2,0) -> 16260 | AD90: =+AB90*AC90 -> 243.9
B91: pasta de mani | C91: 0.03 | D91: =+VLOOKUP(B91,'PRECIO PROVEEDORES'!$A$2:$B$716,2,0) -> 5595 | E91: =+C91*D91 -> 167.85 | AA91: Hierbas frescas, Albahaca | AB91: 0.1 | AC91: =+VLOOKUP(AA91,'PRECIO PROVEEDORES'!$A$2:$B$716,2,0) -> 4160 | AD91: =+AB91*AC91 -> 416
B92: pomelo rosado | C92: 0.05 | D92: =+VLOOKUP(B92,'PRECIO PROVEEDORES'!$A$2:$B$716,2,0) -> 2185 | E92: =+C92*D92 -> 109.25 | AA92: bandeja food track n 11 | AB92: 0.5 | AC92: =+VLOOKUP(AA92,'PRECIO PROVEEDORES'!$A$2:$B$716,2,0) -> 86 | AD92: =+AB92*AC92 -> 43
B93: Bowl con tapa | C93: 0.5 | D93: =+VLOOKUP(B93,'PRECIO PROVEEDORES'!$A$2:$B$716,2,0) -> 974 | E93: =+C93*D93 -> 487
B94: dip 55 cc | C94: 0.5 | D94: =+VLOOKUP(B94,'PRECIO PROVEEDORES'!$A$2:$B$716,2,0) -> 155 | E94: =+C94*D94 -> 77.5
B100: Costo Total de la materia prima | E100: =SUM(E85:E99) -> 3719.1512 | G100: Costo Total de la materia prima | J100: =SUM(J85:J99) -> 3550.9 | L100: Costo Total de la materia prima | O100: =SUM(O85:O99) -> 4565.8859 | Q100: Costo Total de la materia prima | T100: =SUM(T85:T99) -> 3193.49 | V100: Costo Total de la materia prima | Y100: =SUM(Y85:Y99) -> 2351.01 | AA100: Costo Total de la materia prima | AD100: =SUM(AD85:AD99) -> 4170.0684 | AF100: Costo Total de la materia prima | AI100: =SUM(AI85:AI99) -> 2882.2957
B101: Costo total de la preparación | E101: =SUM(E100) -> 3719.1512 | G101: Costo total de la preparación | J101: =SUM(J100) -> 3550.9 | L101: Costo total de la preparación | O101: =SUM(O100) -> 4565.8859 | Q101: Costo total de la preparación | T101: =SUM(T100) -> 3193.49 | V101: Costo total de la preparación | Y101: =SUM(Y100) -> 2351.01 | AA101: Costo total de la preparación | AD101: =SUM(AD100) -> 4170.0684 | AF101: Costo total de la preparación | AI101: =SUM(AI100) -> 2882.2957
B102: Costo porción | E102: =+E101 -> 3719.1512 | G102: Costo porción | J102: =+J101 -> 3550.9 | L102: Costo porción | O102: =+O101 -> 4565.8859 | Q102: Costo porción | T102: =+T101 -> 3193.49 | V102: Costo porción | Y102: =+Y101 -> 2351.01 | AA102: Costo porción | AD102: =+AD101 -> 4170.0684 | AF102: Costo porción | AI102: =+AI101 -> 2882.2957
B103: Porcentaje costo materia prima establecida | D103: 0.3 | G103: Porcentaje costo materia prima establecida | I103: 0.3 | L103: Porcentaje costo materia prima establecida | N103: 0.3 | Q103: Porcentaje costo materia prima establecida | S103: 0.3 | V103: Porcentaje costo materia prima establecida | X103: 0.3 | AA103: Porcentaje costo materia prima establecida | AC103: 0.3 | AF103: Porcentaje costo materia prima establecida | AH103: 0.3
B104: Precio potencial de venta | E104: =+E102*3.33333333333333 -> 12397.171 | G104: Precio potencial de venta | J104: =+J102*3.33333333333333 -> 11836.333 | L104: Precio potencial de venta | O104: =+O102*3.33333333333333 -> 15219.62 | Q104: Precio potencial de venta | T104: =+T102*3.33333333333333 -> 10644.967 | V104: Precio potencial de venta | Y104: =+Y102*3.33333333333333 -> 7836.7 | AA104: Precio potencial de venta | AD104: =+AD102*3.33333333333333 -> 13900.228 | AF104: Precio potencial de venta | AI104: =+AI102*3.33333333333333 -> 9607.6523
B105: Precio de Venta rappi | C105: 13000 | D105: 0.35 | E105: 17550 | G105: Precio de Venta rappi | H105: 12000 | I105: 0.35 | J105: 16200 | L105: Precio de Venta rappi | M105: 16000 | N105: 0.35 | O105: 21600 | Q105: Precio de Venta rappi | R105: 11200 | S105: 0.35 | T105: 15200 | V105: Precio de Venta rappi | W105: 11200 | X105: 0.35 | Y105: 15000 | AA105: Precio de Venta rappi | AB105: 15000 | AC105: 0.35 | AD105: 20250 | AF105: Precio de Venta rappi | AG105: 10000 | AH105: 0.35 | AI105: 13500
E106: =+E105-E104 -> 5152.8292 | J106: =+J105-J104 -> 4363.6667 | O106: =+O105-O104 -> 6380.3802 | T106: =+T105-T104 -> 4555.0333 | Y106: =+Y105-Y104 -> 7163.3 | AD106: =+AD105-AD104 -> 6349.7719 | AI106: =+AI105-AI104 -> 3892.3477
B107: Costo Real MP | E107: =E102/E105 -> 0.21191745 | G107: Costo Real MP | J107: =J102/J105 -> 0.21919136 | L107: Costo Real MP | O107: =O102/O105 -> 0.21138361 | Q107: Costo Real MP | T107: =T102/T105 -> 0.21009803 | V107: Costo Real MP | Y107: =Y102/Y105 -> 0.156734 | AA107: Costo Real MP | AD107: =AD102/AD105 -> 0.2059293 | AF107: Costo Real MP | AI107: =AI102/AI105 -> 0.21350338
B110: FOSFORITO JYQ | G110: FOSFORITO CAPRESE | L110: SANDWICH ALBONDIGA NUEVO | Q110: WRAP DE POLLO | V110: SANDWICH DE ATUN | AA110: SANDWICH DE FOCACCIA | AF110: WRAP DE FALAFEL
C111: Kg/Lt/Uni | D111: $ | E111: Total $ | H111: Kg/Lt/Uni | I111: $ | J111: Total $ | M111: Kg/Lt/Uni | N111: $ | O111: Total $ | R111: Kg/Lt/Uni | S111: $ | T111: Total $ | W111: Kg/Lt/Uni | X111: $ | Y111: Total $ | AB111: Kg/Lt/Uni | AC111: $ | AD111: Total $ | AG111: Kg/Lt/Uni | AH111: $ | AI111: Total $
B112: fosforito | C112: 1 | D112: =+VLOOKUP(B112,'PRECIO PROVEEDORES'!$A$2:$B$716,2,0) -> 447.7276 | E112: =+C112*D112 -> 447.7276 | G112: fosforito | H112: 1 | I112: =+VLOOKUP(G112,'PRECIO PROVEEDORES'!$A$2:$B$716,2,0) -> 447.7276 | J112: =+H112*I112 -> 447.7276 | L112: albondigas | M112: 0.14 | N112: =+VLOOKUP(L112,'PRECIO PROVEEDORES'!$A$2:$B$716,2,0) -> 15378.581 | O112: =+M112*N112 -> 2153.0013 | Q112: pollo | R112: 0.15 | S112: =+VLOOKUP(Q112,'PRECIO PROVEEDORES'!$A$2:$B$716,2,0) -> 7700 | T112: =+R112*S112 -> 1155 | V112: brioche molde para tostadas | W112: 2 | X112: =+VLOOKUP(V112,'PRECIO PROVEEDORES'!$A$2:$B$716,2,0) -> 1100 | Y112: =+W112*X112 -> 2200 | AA112: focaccia | AB112: 0.25 | AC112: =+VLOOKUP(AA112,'PRECIO PROVEEDORES'!$A$2:$B$716,2,0) -> 9771 | AD112: =+AB112*AC112 -> 2442.75 | AF112: falafel | AG112: 0.09 | AH112: =+VLOOKUP(AF112,'PRECIO PROVEEDORES'!$A$2:$B$716,2,0) -> 5953.4143 | AI112: =+AG112*AH112 -> 535.80729
B113: queso danbo tregar | C113: 0.07 | D113: =+VLOOKUP(B113,'PRECIO PROVEEDORES'!$A$2:$B$716,2,0) -> 10697 | E113: =+C113*D113 -> 748.79 | G113: queso danbo tregar | H113: 0.07 | I113: =+VLOOKUP(G113,'PRECIO PROVEEDORES'!$A$2:$B$716,2,0) -> 10697 | J113: =+H113*I113 -> 748.79 | L113: queso Reggianito | M113: 0.1 | N113: =+VLOOKUP(L113,'PRECIO PROVEEDORES'!$A$2:$B$716,2,0) -> 17376 | O113: =+M113*N113 -> 1737.6 | Q113: Repollo blanco | R113: 0.05 | S113: =+VLOOKUP(Q113,'PRECIO PROVEEDORES'!$A$2:$B$716,2,0) -> 2025 | T113: =+R113*S113 -> 101.25 | V113: relleno sandwich de atun | W113: 0.31 | X113: =+VLOOKUP(V113,'PRECIO PROVEEDORES'!$A$2:$B$716,2,0) -> 11952.355 | Y113: =+W113*X113 -> 3705.23 | AA113: queso danbo tregar | AB113: 0.13 | AC113: =+VLOOKUP(AA113,'PRECIO PROVEEDORES'!$A$2:$B$716,2,0) -> 10697 | AD113: =+AB113*AC113 -> 1390.61 | AF113: mix de vegetales asados | AG113: 0.15 | AH113: =+VLOOKUP(AF113,'PRECIO PROVEEDORES'!$A$2:$B$716,2,0) -> 2972.2273 | AI113: =+AG113*AH113 -> 445.83409
B114: Fiambre, Jamon cocido | C114: 0.07 | D114: =+VLOOKUP(B114,'PRECIO PROVEEDORES'!$A$2:$B$716,2,0) -> 11881 | E114: =+C114*D114 -> 831.67 | G114: Hierbas frescas, Albahaca | H114: 0.02 | I114: =+VLOOKUP(G114,'PRECIO PROVEEDORES'!$A$2:$B$716,2,0) -> 4160 | J114: =+H114*I114 -> 83.2 | L114: salsa tomate albondigas | M114: 0.15 | N114: =+VLOOKUP(L114,'PRECIO PROVEEDORES'!$A$2:$B$716,2,0) -> 2112.0856 | O114: =+M114*N114 -> 316.81284 | Q114: Repollo rojo | R114: 0.05 | S114: =+VLOOKUP(Q114,'PRECIO PROVEEDORES'!$A$2:$B$716,2,0) -> 2700 | T114: =+R114*S114 -> 135 | V114: Hoja amarga, Rucula selvatica | W114: 0.03 | X114: =+VLOOKUP(V114,'PRECIO PROVEEDORES'!$A$2:$B$716,2,0) -> 9900 | Y114: =+W114*X114 -> 297 | AA114: Fiambre, Panceta ahumada | AB114: 0.045 | AC114: =+VLOOKUP(AA114,'PRECIO PROVEEDORES'!$A$2:$B$716,2,0) -> 18256.35 | AD114: =+AB114*AC114 -> 821.53575 | AF114: Hoja amarga, Rucula selvatica | AG114: 0.03 | AH114: =+VLOOKUP(AF114,'PRECIO PROVEEDORES'!$A$2:$B$716,2,0) -> 9900 | AI114: =+AG114*AH114 -> 297
B115: Papel de aluminio por lamina | C115: 0.5 | D115: =+VLOOKUP(B115,'PRECIO PROVEEDORES'!$A$2:$B$716,2,0) -> 160.5 | E115: =+C115*D115 -> 80.25 | G115: tomate redondo | H115: 0.04 | I115: =+VLOOKUP(G115,'PRECIO PROVEEDORES'!$A$2:$B$716,2,0) -> 1800 | J115: =+H115*I115 -> 72 | L115: baguetin de leche | M115: 1 | N115: =+VLOOKUP(L115,'PRECIO PROVEEDORES'!$A$2:$B$716,2,0) -> 1574 | O115: =+M115*N115 -> 1574 | Q115: Hoja amarga, Rucula selvatica | R115: 0.03 | S115: =+VLOOKUP(Q115,'PRECIO PROVEEDORES'!$A$2:$B$716,2,0) -> 9900 | T115: =+R115*S115 -> 297 | V115: papas asadas | W115: 0.15 | X115: =+VLOOKUP(V115,'PRECIO PROVEEDORES'!$A$2:$B$716,2,0) -> 1685.0215 | Y115: =+W115*X115 -> 252.75322 | AA115: Aji colorado | AB115: 0.06 | AC115: =+VLOOKUP(AA115,'PRECIO PROVEEDORES'!$A$2:$B$716,2,0) -> 4788 | AD115: =+AB115*AC115 -> 287.28 | AF115: cherrys confitados | AG115: 0.04 | AH115: =+VLOOKUP(AF115,'PRECIO PROVEEDORES'!$A$2:$B$716,2,0) -> 6130.5564 | AI115: =+AG115*AH115 -> 245.22226
G116: Papel de aluminio por lamina | H116: 0.5 | I116: =+VLOOKUP(G116,'PRECIO PROVEEDORES'!$A$2:$B$716,2,0) -> 160.5 | J116: =+H116*I116 -> 80.25 | L116: papas asadas | M116: 0.15 | N116: =+VLOOKUP(L116,'PRECIO PROVEEDORES'!$A$2:$B$716,2,0) -> 1685.0215 | O116: =+M116*N116 -> 252.75322 | Q116: yogurt griego | R116: 0.08 | S116: =+VLOOKUP(Q116,'PRECIO PROVEEDORES'!$A$2:$B$716,2,0) -> 7449.2 | T116: =+R116*S116 -> 595.936 | V116: mayonesa de pimiento | W116: 0.04 | X116: =+VLOOKUP(V116,'PRECIO PROVEEDORES'!$A$2:$B$716,2,0) -> 3891.911 | Y116: =+W116*X116 -> 155.67644 | AA116: pesto de albahaca | AB116: 0.015 | AC116: =+VLOOKUP(AA116,'PRECIO PROVEEDORES'!$A$2:$B$716,2,0) -> 0 | AD116: =+AB116*AC116 -> 0 | AF116: salsa agridulce | AG116: 0.05 | AH116: =+VLOOKUP(AF116,'PRECIO PROVEEDORES'!$A$2:$B$716,2,0) -> 9125.6667 | AI116: =+AG116*AH116 -> 456.28333
L117: mayonesa de pimiento | M117: 0.04 | N117: =+VLOOKUP(L117,'PRECIO PROVEEDORES'!$A$2:$B$716,2,0) -> 3891.911 | O117: =+M117*N117 -> 155.67644 | Q117: queso Reggianito | R117: 0.1 | S117: =+VLOOKUP(Q117,'PRECIO PROVEEDORES'!$A$2:$B$716,2,0) -> 17376 | T117: =+R117*S117 -> 1737.6 | V117: Papel de aluminio por lamina | W117: 0.5 | X117: =+VLOOKUP(V117,'PRECIO PROVEEDORES'!$A$2:$B$716,2,0) -> 160.5 | Y117: =+W117*X117 -> 80.25 | AA117: Aceite de oliva | AB117: 0.01 | AC117: =+VLOOKUP(AA117,'PRECIO PROVEEDORES'!$A$2:$B$716,2,0) -> 16595 | AD117: =+AB117*AC117 -> 165.95 | AF117: wrap | AG117: 1 | AH117: =+VLOOKUP(AF117,'PRECIO PROVEEDORES'!$A$2:$B$716,2,0) -> 253 | AI117: =+AG117*AH117 -> 253
L118: Papel de aluminio por lamina | M118: 0.5 | N118: =+VLOOKUP(L118,'PRECIO PROVEEDORES'!$A$2:$B$716,2,0) -> 160.5 | O118: =+M118*N118 -> 80.25 | Q118: wrap | R118: 1 | S118: =+VLOOKUP(Q118,'PRECIO PROVEEDORES'!$A$2:$B$716,2,0) -> 253 | T118: =+R118*S118 -> 253 | V118: dip 55 cc | W118: 0.5 | X118: =+VLOOKUP(V118,'PRECIO PROVEEDORES'!$A$2:$B$716,2,0) -> 155 | Y118: =+W118*X118 -> 77.5 | AA118: papas asadas | AB118: 0.15 | AC118: =+VLOOKUP(AA118,'PRECIO PROVEEDORES'!$A$2:$B$716,2,0) -> 1685.0215 | AD118: =+AB118*AC118 -> 252.75322 | AF118: Hoja amarga, Rucula selvatica | AG118: 0.04 | AH118: =+VLOOKUP(AF118,'PRECIO PROVEEDORES'!$A$2:$B$716,2,0) -> 9900 | AI118: =+AG118*AH118 -> 396
L119: dip 55 cc | M119: 0.5 | N119: =+VLOOKUP(L119,'PRECIO PROVEEDORES'!$A$2:$B$716,2,0) -> 155 | O119: =+M119*N119 -> 77.5 | Q119: papas asadas | R119: 0.15 | S119: =+VLOOKUP(Q119,'PRECIO PROVEEDORES'!$A$2:$B$716,2,0) -> 1685.0215 | T119: =+R119*S119 -> 252.75322 | V119: bandeja food track n 11 | W119: 0.5 | X119: =+VLOOKUP(V119,'PRECIO PROVEEDORES'!$A$2:$B$716,2,0) -> 86 | Y119: =+W119*X119 -> 43 | AA119: mayonesa de pimiento | AB119: 0.04 | AC119: =+VLOOKUP(AA119,'PRECIO PROVEEDORES'!$A$2:$B$716,2,0) -> 3891.911 | AD119: =+AB119*AC119 -> 155.67644 | AF119: Tomate cherry rojo | AG119: 0.04 | AH119: =+VLOOKUP(AF119,'PRECIO PROVEEDORES'!$A$2:$B$716,2,0) -> 4095 | AI119: =+AG119*AH119 -> 163.8
L120: bandeja food track n 11 | M120: 0.5 | N120: =+VLOOKUP(L120,'PRECIO PROVEEDORES'!$A$2:$B$716,2,0) -> 86 | O120: =+M120*N120 -> 43 | Q120: mayonesa de pimiento | R120: 0.04 | S120: =+VLOOKUP(Q120,'PRECIO PROVEEDORES'!$A$2:$B$716,2,0) -> 3891.911 | T120: =+R120*S120 -> 155.67644 | AA120: Papel de aluminio por lamina | AB120: 0.5 | AC120: =+VLOOKUP(AA120,'PRECIO PROVEEDORES'!$A$2:$B$716,2,0) -> 160.5 | AD120: =+AB120*AC120 -> 80.25 | AF120: papas asadas | AG120: 0.15 | AH120: =+VLOOKUP(AF120,'PRECIO PROVEEDORES'!$A$2:$B$716,2,0) -> 1685.0215 | AI120: =+AG120*AH120 -> 252.75322
Q121: Papel de aluminio por lamina | R121: 0.5 | S121: =+VLOOKUP(Q121,'PRECIO PROVEEDORES'!$A$2:$B$716,2,0) -> 160.5 | T121: =+R121*S121 -> 80.25 | AA121: dip 55 cc | AB121: 0.5 | AC121: =+VLOOKUP(AA121,'PRECIO PROVEEDORES'!$A$2:$B$716,2,0) -> 155 | AD121: =+AB121*AC121 -> 77.5 | AF121: mayonesa de pimiento | AG121: 0.04 | AH121: =+VLOOKUP(AF121,'PRECIO PROVEEDORES'!$A$2:$B$716,2,0) -> 3891.911 | AI121: =+AG121*AH121 -> 155.67644
Q122: dip 55 cc | R122: 0.5 | S122: =+VLOOKUP(Q122,'PRECIO PROVEEDORES'!$A$2:$B$716,2,0) -> 155 | T122: =+R122*S122 -> 77.5 | AA122: bandeja food track n 11 | AB122: 0.5 | AC122: =+VLOOKUP(AA122,'PRECIO PROVEEDORES'!$A$2:$B$716,2,0) -> 86 | AD122: =+AB122*AC122 -> 43 | AF122: Papel de aluminio por lamina | AG122: 0.5 | AH122: =+VLOOKUP(AF122,'PRECIO PROVEEDORES'!$A$2:$B$716,2,0) -> 160.5 | AI122: =+AG122*AH122 -> 80.25
Q123: bandeja food track n 11 | R123: 0.5 | S123: =+VLOOKUP(Q123,'PRECIO PROVEEDORES'!$A$2:$B$716,2,0) -> 86 | T123: =+R123*S123 -> 43 | AF123: dip 55 cc | AG123: 0.5 | AH123: =+VLOOKUP(AF123,'PRECIO PROVEEDORES'!$A$2:$B$716,2,0) -> 155 | AI123: =+AG123*AH123 -> 77.5
AF124: bandeja food track n 11 | AG124: 0.5 | AH124: =+VLOOKUP(AF124,'PRECIO PROVEEDORES'!$A$2:$B$716,2,0) -> 86 | AI124: =+AG124*AH124 -> 43
B127: Costo Total de la materia prima | E127: =SUM(E112:E126) -> 2108.4376 | G127: Costo Total de la materia prima | J127: =SUM(J112:J126) -> 1431.9676 | L127: Costo Total de la materia prima | O127: =SUM(O112:O126) -> 6390.5938 | Q127: Costo Total de la materia prima | T127: =SUM(T112:T126) -> 4883.9657 | V127: Costo Total de la materia prima | Y127: =SUM(Y112:Y126) -> 6811.4097 | AA127: Costo Total de la materia prima | AD127: =SUM(AD112:AD126) -> 5717.3054 | AF127: Costo Total de la materia prima | AI127: =SUM(AI112:AI126) -> 3402.1266
...

Sheet CAFETERIA TUESTE
B2: FLAT WHITE | G2: LATTE | L2: CAPPUCINO | Q2: CORTADO TUESTE
C3: Kg/Lt/Uni | D3: $ | E3: Total $ | H3: Kg/Lt/Uni | I3: $ | J3: Total $ | M3: Kg/Lt/Uni | N3: $ | O3: Total $ | R3: Kg/Lt/Uni | S3: $ | T3: Total $
B4: Café | C4: 0.019 | D4: =+VLOOKUP(B4,'PRECIO PROVEEDORES'!$A$2:$B$716,2,0) -> 47093 | E4: =+C4*D4 -> 894.767 | G4: Café | H4: 0.01 | I4: =+VLOOKUP(G4,'PRECIO PROVEEDORES'!$A$2:$B$716,2,0) -> 47093 | J4: =+H4*I4 -> 470.93 | L4: Café | M4: 0.01 | N4: =+VLOOKUP(L4,'PRECIO PROVEEDORES'!$A$2:$B$716,2,0) -> 47093 | O4: =+M4*N4 -> 470.93 | Q4: Café | R4: 0.01 | S4: =+VLOOKUP(Q4,'PRECIO PROVEEDORES'!$A$2:$B$716,2,0) -> 47093 | T4: =+R4*S4 -> 470.93
B5: leche | C5: 0.14 | D5: =+VLOOKUP(B5,'PRECIO PROVEEDORES'!$A$2:$B$716,2,0) -> 1940 | E5: =+C5*D5 -> 271.6 | G5: leche | H5: 0.24 | I5: =+VLOOKUP(G5,'PRECIO PROVEEDORES'!$A$2:$B$716,2,0) -> 1940 | J5: =+H5*I5 -> 465.6 | L5: leche | M5: 0.21 | N5: =+VLOOKUP(L5,'PRECIO PROVEEDORES'!$A$2:$B$716,2,0) -> 1940 | O5: =+M5*N5 -> 407.4 | Q5: leche | R5: 0.1 | S5: =+VLOOKUP(Q5,'PRECIO PROVEEDORES'!$A$2:$B$716,2,0) -> 1940 | T5: =+R5*S5 -> 194
B11: Costo Total de la materia prima | E11: =SUM(E4:E10) -> 1166.367 | G11: Costo Total de la materia prima | J11: =SUM(J4:J10) -> 936.53 | L11: Costo Total de la materia prima | O11: =SUM(O4:O10) -> 878.33 | Q11: Costo Total de la materia prima | T11: =SUM(T4:T10) -> 664.93
B12: Costo total de la preparación | E12: =SUM(E11) -> 1166.367 | G12: Costo total de la preparación | J12: =SUM(J11) -> 936.53 | L12: Costo total de la preparación | O12: =SUM(O11) -> 878.33 | Q12: Costo total de la preparación | T12: =SUM(T11) -> 664.93
B13: Costo porción | E13: =+E12 -> 1166.367 | G13: Costo porción | J13: =+J12 -> 936.53 | L13: Costo porción | O13: =+O12 -> 878.33 | Q13: Costo porción | T13: =+T12 -> 664.93
B14: Porcentaje costo materia prima establecida | D14: 0.3 | G14: Porcentaje costo materia prima establecida | I14: 0.3 | L14: Porcentaje costo materia prima establecida | N14: 0.3 | Q14: Porcentaje costo materia prima establecida | S14: 0.3
B15: Precio potencial de venta | E15: =+E13*3.33333333333333 -> 3887.89 | G15: Precio potencial de venta | J15: =+J13*3.33333333333333 -> 3121.7667 | L15: Precio potencial de venta | O15: =+O13*3.33333333333333 -> 2927.7667 | Q15: Precio potencial de venta | T15: =+T13*3.33333333333333 -> 2216.4333
B16: Precio de Venta | E16: 6300 | G16: Precio de Venta | J16: 6100 | L16: Precio de Venta | O16: 5900 | Q16: Precio de Venta | T16: 4800
E17: =+E16-E15 -> 2412.11 | J17: =+J16-J15 -> 2978.2333 | O17: 5000 | T17: =+T16-T15 -> 2583.5667
B18: Costo Real MP | E18: =E13/E16 -> 0.18513762 | G18: Costo Real MP | J18: =J13/J16 -> 0.15352951 | L18: Costo Real MP | O18: =O13/O16 -> 0.14886949 | Q18: Costo Real MP | T18: =T13/T16 -> 0.13852708
B21: MOCHA | G21: MOCHA BLANCO | L21: LATTES CON SYRUPS (vainilla,caramel,hazelnut) | Q21: PINK LATTE, GOLDEN, INDIAN, MATCHA, CHOCO CHAI
C22: Kg/Lt/Uni | D22: $ | E22: Total $ | H22: Kg/Lt/Uni | I22: $ | J22: Total $ | M22: Kg/Lt/Uni | N22: $ | O22: Total $ | R22: Kg/Lt/Uni | S22: $ | T22: Total $
B23: Café | C23: 0.019 | D23: =+VLOOKUP(B23,'PRECIO PROVEEDORES'!$A$2:$B$716,2,0) -> 47093 | E23: =+C23*D23 -> 894.767 | G23: Café | H23: 0.019 | I23: =+VLOOKUP(G23,'PRECIO PROVEEDORES'!$A$2:$B$716,2,0) -> 47093 | J23: =+H23*I23 -> 894.767 | L23: Café | M23: 0.01 | N23: =+VLOOKUP(L23,'PRECIO PROVEEDORES'!$A$2:$B$716,2,0) -> 47093 | O23: =+M23*N23 -> 470.93 | Q23: lattes en polvo | R23: 0.003 | S23: =+VLOOKUP(Q23,'PRECIO PROVEEDORES'!$A$2:$B$716,2,0) -> 287980 | T23: =+R23*S23 -> 863.94
B24: leche | C24: 0.23 | D24: =+VLOOKUP(B24,'PRECIO PROVEEDORES'!$A$2:$B$716,2,0) -> 1940 | E24: =+C24*D24 -> 446.2 | G24: leche | H24: 0.23 | I24: =+VLOOKUP(G24,'PRECIO PROVEEDORES'!$A$2:$B$716,2,0) -> 1940 | J24: =+H24*I24 -> 446.2 | L24: leche | M24: 0.24 | N24: =+VLOOKUP(L24,'PRECIO PROVEEDORES'!$A$2:$B$716,2,0) -> 1940 | O24: =+M24*N24 -> 465.6 | Q24: leche | R24: 0.24 | S24: =+VLOOKUP(Q24,'PRECIO PROVEEDORES'!$A$2:$B$716,2,0) -> 1940 | T24: =+R24*S24 -> 465.6
B25: Chips alpino con leche | C25: 0.04 | D25: =+VLOOKUP(B25,'PRECIO PROVEEDORES'!$A$2:$B$716,2,0) -> 9561 | E25: =+C25*D25 -> 382.44 | G25: leche condensada | H25: 0.02 | I25: =+VLOOKUP(G25,'PRECIO PROVEEDORES'!$A$2:$B$716,2,0) -> 12675 | J25: =+H25*I25 -> 253.5 | L25: syrup | M25: 0.018 | N25: =+VLOOKUP(L25,'PRECIO PROVEEDORES'!$A$2:$B$716,2,0) -> 15388 | O25: =+M25*N25 -> 276.984
B30: Costo Total de la materia prima | E30: =SUM(E23:E29) -> 1723.407 | G30: Costo Total de la materia prima | J30: =SUM(J23:J29) -> 1594.467 | L30: Costo Total de la materia prima | O30: =SUM(O23:O29) -> 1213.514 | Q30: Costo Total de la materia prima | T30: =SUM(T23:T29) -> 1329.54
B31: Costo total de la preparación | E31: =SUM(E30) -> 1723.407 | G31: Costo total de la preparación | J31: =SUM(J30) -> 1594.467 | L31: Costo total de la preparación | O31: =SUM(O30) -> 1213.514 | Q31: Costo total de la preparación | T31: =SUM(T30) -> 1329.54
B32: Costo porción | E32: =+E31 -> 1723.407 | G32: Costo porción | J32: =+J31 -> 1594.467 | L32: Costo porción | O32: =+O31 -> 1213.514 | Q32: Costo porción | T32: =+T31 -> 1329.54
B33: Porcentaje costo materia prima establecida | D33: 0.3 | G33: Porcentaje costo materia prima establecida | I33: 0.3 | L33: Porcentaje costo materia prima establecida | N33: 0.3 | Q33: Porcentaje costo materia prima establecida | S33: 0.3 | U33: matcha | V33: 5800
B34: Precio potencial de venta | E34: =+E32*3.33333333333333 -> 5744.69 | G34: Precio potencial de venta | J34: =+J32*3.33333333333333 -> 5314.89 | L34: Precio potencial de venta | O34: =+O32*3.33333333333333 -> 4045.0467 | Q34: Precio potencial de venta | T34: =+T32*3.33333333333333 -> 4431.8
B35: Precio de Venta | C35: iced | E35: 6800 | G35: Precio de Venta | H35: iced | J35: 6800 | L35: Precio de Venta | O35: 6700 | Q35: Precio de Venta | T35: 6000
E36: =+E35-E34 -> 1055.31 | J36: =+J35-J34 -> 1485.11 | O36: =+O35-O34 -> 2654.9533 | T36: =+T35-T34 -> 1568.2
B37: Costo Real MP | E37: =E32/E35 -> 0.25344221 | G37: Costo Real MP | J37: =J32/J35 -> 0.23448044 | L37: Costo Real MP | O37: =O32/O35 -> 0.18112149 | Q37: Costo Real MP | T37: =T32/T35 -> 0.22159
B40: BABYCHINO | G40: CHOCO CALIENTE | L40: CHOCO BLANCO | Q40: CHAI LATTE
C41: Kg/Lt/Uni | D41: $ | E41: Total $ | H41: Kg/Lt/Uni | I41: $ | J41: Total $ | M41: Kg/Lt/Uni | N41: $ | O41: Total $ | R41: Kg/Lt/Uni | S41: $ | T41: Total $
B42: leche condensada | C42: 0.025 | D42: =+VLOOKUP(B42,'PRECIO PROVEEDORES'!$A$2:$B$716,2,0) -> 12675 | E42: =+C42*D42 -> 316.875 | G42: leche | H42: 0.23 | I42: =+VLOOKUP(G42,'PRECIO PROVEEDORES'!$A$2:$B$716,2,0) -> 1940 | J42: =+H42*I42 -> 446.2 | L42: leche | M42: 0.23 | N42: =+VLOOKUP(L42,'PRECIO PROVEEDORES'!$A$2:$B$716,2,0) -> 1940 | O42: =+M42*N42 -> 446.2 | Q42: leche | R42: 0.24 | S42: =+VLOOKUP(Q42,'PRECIO PROVEEDORES'!$A$2:$B$716,2,0) -> 1940 | T42: =+R42*S42 -> 465.6
B43: leche | C43: 0.21 | D43: =+VLOOKUP(B43,'PRECIO PROVEEDORES'!$A$2:$B$716,2,0) -> 1940 | E43: =+C43*D43 -> 407.4 | G43: syrup | H43: 0.052 | I43: =+VLOOKUP(G43,'PRECIO PROVEEDORES'!$A$2:$B$716,2,0) -> 15388 | J43: =+H43*I43 -> 800.176 | L43: leche condensada | M43: 0.04 | N43: =+VLOOKUP(L43,'PRECIO PROVEEDORES'!$A$2:$B$716,2,0) -> 12675 | O43: =+M43*N43 -> 507 | Q43: te buena vibra chai | R43: 0.003 | S43: =+VLOOKUP(Q43,'PRECIO PROVEEDORES'!$A$2:$B$716,2,0) -> 90016 | T43: =+R43*S43 -> 270.048
B44: malvaviscos | C44: 0.009 | D44: =+VLOOKUP(B44,'PRECIO PROVEEDORES'!$A$2:$B$716,2,0) -> 22687.5 | E44: =+C44*D44 -> 204.1875 | G44: Chips alpino con leche | H44: 0.025 | I44: =+VLOOKUP(G44,'PRECIO PROVEEDORES'!$A$2:$B$716,2,0) -> 9561 | J44: =+H44*I44 -> 239.025
B49: Costo Total de la materia prima | E49: =SUM(E42:E48) -> 928.4625 | G49: Costo Total de la materia prima | J49: =SUM(J42:J48) -> 1485.401 | L49: Costo Total de la materia prima | O49: =SUM(O42:O48) -> 953.2 | Q49: Costo Total de la materia prima | T49: =SUM(T42:T48) -> 735.648
B50: Costo total de la preparación | E50: =SUM(E49) -> 928.4625 | G50: Costo total de la preparación | J50: =SUM(J49) -> 1485.401 | L50: Costo total de la preparación | O50: =SUM(O49) -> 953.2 | Q50: Costo total de la preparación | T50: =SUM(T49) -> 735.648
B51: Costo porción | E51: =+E50 -> 928.4625 | G51: Costo porción | J51: =+J50 -> 1485.401 | L51: Costo porción | O51: =+O50 -> 953.2 | Q51: Costo porción | T51: =+T50 -> 735.648
B52: Porcentaje costo materia prima establecida | D52: 0.3 | G52: Porcentaje costo materia prima establecida | I52: 0.3 | L52: Porcentaje costo materia prima establecida | N52: 0.3 | Q52: Porcentaje costo materia prima establecida | S52: 0.3
B53: Precio potencial de venta | E53: =+E51*3.33333333333333 -> 3094.875 | G53: Precio potencial de venta | J53: =+J51*3.33333333333333 -> 4951.3367 | L53: Precio potencial de venta | O53: =+O51*3.33333333333333 -> 3177.3333 | Q53: Precio potencial de venta | T53: =+T51*3.33333333333333 -> 2452.16
B54: Precio de Venta | E54: 4100 | G54: Precio de Venta | J54: 6000 | L54: Precio de Venta | O54: 6000 | Q54: Precio de Venta | T54: 5900
E55: =+E54-E53 -> 1005.125 | J55: =+J54-J53 -> 1048.6633 | O55: =+O54-O53 -> 2822.6667 | T55: =+T54-T53 -> 3447.84
B56: Costo Real MP | E56: =E51/E54 -> 0.22645427 | G56: Costo Real MP | J56: =J51/J54 -> 0.24756683 | L56: Costo Real MP | O56: =O51/O54 -> 0.15886667 | Q56: Costo Real MP | T56: =T51/T54 -> 0.1246861
B59: DOPPIO | G59: AMERICANO DOBLE SHOT | L59: ESPRESSO SIMPLE | Q59: LUNGO
C60: Kg/Lt/Uni | D60: $ | E60: Total $ | H60: Kg/Lt/Uni | I60: $ | J60: Total $ | M60: Kg/Lt/Uni | N60: $ | O60: Total $ | R60: Kg/Lt/Uni | S60: $ | T60: Total $
B61: Café | C61: 0.019 | D61: =+VLOOKUP(B61,'PRECIO PROVEEDORES'!$A$2:$B$716,2,0) -> 47093 | E61: =+C61*D61 -> 894.767 | G61: Café | H61: 0.019 | I61: =+VLOOKUP(G61,'PRECIO PROVEEDORES'!$A$2:$B$716,2,0) -> 47093 | J61: =+H61*I61 -> 894.767 | L61: Café | M61: 0.01 | N61: =+VLOOKUP(L61,'PRECIO PROVEEDORES'!$A$2:$B$716,2,0) -> 47093 | O61: =+M61*N61 -> 470.93 | Q61: Café | R61: 0.01 | S61: =+VLOOKUP(Q61,'PRECIO PROVEEDORES'!$A$2:$B$716,2,0) -> 47093 | T61: =+R61*S61 -> 470.93
B68: Costo Total de la materia prima | E68: =SUM(E61:E67) -> 894.767 | G68: Costo Total de la materia prima | J68: =SUM(J61:J67) -> 894.767 | L68: Costo Total de la materia prima | O68: =SUM(O61:O67) -> 470.93 | Q68: Costo Total de la materia prima | T68: =SUM(T61:T67) -> 470.93
B69: Costo total de la preparación | E69: =SUM(E68) -> 894.767 | G69: Costo total de la preparación | J69: =SUM(J68) -> 894.767 | L69: Costo total de la preparación | O69: =SUM(O68) -> 470.93 | Q69: Costo total de la preparación | T69: =SUM(T68) -> 470.93
B70: Costo porción | E70: =+E69 -> 894.767 | G70: Costo porción | J70: =+J69 -> 894.767 | L70: Costo porción | O70: =+O69 -> 470.93 | Q70: Costo porción | T70: =+T69 -> 470.93
B71: Porcentaje costo materia prima establecida | D71: 0.3 | G71: Porcentaje costo materia prima establecida | I71: 0.3 | L71: Porcentaje costo materia prima establecida | N71: 0.3 | Q71: Porcentaje costo materia prima establecida | S71: 0.3
B72: Precio potencial de venta | E72: =+E70*3.33333333333333 -> 2982.5567 | G72: Precio potencial de venta | J72: =+J70*3.33333333333333 -> 2982.5567 | L72: Precio potencial de venta | O72: =+O70*3.33333333333333 -> 1569.7667 | Q72: Precio potencial de venta | T72: =+T70*3.33333333333333 -> 1569.7667
B73: Precio de Venta | E73: 4700 | G73: Precio de Venta | J73: 5000 | L73: Precio de Venta | O73: 4400 | Q73: Precio de Venta | T73: 4700
E74: =+E73-E72 -> 1717.4433 | J74: =+J73-J72 -> 2017.4433 | O74: =+O73-O72 -> 2830.2333 | T74: =+T73-T72 -> 3130.2333
B75: Costo Real MP | E75: =E70/E73 -> 0.19037596 | G75: Costo Real MP | J75: =J70/J73 -> 0.1789534 | L75: Costo Real MP | O75: =O70/O73 -> 0.10702955 | Q75: Costo Real MP | T75: =T70/T73 -> 0.10019787
B78: ICED FLAT WHITE | G78: ICED LATTES CON SYRUPS vainilla, avellanas, caramelo | L78: ICED PISTACHO/TOFFE LATTE | Q78: TONIC ESPRESSO
C79: Kg/Lt/Uni | D79: $ | E79: Total $ | H79: Kg/Lt/Uni | I79: $ | J79: Total $ | M79: Kg/Lt/Uni | N79: $ | O79: Total $ | R79: Kg/Lt/Uni | S79: $ | T79: Total $
B80: Café | C80: 0.019 | D80: =+VLOOKUP(B80,'PRECIO PROVEEDORES'!$A$2:$B$716,2,0) -> 47093 | E80: =+C80*D80 -> 894.767 | G80: Café | H80: 0.01 | I80: =+VLOOKUP(G80,'PRECIO PROVEEDORES'!$A$2:$B$716,2,0) -> 47093 | J80: =+H80*I80 -> 470.93 | L80: Café | M80: 0.01 | N80: =+VLOOKUP(L80,'PRECIO PROVEEDORES'!$A$2:$B$716,2,0) -> 47093 | O80: =+M80*N80 -> 470.93 | Q80: Café | R80: 0.019 | S80: =+VLOOKUP(Q80,'PRECIO PROVEEDORES'!$A$2:$B$716,2,0) -> 47093 | T80: =+R80*S80 -> 894.767
B81: leche | C81: 0.12 | D81: =+VLOOKUP(B81,'PRECIO PROVEEDORES'!$A$2:$B$716,2,0) -> 1940 | E81: =+C81*D81 -> 232.8 | G81: leche | H81: 0.15 | I81: =+VLOOKUP(G81,'PRECIO PROVEEDORES'!$A$2:$B$716,2,0) -> 1940 | J81: =+H81*I81 -> 291 | L81: leche | M81: 0.15 | N81: =+VLOOKUP(L81,'PRECIO PROVEEDORES'!$A$2:$B$716,2,0) -> 1940 | O81: =+M81*N81 -> 291 | Q81: agua tonica | R81: 0.2 | S81: =+VLOOKUP(Q81,'PRECIO PROVEEDORES'!$A$2:$B$716,2,0) -> 1755.33 | T81: =+R81*S81 -> 351.066
B82: hielo | C82: 0.12 | D82: =+VLOOKUP(B82,'PRECIO PROVEEDORES'!$A$2:$B$716,2,0) -> 400 | E82: =+C82*D82 -> 48 | G82: hielo | H82: 0.15 | I82: =+VLOOKUP(G82,'PRECIO PROVEEDORES'!$A$2:$B$716,2,0) -> 400 | J82: =+H82*I82 -> 60 | L82: hielo | M82: 0.15 | N82: =+VLOOKUP(L82,'PRECIO PROVEEDORES'!$A$2:$B$716,2,0) -> 400 | O82: =+M82*N82 -> 60 | Q82: hielo | R82: 0.15 | S82: =+VLOOKUP(Q82,'PRECIO PROVEEDORES'!$A$2:$B$716,2,0) -> 400 | T82: =+R82*S82 -> 60
G83: syrup | H83: 0.052 | I83: =+VLOOKUP(G83,'PRECIO PROVEEDORES'!$A$2:$B$716,2,0) -> 15388 | J83: =+H83*I83 -> 800.176 | L83: salsa pistacho toffee | M83: 0.03 | N83: =+VLOOKUP(L83,'PRECIO PROVEEDORES'!$A$2:$B$716,2,0) -> 18007 | O83: =+M83*N83 -> 540.21
B88: Costo Total de la materia prima | E88: =SUM(E80:E87) -> 1175.567 | G88: Costo Total de la materia prima | J88: =SUM(J80:J87) -> 1622.106 | L88: Costo Total de la materia prima | O88: =SUM(O80:O87) -> 1362.14 | Q88: Costo Total de la materia prima | T88: =SUM(T80:T87) -> 1305.833
B89: Costo total de la preparación | E89: =SUM(E88) -> 1175.567 | G89: Costo total de la preparación | J89: =SUM(J88) -> 1622.106 | L89: Costo total de la preparación | O89: =SUM(O88) -> 1362.14 | Q89: Costo total de la preparación | T89: =SUM(T88) -> 1305.833
B90: Costo porción | E90: =+E89 -> 1175.567 | G90: Costo porción | J90: =+J89 -> 1622.106 | L90: Costo porción | O90: =+O89 -> 1362.14 | Q90: Costo porción | T90: =+T89 -> 1305.833
B91: Porcentaje costo materia prima establecida | D91: 0.3 | G91: Porcentaje costo materia prima establecida | I91: 0.3 | L91: Porcentaje costo materia prima establecida | N91: 0.3 | Q91: Porcentaje costo materia prima establecida | S91: 0.3
B92: Precio potencial de venta | E92: =+E90*3.33333333333333 -> 3918.5567 | G92: Precio potencial de venta | J92: =+J90*3.33333333333333 -> 5407.02 | L92: Precio potencial de venta | O92: =+O90*3.33333333333333 -> 4540.4667 | Q92: Precio potencial de venta | T92: =+T90*3.33333333333333 -> 4352.7767
B93: Precio de Venta | E93: 6500 | G93: Precio de Venta | J93: 6900 | L93: Precio de Venta | O93: 7700 | Q93: Precio de Venta | T93: 5800
E94: =+E93-E92 -> 2581.4433 | J94: =+J93-J92 -> 1492.98 | O94: =+O93-O92 -> 3159.5333 | T94: =+T93-T92 -> 1447.2233
B95: Costo Real MP | E95: =E90/E93 -> 0.18085646 | G95: Costo Real MP | J95: =J90/J93 -> 0.23508783 | L95: Costo Real MP | O95: =O90/O93 -> 0.1769013 | Q95: Costo Real MP | T95: =T90/T93 -> 0.22514362
B98: LEMON AMERICANO | G98: LATTES CON SYRUPS PISTACCHO/ TOFFEE | L98: SHAKEN HIBISCUS AND LEMON TEA | Q98: GINGER MOJITO
C99: Kg/Lt/Uni | D99: $ | E99: Total $ | H99: Kg/Lt/Uni | I99: $ | J99: Total $ | M99: Kg/Lt/Uni | N99: $ | O99: Total $ | R99: Kg/Lt/Uni | S99: $ | T99: Total $
B100: hielo | C100: 0.12 | D100: =+VLOOKUP(B100,'PRECIO PROVEEDORES'!$A$2:$B$716,2,0) -> 400 | E100: =+C100*D100 -> 48 | G100: Café | H100: 0.01 | I100: =+VLOOKUP(G100,'PRECIO PROVEEDORES'!$A$2:$B$716,2,0) -> 47093 | J100: =+H100*I100 -> 470.93 | L100: agua con gas | M100: 0.23 | N100: =+VLOOKUP(L100,'PRECIO PROVEEDORES'!$A$2:$B$716,2,0) -> 558.33 | O100: =+M100*N100 -> 128.4159 | Q100: almibar de jengibre | R100: 0.025 | S100: =+VLOOKUP(Q100,'PRECIO PROVEEDORES'!$A$2:$B$716,2,0) -> 3600 | T100: =+R100*S100 -> 90
B101: almibar limon | C101: 0.045 | D101: =+VLOOKUP(B101,'PRECIO PROVEEDORES'!$A$2:$B$716,2,0) -> 12676 | E101: =+C101*D101 -> 570.42 | G101: leche | H101: 0.15 | I101: =+VLOOKUP(G101,'PRECIO PROVEEDORES'!$A$2:$B$716,2,0) -> 1940 | J101: =+H101*I101 -> 291 | L101: almibar limon | M101: 0.045 | N101: =+VLOOKUP(L101,'PRECIO PROVEEDORES'!$A$2:$B$716,2,0) -> 12676 | O101: =+M101*N101 -> 570.42 | Q101: agua con gas | R101: 0.23 | S101: =+VLOOKUP(Q101,'PRECIO PROVEEDORES'!$A$2:$B$716,2,0) -> 558.33 | T101: =+R101*S101 -> 128.4159
B102: Café | C102: 0.019 | D102: =+VLOOKUP(B102,'PRECIO PROVEEDORES'!$A$2:$B$716,2,0) -> 47093 | E102: =+C102*D102 -> 894.767 | G102: salsa pistacho toffee | H102: 0.052 | I102: =+VLOOKUP(G102,'PRECIO PROVEEDORES'!$A$2:$B$716,2,0) -> 18007 | J102: =+H102*I102 -> 936.364 | L102: hielo | M102: 0.16 | N102: =+VLOOKUP(L102,'PRECIO PROVEEDORES'!$A$2:$B$716,2,0) -> 400 | O102: =+M102*N102 -> 64 | Q102: almibar limon | R102: 0.052 | S102: =+VLOOKUP(Q102,'PRECIO PROVEEDORES'!$A$2:$B$716,2,0) -> 12676 | T102: =+R102*S102 -> 659.152
L103: hibiscus | M103: 0.06 | N103: =+VLOOKUP(L103,'PRECIO PROVEEDORES'!$A$2:$B$716,2,0) -> 634 | O103: =+M103*N103 -> 38.04 | S103: ='PRECIO PROVEEDORES'!Q438 -> 0
B107: Costo Total de la materia prima | E107: =SUM(E100:E106) -> 1513.187 | G107: Costo Total de la materia prima | J107: =SUM(J100:J106) -> 1698.294 | L107: Costo Total de la materia prima | O107: =SUM(O100:O106) -> 800.8759 | Q107: Costo Total de la materia prima | T107: =SUM(T100:T106) -> 877.5679
B108: Costo total de la preparación | E108: =SUM(E107) -> 1513.187 | G108: Costo total de la preparación | J108: =SUM(J107) -> 1698.294 | L108: Costo total de la preparación | O108: =SUM(O107) -> 800.8759 | Q108: Costo total de la preparación | T108: =SUM(T107) -> 877.5679
B109: Costo porción | E109: =+E108 -> 1513.187 | G109: Costo porción | J109: =+J108 -> 1698.294 | L109: Costo porción | O109: =+O108 -> 800.8759 | Q109: Costo porción | T109: =+T108 -> 877.5679
B110: Porcentaje costo materia prima establecida | D110: 0.3 | G110: Porcentaje costo materia prima establecida | I110: 0.3 | L110: Porcentaje costo materia prima establecida | N110: 0.3 | Q110: Porcentaje costo materia prima establecida | S110: 0.3
B111: Precio potencial de venta | E111: =+E109*3.33333333333333 -> 5043.9567 | G111: Precio potencial de venta | J111: =+J109*3.33333333333333 -> 5660.98 | L111: Precio potencial de venta | O111: =+O109*3.33333333333333 -> 2669.5863 | Q111: Precio potencial de venta | T111: =+T109*3.33333333333333 -> 2925.2263
B112: Precio de Venta | E112: 6000 | G112: Precio de Venta | J112: 7500 | L112: Precio de Venta | O112: 6500 | Q112: Precio de Venta | T112: 6500
E113: =+E112-E111 -> 956.04333 | J113: =+J112-J111 -> 1839.02 | O113: =+O112-O111 -> 3830.4137 | T113: =+T112-T111 -> 3574.7737
B114: Costo Real MP | E114: =E109/E112 -> 0.25219783 | G114: Costo Real MP | J114: =J109/J112 -> 0.2264392 | L114: Costo Real MP | O114: =O109/O112 -> 0.12321168 | Q114: Costo Real MP | T114: =T109/T112 -> 0.13501045
B117: ICED TEA ROSE | G117: JUGO NARANJA | L117: LIMONADA MENTA Y JENGIBRE | Q117: PINK LIMO
C118: Kg/Lt/Uni | D118: $ | E118: Total $ | H118: Kg/Lt/Uni | I118: $ | J118: Total $ | M118: Kg/Lt/Uni | N118: $ | O118: Total $ | R118: Kg/Lt/Uni | S118: $ | T118: Total $
B119: frutos rojos | C119: 0.02 | D119: =+VLOOKUP(B119,'PRECIO PROVEEDORES'!$A$2:$B$716,2,0) -> 2250.4 | E119: =+C119*D119 -> 45.008 | G119: naranja exprimida | H119: 0.2 | I119: =+VLOOKUP(G119,'PRECIO PROVEEDORES'!$A$2:$B$716,2,0) -> 2880 | J119: =+H119*I119 -> 576 | L119: almibar limon | M119: 0.052 | N119: =+VLOOKUP(L119,'PRECIO PROVEEDORES'!$A$2:$B$716,2,0) -> 12676 | O119: =+M119*N119 -> 659.152 | Q119: almibar limon | R119: 0.045 | S119: =+VLOOKUP(Q119,'PRECIO PROVEEDORES'!$A$2:$B$716,2,0) -> 12676 | T119: =+R119*S119 -> 570.42
B120: Naranja jugo | C120: 0.044 | D120: =+VLOOKUP(B120,'PRECIO PROVEEDORES'!$A$2:$B$716,2,0) -> 1440 | E120: =+C120*D120 -> 63.36 | G120: hielo | H120: 0.1 | I120: =+VLOOKUP(G120,'PRECIO PROVEEDORES'!$A$2:$B$716,2,0) -> 400 | J120: =+H120*I120 -> 40 | L120: almibar de jengibre | M120: 0.045 | N120: =+VLOOKUP(L120,'PRECIO PROVEEDORES'!$A$2:$B$716,2,0) -> 3600 | O120: =+M120*N120 -> 162 | Q120: Mix de frutos rojos congelados | R120: 0.08 | S120: =+VLOOKUP(Q120,'PRECIO PROVEEDORES'!$A$2:$B$716,2,0) -> 12874.4 | T120: =+R120*S120 -> 1029.952
B121: Mix de frutos rojos congelados | C121: 0.02 | D121: =+VLOOKUP(B121,'PRECIO PROVEEDORES'!$A$2:$B$716,2,0) -> 12874.4 | E121: =+C121*D121 -> 257.488 | L121: hielo | M121: 0.1 | N121: =+VLOOKUP(L121,'PRECIO PROVEEDORES'!$A$2:$B$716,2,0) -> 400 | O121: =+M121*N121 -> 40
B122: azucar | C122: 0.007 | D122: =+VLOOKUP(B122,'PRECIO PROVEEDORES'!$A$2:$B$716,2,0) -> 1352 | E122: =+C122*D122 -> 9.464 | N122: ='PRECIO PROVEEDORES'!L457 -> 0
B123: hielo | C123: 0.06 | D123: =+VLOOKUP(B123,'PRECIO PROVEEDORES'!$A$2:$B$716,2,0) -> 400 | E123: =+C123*D123 -> 24
B126: Costo Total de la materia prima | E126: =SUM(E119:E125) -> 399.32 | G126: Costo Total de la materia prima | J126: =SUM(J119:J125) -> 616 | L126: Costo Total de la materia prima | O126: =SUM(O119:O125) -> 861.152 | Q126: Costo Total de la materia prima | T126: =SUM(T119:T125) -> 1600.372
B127: Costo total de la preparación | E127: =SUM(E126) -> 399.32 | G127: Costo total de la preparación | J127: =SUM(J126) -> 616 | L127: Costo total de la preparación | O127: =SUM(O126) -> 861.152 | Q127: Costo total de la preparación | T127: =SUM(T126) -> 1600.372
B128: Costo porción | E128: =+E127 -> 399.32 | G128: Costo porción | J128: =+J127 -> 616 | L128: Costo porción | O128: =+O127 -> 861.152 | Q128: Costo porción | T128: =+T127 -> 1600.372
B129: Porcentaje costo materia prima establecida | D129: 0.3 | G129: Porcentaje costo materia prima establecida | I129: 0.3 | L129: Porcentaje costo materia prima establecida | N129: 0.3 | Q129: Porcentaje costo materia prima establecida | S129: 0.3
B130: Precio potencial de venta | E130: =+E128*3.33333333333333 -> 1331.0667 | G130: Precio potencial de venta | J130: =+J128*3.33333333333333 -> 2053.3333 | L130: Precio potencial de venta | O130: =+O128*3.33333333333333 -> 2870.5067 | Q130: Precio potencial de venta | T130: =+T128*3.33333333333333 -> 5334.5733
B131: Precio de Venta | E131: 6500 | G131: Precio de Venta | J131: 5300 | L131: Precio de Venta | O131: 6000 | Q131: Precio de Venta | T131: 6800
E132: =+E131-E130 -> 5168.9333 | J132: =+J131-J130 -> 3246.6667 | O132: =+O131-O130 -> 3129.4933 | T132: =+T131-T130 -> 1465.4267
B133: Costo Real MP | E133: =E128/E131 -> 0.061433846 | G133: Costo Real MP | J133: =J128/J131 -> 0.11622642 | L133: Costo Real MP | O133: =O128/O131 -> 0.14352533 | Q133: Costo Real MP | T133: =T128/T131 -> 0.23534882
B136: POMELADA CON ROMERO | G136: MARACUYA FRESH | L136: TINTO DE VERANO | Q136: LICUADO
C137: Kg/Lt/Uni | D137: $ | E137: Total $ | H137: Kg/Lt/Uni | I137: $ | J137: Total $ | M137: Kg/Lt/Uni | N137: $ | O137: Total $ | R137: Kg/Lt/Uni | S137: $ | T137: Total $
B138: almibar pomelo | C138: 0.052 | D138: =+VLOOKUP(B138,'PRECIO PROVEEDORES'!$A$2:$B$716,2,0) -> 4708 | E138: =+C138*D138 -> 244.816 | G138: azucar | H138: 0.04 | I138: =+VLOOKUP(G138,'PRECIO PROVEEDORES'!$A$2:$B$716,2,0) -> 1352 | J138: =+H138*I138 -> 54.08 | L138: san felipe vino | M138: 0.15 | N138: =+VLOOKUP(L138,'PRECIO PROVEEDORES'!$A$2:$B$716,2,0) -> 4000 | O138: =+M138*N138 -> 600 | Q138: Banana | R138: 0.1 | S138: =+VLOOKUP(Q138,'PRECIO PROVEEDORES'!$A$2:$B$716,2,0) -> 3360 | T138: =+R138*S138 -> 336
B139: almibar limon | C139: 0.045 | D139: =+VLOOKUP(B139,'PRECIO PROVEEDORES'!$A$2:$B$716,2,0) -> 12676 | E139: =+C139*D139 -> 570.42 | G139: maracuya | H139: 0.1 | I139: =+VLOOKUP(G139,'PRECIO PROVEEDORES'!$A$2:$B$716,2,0) -> 11679 | J139: =+H139*I139 -> 1167.9 | L139: vermouth | M139: 0.05 | N139: =+VLOOKUP(L139,'PRECIO PROVEEDORES'!$A$2:$B$716,2,0) -> 8666 | O139: =+M139*N139 -> 433.3 | Q139: leche entera | R139: 0.15 | S139: =+VLOOKUP(Q139,'PRECIO PROVEEDORES'!$A$2:$B$716,2,0) -> 2017.07 | T139: =+R139*S139 -> 302.5605
B140: hielo | C140: 0.1 | D140: =+VLOOKUP(B140,'PRECIO PROVEEDORES'!$A$2:$B$716,2,0) -> 400 | E140: =+C140*D140 -> 40 | G140: hielo | H140: 0.08 | I140: =+VLOOKUP(G140,'PRECIO PROVEEDORES'!$A$2:$B$716,2,0) -> 400 | J140: =+H140*I140 -> 32 | L140: pomelo rosado | M140: 0.1 | N140: =+VLOOKUP(L140,'PRECIO PROVEEDORES'!$A$2:$B$716,2,0) -> 2185 | O140: =+M140*N140 -> 218.5
G141: almibar de jengibre | H141: 0.045 | I141: =+VLOOKUP(G141,'PRECIO PROVEEDORES'!$A$2:$B$716,2,0) -> 3600 | J141: =+H141*I141 -> 162 | L141: limon | M141: 0.1 | N141: =+VLOOKUP(L141,'PRECIO PROVEEDORES'!$A$2:$B$716,2,0) -> 3000 | O141: =+M141*N141 -> 300 | S141: ='PRECIO PROVEEDORES'!Q476 -> 0
G142: Hierbas frescas, Menta bariada | H142: 0.008 | I142: =+VLOOKUP(G142,'PRECIO PROVEEDORES'!$A$2:$B$716,2,0) -> 18304 | J142: =+H142*I142 -> 146.432 | L142: naranja jugo | M142: 0.1 | N142: =+VLOOKUP(L142,'PRECIO PROVEEDORES'!$A$2:$B$716,2,0) -> 1440 | O142: =+M142*N142 -> 144
L143: hielo | M143: 0.3 | N143: =+VLOOKUP(L143,'PRECIO PROVEEDORES'!$A$2:$B$716,2,0) -> 400 | O143: =+M143*N143 -> 120
...

Sheet PASTELERIA PARA TUESTE
B2: COOKIE DOBLE CHOCO | G2: TARTA CHOCOLATE Y PISTACHO | L2: MEDIALUNA 90 GRS
C3: Kg/Lt/Uni | D3: $ | E3: Total $ | H3: Kg/Lt/Uni | I3: $ | J3: Total $ | M3: Kg/Lt/Uni | N3: $ | O3: Total $
B4: manteca ramolac | C4: 0.45 | D4: =+VLOOKUP(B4,'PRECIO PROVEEDORES'!$A$2:$B$716,2,0) -> 13662 | E4: =+C4*D4 -> 6147.9 | G4: pistacho natural | H4: 0.004 | I4: =+VLOOKUP(G4,'PRECIO PROVEEDORES'!$A$2:$B$716,2,0) -> 78338 | J4: =+H4*I4 -> 313.352 | L4: harina 0000 | M4: 1.8 | N4: =+VLOOKUP(L4,'PRECIO PROVEEDORES'!$A$2:$B$716,2,0) -> 1043.22 | O4: =+M4*N4 -> 1877.796
B5: azucar | C5: 0.4 | D5: =+VLOOKUP(B5,'PRECIO PROVEEDORES'!$A$2:$B$716,2,0) -> 1352 | E5: =+C5*D5 -> 540.8 | G5: Fenix 83 ( con leche) | H5: 0.03 | I5: =+VLOOKUP(G5,'PRECIO PROVEEDORES'!$A$2:$B$716,2,0) -> 36068 | J5: =+H5*I5 -> 1082.04 | L5: harina 000 | M5: 0.2 | N5: =+VLOOKUP(L5,'PRECIO PROVEEDORES'!$A$2:$B$716,2,0) -> 890 | O5: =+M5*N5 -> 178
B6: Azucar negro | C6: 0.4 | D6: =+VLOOKUP(B6,'PRECIO PROVEEDORES'!$A$2:$B$716,2,0) -> 1624.77 | E6: =+C6*D6 -> 649.908 | G6: crema de leche | H6: 0.02 | I6: =+VLOOKUP(G6,'PRECIO PROVEEDORES'!$A$2:$B$716,2,0) -> 10203 | J6: =+H6*I6 -> 204.06 | L6: azucar | M6: 0.25 | N6: =+VLOOKUP(L6,'PRECIO PROVEEDORES'!$A$2:$B$716,2,0) -> 1352 | O6: =+M6*N6 -> 338
B7: Huevos | C7: 4 | D7: =+VLOOKUP(B7,'PRECIO PROVEEDORES'!$A$2:$B$716,2,0) -> 192 | E7: =+C7*D7 -> 768 | G7: miel | H7: 0.002 | I7: =+VLOOKUP(G7,'PRECIO PROVEEDORES'!$A$2:$B$716,2,0) -> 6062 | J7: =+H7*I7 -> 12.124 | L7: levadura seca | M7: 0.02 | N7: =+VLOOKUP(L7,'PRECIO PROVEEDORES'!$A$2:$B$716,2,0) -> 17780 | O7: =+M7*N7 -> 355.6
B8: harina 0000 | C8: 0.92 | D8: =+VLOOKUP(B8,'PRECIO PROVEEDORES'!$A$2:$B$716,2,0) -> 1043.22 | E8: =+C8*D8 -> 959.7624 | G8: frambuesa congelada | H8: 0.03 | I8: =+VLOOKUP(G8,'PRECIO PROVEEDORES'!$A$2:$B$716,2,0) -> 24829 | J8: =+H8*I8 -> 744.87 | L8: sal fina | M8: 0.04 | N8: =+VLOOKUP(L8,'PRECIO PROVEEDORES'!$A$2:$B$716,2,0) -> 1633 | O8: =+M8*N8 -> 65.32
B9: bicarbonato de sodio | C9: 0.01 | D9: =+VLOOKUP(B9,'PRECIO PROVEEDORES'!$A$2:$B$716,2,0) -> 2517 | E9: =+C9*D9 -> 25.17 | G9: azucar | H9: 0.01 | I9: =+VLOOKUP(G9,'PRECIO PROVEEDORES'!$A$2:$B$716,2,0) -> 1352 | J9: =+H9*I9 -> 13.52 | L9: leche | M9: 0.5 | N9: =+VLOOKUP(L9,'PRECIO PROVEEDORES'!$A$2:$B$716,2,0) -> 1940 | O9: =+M9*N9 -> 970
B10: Polvo para hornear | C10: 0.014 | D10: =+VLOOKUP(B10,'PRECIO PROVEEDORES'!$A$2:$B$716,2,0) -> 6040 | E10: =+C10*D10 -> 84.56 | L10: huevos | M10: 6 | N10: =+VLOOKUP(L10,'PRECIO PROVEEDORES'!$A$2:$B$716,2,0) -> 192 | O10: =+M10*N10 -> 1152
B11: sal fina | C11: 0.014 | D11: =+VLOOKUP(B11,'PRECIO PROVEEDORES'!$A$2:$B$716,2,0) -> 1633 | E11: =+C11*D11 -> 22.862 | L11: miel | M11: 0.06 | N11: =+VLOOKUP(L11,'PRECIO PROVEEDORES'!$A$2:$B$716,2,0) -> 6062 | O11: =+M11*N11 -> 363.72
B12: Fenix 83 ( con leche) | C12: 0.25 | D12: =+VLOOKUP(B12,'PRECIO PROVEEDORES'!$A$2:$B$716,2,0) -> 36068 | E12: =+C12*D12 -> 9017 | L12: manteca | M12: 0.57 | N12: =+VLOOKUP(L12,'PRECIO PROVEEDORES'!$A$2:$B$716,2,0) -> 12000 | O12: =+M12*N12 -> 6840
B13: Fenix 86 (semi amargo) | C13: 0.25 | D13: =+VLOOKUP(B13,'PRECIO PROVEEDORES'!$A$2:$B$716,2,0) -> 39988 | E13: =+C13*D13 -> 9997
B14: Esencia de vainilla | C14: 0.01 | D14: =+VLOOKUP(B14,'PRECIO PROVEEDORES'!$A$2:$B$716,2,0) -> 2118 | E14: =+C14*D14 -> 21.18
B19: Costo Total de la materia prima | E19: =SUM(E4:E18) -> 28234.142 | G19: Costo Total de la materia prima | J19: =SUM(J4:J18) -> 2369.966 | L19: Costo Total de la materia prima | O19: =SUM(O4:O18) -> 12140.436
B20: Costo total de la preparación | E20: =SUM(E19) -> 28234.142 | G20: Costo total de la preparación | J20: =SUM(J19) -> 2369.966 | L20: Costo total de la preparación | O20: =SUM(O19) -> 12140.436
B21: Costo porción | E21: =+E20/29 -> 973.59112 | G21: Costo porción | J21: =+J20 -> 2369.966 | L21: Costo porción | O21: =+O20/42 -> 289.058
B22: Porcentaje costo materia prima establecida | D22: 0.3 | G22: Porcentaje costo materia prima establecida | I22: 0.3 | L22: Porcentaje costo materia prima establecida | N22: 0.3
B23: Precio potencial de venta | E23: =+E21*3.33333333333333 -> 3245.3037 | G23: Precio potencial de venta | J23: =+J21*3.33333333333333 -> 7899.8867 | L23: Precio potencial de venta | O23: =+O21*3.33333333333333 -> 963.52667
B24: Precio de Venta a tueste | E24: 2140 | G24: Precio de Venta | J24: 6800 | O24: 1200
E25: =+E24-E23 -> -1105.3037 | J25: =+J24-J23 -> -1099.8867 | O25: =+O24-O23 -> 236.47333
B26: Costo Real MP | E26: =E21/E24 -> 0.45494912 | G26: Costo Real MP | J26: =J21/J24 -> 0.34852441 | L26: Costo Real MP | O26: =O21/O24 -> 0.24088167
B29: CROISSANT 140 grs | G29: COOKIE DE FRAMBUESA Y CHOCO BLANCO | L29: KEYLIME PIE
C30: Kg/Lt/Uni | D30: $ | E30: Total $ | H30: Kg/Lt/Uni | I30: $ | J30: Total $ | M30: Kg/Lt/Uni | N30: $ | O30: Total $
B31: harina 0000 | C31: 2 | D31: =+VLOOKUP(B31,'PRECIO PROVEEDORES'!$A$2:$B$716,2,0) -> 1043.22 | E31: =+C31*D31 -> 2086.44 | G31: manteca | H31: 0.32 | I31: =+VLOOKUP(G31,'PRECIO PROVEEDORES'!$A$2:$B$716,2,0) -> 12000 | J31: =+H31*I31 -> 3840 | L31: lima | M31: 0.265 | N31: =+VLOOKUP(L31,'PRECIO PROVEEDORES'!$A$2:$B$716,2,0) -> 5400 | O31: =+M31*N31 -> 1431
B32: harina 000 | C32: 0.5 | D32: =+VLOOKUP(B32,'PRECIO PROVEEDORES'!$A$2:$B$716,2,0) -> 890 | E32: =+C32*D32 -> 445 | G32: azucar | H32: 0.4 | I32: =+VLOOKUP(G32,'PRECIO PROVEEDORES'!$A$2:$B$716,2,0) -> 1352 | J32: =+H32*I32 -> 540.8 | L32: leche condensada | M32: 0.88 | N32: =+VLOOKUP(L32,'PRECIO PROVEEDORES'!$A$2:$B$716,2,0) -> 12675 | O32: =+M32*N32 -> 11154
B33: azucar | C33: 0.25 | D33: =+VLOOKUP(B33,'PRECIO PROVEEDORES'!$A$2:$B$716,2,0) -> 1352 | E33: =+C33*D33 -> 338 | G33: huevos | H33: 2 | I33: =+VLOOKUP(G33,'PRECIO PROVEEDORES'!$A$2:$B$716,2,0) -> 192 | J33: =+H33*I33 -> 384 | L33: huevos | M33: 6 | N33: =+VLOOKUP(L33,'PRECIO PROVEEDORES'!$A$2:$B$716,2,0) -> 192 | O33: =+M33*N33 -> 1152
B34: levadura seca | C34: 0.016 | D34: =+VLOOKUP(B34,'PRECIO PROVEEDORES'!$A$2:$B$716,2,0) -> 17780 | E34: =+C34*D34 -> 284.48 | G34: harina 0000 | H34: 0.535 | I34: =+VLOOKUP(G34,'PRECIO PROVEEDORES'!$A$2:$B$716,2,0) -> 1043.22 | J34: =+H34*I34 -> 558.1227 | L34: harina 000 | M34: 0.18 | N34: =+VLOOKUP(L34,'PRECIO PROVEEDORES'!$A$2:$B$716,2,0) -> 890 | O34: =+M34*N34 -> 160.2
B35: huevos | C35: 3 | D35: =+VLOOKUP(B35,'PRECIO PROVEEDORES'!$A$2:$B$716,2,0) -> 192 | E35: =+C35*D35 -> 576 | G35: Polvo para hornear | H35: 0.01 | I35: =+VLOOKUP(G35,'PRECIO PROVEEDORES'!$A$2:$B$716,2,0) -> 6040 | J35: =+H35*I35 -> 60.4 | L35: canela en polvo | M35: 0.001 | N35: =+VLOOKUP(L35,'PRECIO PROVEEDORES'!$A$2:$B$716,2,0) -> 10061.64 | O35: =+M35*N35 -> 10.06164
B36: manteca | C36: 0.7 | D36: =+VLOOKUP(B36,'PRECIO PROVEEDORES'!$A$2:$B$716,2,0) -> 12000 | E36: =+C36*D36 -> 8400 | G36: Esencia de vainilla | H36: 0.01 | I36: =+VLOOKUP(G36,'PRECIO PROVEEDORES'!$A$2:$B$716,2,0) -> 2118 | J36: =+H36*I36 -> 21.18 | L36: azucar | M36: 0.152 | N36: =+VLOOKUP(L36,'PRECIO PROVEEDORES'!$A$2:$B$716,2,0) -> 1352 | O36: =+M36*N36 -> 205.504
B37: sal fina | C37: 0.044 | D37: =+VLOOKUP(B37,'PRECIO PROVEEDORES'!$A$2:$B$716,2,0) -> 1633 | E37: =+C37*D37 -> 71.852 | G37: Fenix 90 blanco | H37: 0.2 | I37: =+VLOOKUP(G37,'PRECIO PROVEEDORES'!$A$2:$B$716,2,0) -> 34892 | J37: =+H37*I37 -> 6978.4 | L37: bicarbonato de sodio | M37: 0.003 | N37: =+VLOOKUP(L37,'PRECIO PROVEEDORES'!$A$2:$B$716,2,0) -> 2517 | O37: =+M37*N37 -> 7.551
G38: frambuesa congelada | H38: 0.12 | I38: =+VLOOKUP(G38,'PRECIO PROVEEDORES'!$A$2:$B$716,2,0) -> 24829 | J38: =+H38*I38 -> 2979.48 | L38: sal fina | M38: 0.001 | N38: =+VLOOKUP(L38,'PRECIO PROVEEDORES'!$A$2:$B$716,2,0) -> 1633 | O38: =+M38*N38 -> 1.633
B39: POR KG MASA | L39: manteca | M39: 0.167 | N39: =+VLOOKUP(L39,'PRECIO PROVEEDORES'!$A$2:$B$716,2,0) -> 12000 | O39: =+M39*N39 -> 2004
L40: leche | M40: 0.067 | N40: =+VLOOKUP(L40,'PRECIO PROVEEDORES'!$A$2:$B$716,2,0) -> 1940 | O40: =+M40*N40 -> 129.98
L41: miel | M41: 0.017 | N41: =+VLOOKUP(L41,'PRECIO PROVEEDORES'!$A$2:$B$716,2,0) -> 6062 | O41: =+M41*N41 -> 103.054
L42: Crema de leche | M42: 0.12 | N42: =+VLOOKUP(L42,'PRECIO PROVEEDORES'!$A$2:$B$716,2,0) -> 10203 | O42: =+M42*N42 -> 1224.36
L43: almendras | M43: 0.01 | N43: =+VLOOKUP(L43,'PRECIO PROVEEDORES'!$A$2:$B$716,2,0) -> 25872 | O43: =+M43*N43 -> 258.72
L44: Fenix 90 blanco | M44: 0.01 | N44: =+VLOOKUP(L44,'PRECIO PROVEEDORES'!$A$2:$B$716,2,0) -> 34892 | O44: =+M44*N44 -> 348.92
B46: Costo Total de la materia prima | E46: =SUM(E31:E45) -> 12201.772 | G46: Costo Total de la materia prima | J46: =SUM(J31:J45) -> 15362.383 | L46: Costo Total de la materia prima | O46: =SUM(O31:O45) -> 18190.984
B47: Costo total de la preparación | E47: =SUM(E46) -> 12201.772 | G47: Costo total de la preparación | J47: =SUM(J46) -> 15362.383 | L47: Costo total de la preparación | O47: =SUM(O46) -> 18190.984
B48: Costo porción | E48: =+E47/28 -> 435.77757 | G48: Costo porción | J48: =+J47/16 -> 960.14892 | L48: Costo porción | O48: =+O47/8 -> 2273.873
B49: Porcentaje costo materia prima establecida | D49: 0.3 | G49: Porcentaje costo materia prima establecida | I49: 0.3 | L49: Porcentaje costo materia prima establecida | N49: 0.3
B50: Precio potencial de venta | E50: =+E48*3.33333333333333 -> 1452.5919 | G50: Precio potencial de venta | J50: =+J48*3.33333333333333 -> 3200.4964 | L50: Precio potencial de venta | O50: =+O48*3.33333333333333 -> 7579.5765
B51: Precio de Venta a tueste | E51: 1307 | G51: Precio de Venta a tueste | J51: 2758 | L51: Precio de Venta a tueste | O51: 6816
E52: =+E51-E50 -> -145.5919 | J52: =+J51-J50 -> -442.4964 | O52: =+O51-O50 -> -763.57652
B53: Costo Real MP | E53: =E48/E51 -> 0.33341819 | G53: Costo Real MP | J53: =J48/J51 -> 0.34813231 | L53: Costo Real MP | O53: =O48/O51 -> 0.33360812
B56: COOKIE RED VELVET CON FROSTING | G56: COOKIE DE AVENA Y FRUTOS SECOS | L56: PAN DE CHOCOLATE Y FRAMBUESA
C57: Kg/Lt/Uni | D57: $ | E57: Total $ | H57: Kg/Lt/Uni | I57: $ | J57: Total $ | M57: Kg/Lt/Uni | N57: $ | O57: Total $
B58: manteca | C58: 0.0225 | D58: =+VLOOKUP(B58,'PRECIO PROVEEDORES'!$A$2:$B$716,2,0) -> 12000 | E58: =+C58*D58 -> 270 | G58: manteca | H58: 0.275 | I58: =+VLOOKUP(G58,'PRECIO PROVEEDORES'!$A$2:$B$716,2,0) -> 12000 | J58: =+H58*I58 -> 3300 | L58: harina 0000 | M58: 1.8 | N58: =+VLOOKUP(L58,'PRECIO PROVEEDORES'!$A$2:$B$716,2,0) -> 1043.22 | O58: =+M58*N58 -> 1877.796
B59: azucar | C59: 0.2 | D59: =+VLOOKUP(B59,'PRECIO PROVEEDORES'!$A$2:$B$716,2,0) -> 1352 | E59: =+C59*D59 -> 270.4 | G59: azucar | H59: 0.475 | I59: =+VLOOKUP(G59,'PRECIO PROVEEDORES'!$A$2:$B$716,2,0) -> 1352 | J59: =+H59*I59 -> 642.2 | L59: harina 000 | M59: 0.2 | N59: =+VLOOKUP(L59,'PRECIO PROVEEDORES'!$A$2:$B$716,2,0) -> 890 | O59: =+M59*N59 -> 178
B60: Azucar negro | C60: 0.2 | D60: =+VLOOKUP(B60,'PRECIO PROVEEDORES'!$A$2:$B$716,2,0) -> 1624.77 | E60: =+C60*D60 -> 324.954 | G60: azucar negro | H60: 0.125 | I60: =+VLOOKUP(G60,'PRECIO PROVEEDORES'!$A$2:$B$716,2,0) -> 1624.77 | J60: =+H60*I60 -> 203.09625 | L60: azucar | M60: 0.35 | N60: =+VLOOKUP(L60,'PRECIO PROVEEDORES'!$A$2:$B$716,2,0) -> 1352 | O60: =+M60*N60 -> 473.2
B61: colorante rojo | C61: 0.003 | D61: ='PRECIO PROVEEDORES'!B359 -> 5400 | E61: =+C61*D61 -> 16.2 | G61: huevos | H61: 2 | I61: =+VLOOKUP(G61,'PRECIO PROVEEDORES'!$A$2:$B$716,2,0) -> 192 | J61: =+H61*I61 -> 384 | L61: levadura seca | M61: 0.02 | N61: =+VLOOKUP(L61,'PRECIO PROVEEDORES'!$A$2:$B$716,2,0) -> 17780 | O61: =+M61*N61 -> 355.6
B62: esencia de vainilla | C62: 0.005 | D62: =+VLOOKUP(B62,'PRECIO PROVEEDORES'!$A$2:$B$716,2,0) -> 2118 | E62: =+C62*D62 -> 10.59 | G62: harina 0000 | H62: 0.33 | I62: =+VLOOKUP(G62,'PRECIO PROVEEDORES'!$A$2:$B$716,2,0) -> 1043.22 | J62: =+H62*I62 -> 344.2626 | L62: sal fina | M62: 0.04 | N62: =+VLOOKUP(L62,'PRECIO PROVEEDORES'!$A$2:$B$716,2,0) -> 1633 | O62: =+M62*N62 -> 65.32
B63: harina 0000 | C63: 0.42 | D63: =+VLOOKUP(B63,'PRECIO PROVEEDORES'!$A$2:$B$716,2,0) -> 1043.22 | E63: =+C63*D63 -> 438.1524 | G63: polvo para hornear | H63: 0.008 | I63: =+VLOOKUP(G63,'PRECIO PROVEEDORES'!$A$2:$B$716,2,0) -> 6040 | J63: =+H63*I63 -> 48.32 | L63: leche | M63: 0.5 | N63: =+VLOOKUP(L63,'PRECIO PROVEEDORES'!$A$2:$B$716,2,0) -> 1940 | O63: =+M63*N63 -> 970
B64: Cacao amargo | C64: 0.02 | D64: =+VLOOKUP(B64,'PRECIO PROVEEDORES'!$A$2:$B$716,2,0) -> 13205 | E64: =+C64*D64 -> 264.1 | G64: Avena arrollada | H64: 0.4 | I64: =+VLOOKUP(G64,'PRECIO PROVEEDORES'!$A$2:$B$716,2,0) -> 2180 | J64: =+H64*I64 -> 872 | L64: huevos | M64: 6 | N64: =+VLOOKUP(L64,'PRECIO PROVEEDORES'!$A$2:$B$716,2,0) -> 192 | O64: =+M64*N64 -> 1152
B65: bicarbonato de sodio | C65: 0.004 | D65: =+VLOOKUP(B65,'PRECIO PROVEEDORES'!$A$2:$B$716,2,0) -> 2517 | E65: =+C65*D65 -> 10.068 | G65: leche | H65: 0.025 | I65: =+VLOOKUP(G65,'PRECIO PROVEEDORES'!$A$2:$B$716,2,0) -> 1940 | J65: =+H65*I65 -> 48.5 | L65: miel | M65: 0.06 | N65: =+VLOOKUP(L65,'PRECIO PROVEEDORES'!$A$2:$B$716,2,0) -> 6062 | O65: =+M65*N65 -> 363.72
B66: queso crema | C66: 0.084 | D66: =+VLOOKUP(B66,'PRECIO PROVEEDORES'!$A$2:$B$716,2,0) -> 6600 | E66: =+C66*D66 -> 554.4 | G66: Pasas de uva negra | H66: 0.075 | I66: =+VLOOKUP(G66,'PRECIO PROVEEDORES'!$A$2:$B$716,2,0) -> 6292 | J66: =+H66*I66 -> 471.9 | L66: manteca | M66: 0.72 | N66: =+VLOOKUP(L66,'PRECIO PROVEEDORES'!$A$2:$B$716,2,0) -> 12000 | O66: =+M66*N66 -> 8640
B67: azucar impalpable | C67: 0.042 | D67: =+VLOOKUP(B67,'PRECIO PROVEEDORES'!$A$2:$B$716,2,0) -> 1684 | E67: =+C67*D67 -> 70.728 | G67: Nueces cuartos | H67: 0.075 | I67: =+VLOOKUP(G67,'PRECIO PROVEEDORES'!$A$2:$B$716,2,0) -> 27769.5 | J67: =+H67*I67 -> 2082.7125 | L67: Fenix 86 (semi amargo) | M67: 0.3 | N67: =+VLOOKUP(L67,'PRECIO PROVEEDORES'!$A$2:$B$716,2,0) -> 39988 | O67: =+M67*N67 -> 11996.4
B68: almidon de maiz | C68: 0.007 | D68: =+VLOOKUP(B68,'PRECIO PROVEEDORES'!$A$2:$B$716,2,0) -> 2191 | E68: =+C68*D68 -> 15.337 | G68: mani tostado sin sal | H68: 0.075 | I68: =+VLOOKUP(G68,'PRECIO PROVEEDORES'!$A$2:$B$716,2,0) -> 5987 | J68: =+H68*I68 -> 449.025 | L68: cacao amargo | M68: 0.04 | N68: =+VLOOKUP(L68,'PRECIO PROVEEDORES'!$A$2:$B$716,2,0) -> 13205 | O68: =+M68*N68 -> 528.2
B69: huevos | C69: 2 | D69: =+VLOOKUP(B69,'PRECIO PROVEEDORES'!$A$2:$B$716,2,0) -> 192 | E69: =+C69*D69 -> 384 | L69: azucar impalpable | M69: 0.1 | N69: =+VLOOKUP(L69,'PRECIO PROVEEDORES'!$A$2:$B$716,2,0) -> 1684 | O69: =+M69*N69 -> 168.4
B70: Fenix 90 blanco | C70: 0.3 | D70: =+VLOOKUP(B70,'PRECIO PROVEEDORES'!$A$2:$B$716,2,0) -> 34892 | E70: =+C70*D70 -> 10467.6 | L70: almidon de maiz | M70: 0.015 | N70: =+VLOOKUP(L70,'PRECIO PROVEEDORES'!$A$2:$B$716,2,0) -> 2191 | O70: =+M70*N70 -> 32.865
B71: leche | C71: 0.02 | D71: =+VLOOKUP(B71,'PRECIO PROVEEDORES'!$A$2:$B$716,2,0) -> 1940 | E71: =+C71*D71 -> 38.8 | L71: frambuesa congelada | M71: 0.2 | N71: =+VLOOKUP(L71,'PRECIO PROVEEDORES'!$A$2:$B$716,2,0) -> 24829 | O71: =+M71*N71 -> 4965.8
B72: polvo para hornear | C72: 0.008 | D72: =+VLOOKUP(B72,'PRECIO PROVEEDORES'!$A$2:$B$716,2,0) -> 6040 | E72: =+C72*D72 -> 48.32
B75: Costo Total de la materia prima | E75: =SUM(E58:E72) -> 13183.649 | G75: Costo Total de la materia prima | J75: =SUM(J58:J72) -> 8846.0163 | L75: Costo Total de la materia prima | O75: =SUM(O58:O72) -> 31767.301
B76: Costo total de la preparación | E76: =SUM(E75) -> 13183.649 | G76: Costo total de la preparación | J76: =SUM(J75) -> 8846.0163 | L76: Costo total de la preparación | O76: =SUM(O75) -> 31767.301
B77: Costo porción | E77: =+E76/14 -> 941.68924 | G77: Costo porción | J77: =+J76/18 -> 491.44535 | L77: Costo porción | O77: =+O76/24 -> 1323.6375
B78: Porcentaje costo materia prima establecida | D78: 0.3 | G78: Porcentaje costo materia prima establecida | I78: 0.3 | L78: Porcentaje costo materia prima establecida | N78: 0.3
B79: Precio potencial de venta | E79: =+E77*3.33333333333333 -> 3138.9641 | G79: Precio potencial de venta | J79: =+J77*3.33333333333333 -> 1638.1512 | L79: Precio potencial de venta | O79: =+O77*3.33333333333333 -> 4412.1251
B80: Precio de Venta | E80: 4500 | G80: Precio de Venta | L80: Precio de Venta | O80: 4600
E81: =+E80-E79 -> 1361.0359 | J81: =+J80-J79 -> -1638.1512 | O81: =+O80-O79 -> 187.87486
B82: Costo Real MP | E82: =E77/E80 -> 0.20926428 | G82: Costo Real MP | J82: =J77/J80 -> #DIV/0! | L82: Costo Real MP | O82: =O77/O80 -> 0.28774729
B85: ALFAJOR DE ALMENDRAS | G85: ALFACOOKIE CON DDL | L85: TORTA BRUCE
C86: Kg/Lt/Uni | D86: $ | E86: Total $ | H86: Kg/Lt/Uni | I86: $ | J86: Total $ | M86: Kg/Lt/Uni | N86: $ | O86: Total $
B87: tapitas alfajor de almendras | C87: 2 | D87: =+VLOOKUP(B87,'PRECIO PROVEEDORES'!$A$2:$B$716,2,0) -> 248.90715 | E87: =+C87*D87 -> 497.81429 | G87: dulce de leche | H87: 0.16 | I87: =+VLOOKUP(G87,'PRECIO PROVEEDORES'!$A$2:$B$716,2,0) -> 3356 | J87: =+H87*I87 -> 536.96 | L87: leche | M87: 0.32 | N87: =+VLOOKUP(L87,'PRECIO PROVEEDORES'!$A$2:$B$716,2,0) -> 1940 | O87: =+M87*N87 -> 620.8
B88: Dulce de leche | C88: 0.035 | D88: =+VLOOKUP(B88,'PRECIO PROVEEDORES'!$A$2:$B$716,2,0) -> 3356 | E88: =+C88*D88 -> 117.46 | G88: manteca | H88: 0.45 | I88: =+VLOOKUP(G88,'PRECIO PROVEEDORES'!$A$2:$B$716,2,0) -> 12000 | J88: =+H88*I88 -> 5400 | L88: manteca | M88: 0.145 | N88: =+VLOOKUP(L88,'PRECIO PROVEEDORES'!$A$2:$B$716,2,0) -> 12000 | O88: =+M88*N88 -> 1740
B89: Chips alpino con leche | C89: 0.02 | D89: =+VLOOKUP(B89,'PRECIO PROVEEDORES'!$A$2:$B$716,2,0) -> 9561 | E89: =+C89*D89 -> 191.22 | G89: azucar | H89: 0.4 | I89: =+VLOOKUP(G89,'PRECIO PROVEEDORES'!$A$2:$B$716,2,0) -> 1352 | J89: =+H89*I89 -> 540.8 | L89: huevos | M89: 4 | N89: =+VLOOKUP(L89,'PRECIO PROVEEDORES'!$A$2:$B$716,2,0) -> 192 | O89: =+M89*N89 -> 768
B90: Almendras | C90: 0.005 | D90: =+VLOOKUP(B90,'PRECIO PROVEEDORES'!$A$2:$B$716,2,0) -> 25872 | E90: =+C90*D90 -> 129.36 | G90: azucar negro | H90: 0.4 | I90: =+VLOOKUP(G90,'PRECIO PROVEEDORES'!$A$2:$B$716,2,0) -> 1624.77 | J90: =+H90*I90 -> 649.908 | L90: azucar | M90: 0.45 | N90: =+VLOOKUP(L90,'PRECIO PROVEEDORES'!$A$2:$B$716,2,0) -> 1352 | O90: =+M90*N90 -> 608.4
G91: huevos | H91: 4 | I91: =+VLOOKUP(G91,'PRECIO PROVEEDORES'!$A$2:$B$716,2,0) -> 192 | J91: =+H91*I91 -> 768 | L91: harina 0000 | M91: 0.31 | N91: =+VLOOKUP(L91,'PRECIO PROVEEDORES'!$A$2:$B$716,2,0) -> 1043.22 | O91: =+M91*N91 -> 323.3982
G92: harina 0000 | H92: 0.92 | I92: =+VLOOKUP(G92,'PRECIO PROVEEDORES'!$A$2:$B$716,2,0) -> 1043.22 | J92: =+H92*I92 -> 959.7624 | L92: cacao amargo | M92: 0.06 | N92: =+VLOOKUP(L92,'PRECIO PROVEEDORES'!$A$2:$B$716,2,0) -> 13205 | O92: =+M92*N92 -> 792.3
G93: bicarbonato de sodio | H93: 0.01 | I93: =+VLOOKUP(G93,'PRECIO PROVEEDORES'!$A$2:$B$716,2,0) -> 2517 | J93: =+H93*I93 -> 25.17 | L93: bicarbonato de sodio | M93: 0.005 | N93: =+VLOOKUP(L93,'PRECIO PROVEEDORES'!$A$2:$B$716,2,0) -> 2517 | O93: =+M93*N93 -> 12.585
G94: polvo para hornear | H94: 0.014 | I94: =+VLOOKUP(G94,'PRECIO PROVEEDORES'!$A$2:$B$716,2,0) -> 6040 | J94: =+H94*I94 -> 84.56 | L94: cafe instantaneo | M94: 0.005 | N94: =+VLOOKUP(L94,'PRECIO PROVEEDORES'!$A$2:$B$716,2,0) -> 36376.47 | O94: =+M94*N94 -> 181.88235
G95: sal fina | H95: 0.014 | I95: =+VLOOKUP(G95,'PRECIO PROVEEDORES'!$A$2:$B$716,2,0) -> 1633 | J95: =+H95*I95 -> 22.862 | L95: dulce de leche | M95: 0.6 | N95: =+VLOOKUP(L95,'PRECIO PROVEEDORES'!$A$2:$B$716,2,0) -> 3356 | O95: =+M95*N95 -> 2013.6
G96: Fenix 83 ( con leche) | H96: 0.25 | I96: =+VLOOKUP(G96,'PRECIO PROVEEDORES'!$A$2:$B$716,2,0) -> 36068 | J96: =+H96*I96 -> 9017 | L96: Crema de leche | M96: 0.2 | N96: =+VLOOKUP(L96,'PRECIO PROVEEDORES'!$A$2:$B$716,2,0) -> 10203 | O96: =+M96*N96 -> 2040.6
G97: Fenix 86 (semi amargo) | H97: 0.25 | I97: =+VLOOKUP(G97,'PRECIO PROVEEDORES'!$A$2:$B$716,2,0) -> 39988 | J97: =+H97*I97 -> 9997 | L97: Fenix 86 (semi amargo) | M97: 0.2 | N97: =+VLOOKUP(L97,'PRECIO PROVEEDORES'!$A$2:$B$716,2,0) -> 39988 | O97: =+M97*N97 -> 7997.6
G98: esencia de vainilla | H98: 0.01 | I98: =+VLOOKUP(G98,'PRECIO PROVEEDORES'!$A$2:$B$716,2,0) -> 2118 | J98: =+H98*I98 -> 21.18 | L98: Chips alpino con leche | M98: 0.05 | N98: =+VLOOKUP(L98,'PRECIO PROVEEDORES'!$A$2:$B$716,2,0) -> 9561 | O98: =+M98*N98 -> 478.05
B102: Costo Total de la materia prima | E102: =SUM(E87:E101) -> 935.85429 | G102: Costo Total de la materia prima | J102: =SUM(J87:J101) -> 28023.202 | L102: Costo Total de la materia prima | O102: =SUM(O87:O101) -> 17577.216
B103: Costo total de la preparación | E103: =SUM(E102) -> 935.85429 | G103: Costo total de la preparación | J103: =SUM(J102) -> 28023.202 | L103: Costo total de la preparación | O103: =SUM(O102) -> 17577.216
B104: Costo porción | E104: =+E103 -> 935.85429 | G104: Costo porción | J104: =+J103/29 -> 966.31732 | L104: Costo porción | O104: =+O103 -> 17577.216
B105: Porcentaje costo materia prima establecida | D105: 0.3 | G105: Porcentaje costo materia prima establecida | I105: 0.3 | L105: Porcentaje costo materia prima establecida | N105: 0.3
B106: Precio potencial de venta | E106: =+E104*3.33333333333333 -> 3119.5143 | G106: Precio potencial de venta | J106: =+J104*3.33333333333333 -> 3221.0577 | L106: Precio potencial de venta | O106: =+O104*3.33333333333333 -> 58590.718
B107: Precio de Venta a tueste | E107: 2565 | G107: Precio de Venta a tueste | L107: Precio de Venta | O107: 53226
E108: =+E107-E106 -> -554.51432 | J108: =+J107-J106 -> -3221.0577 | O108: =+O107-O106 -> -5364.7185
B109: Costo Real MP | E109: =E104/E107 -> 0.36485548 | G109: Costo Real MP | J109: =J104/J107 -> #DIV/0! | L109: Costo Real MP | O109: =O104/O107 -> 0.33023739
B112: CARROT CAKE | G112: CHEESECAKE FRUTOS ROJOS | L112: BUDIN CHOCOLATE, BANANA Y NUEZ
C113: Kg/Lt/Uni | D113: $ | E113: Total $ | H113: Kg/Lt/Uni | I113: $ | J113: Total $ | M113: Kg/Lt/Uni | N113: $ | O113: Total $
B114: zanahoria | C114: 0.4 | D114: =+VLOOKUP(B114,'PRECIO PROVEEDORES'!$A$2:$B$716,2,0) -> 1650 | E114: =+C114*D114 -> 660 | G114: galletas caseras | H114: 0.3 | I114: =+VLOOKUP(G114,'PRECIO PROVEEDORES'!$A$2:$B$716,2,0) -> 4063.4264 | J114: =+H114*I114 -> 1219.0279 | L114: banana | M114: 0.27 | N114: =+VLOOKUP(L114,'PRECIO PROVEEDORES'!$A$2:$B$716,2,0) -> 3360 | O114: =+M114*N114 -> 907.2
B115: coco rallado | C115: 0.06 | D115: =+VLOOKUP(B115,'PRECIO PROVEEDORES'!$A$2:$B$716,2,0) -> 11721 | E115: =+C115*D115 -> 703.26 | G115: manteca | H115: 0.08 | I115: =+VLOOKUP(G115,'PRECIO PROVEEDORES'!$A$2:$B$716,2,0) -> 12000 | J115: =+H115*I115 -> 960 | L115: manzana verde | M115: 0.155 | N115: =+VLOOKUP(L115,'PRECIO PROVEEDORES'!$A$2:$B$716,2,0) -> 2850 | O115: =+M115*N115 -> 441.75
B116: azucar | C116: 0.3 | D116: =+VLOOKUP(B116,'PRECIO PROVEEDORES'!$A$2:$B$716,2,0) -> 1352 | E116: =+C116*D116 -> 405.6 | G116: queso crema | H116: 0.8 | I116: =+VLOOKUP(G116,'PRECIO PROVEEDORES'!$A$2:$B$716,2,0) -> 6600 | J116: =+H116*I116 -> 5280 | L116: azucar | M116: 0.25 | N116: =+VLOOKUP(L116,'PRECIO PROVEEDORES'!$A$2:$B$716,2,0) -> 1352 | O116: =+M116*N116 -> 338
B117: esencia de vainilla | C117: 0.005 | D117: =+VLOOKUP(B117,'PRECIO PROVEEDORES'!$A$2:$B$716,2,0) -> 2118 | E117: =+C117*D117 -> 10.59 | G117: crema de leche | H117: 0.15 | I117: =+VLOOKUP(G117,'PRECIO PROVEEDORES'!$A$2:$B$716,2,0) -> 10203 | J117: =+H117*I117 -> 1530.45 | L117: aceite de girasol | M117: 0.085 | N117: =+VLOOKUP(L117,'PRECIO PROVEEDORES'!$A$2:$B$716,2,0) -> 4299.01 | O117: =+M117*N117 -> 365.41585
B118: harina 0000 | C118: 0.225 | D118: =+VLOOKUP(B118,'PRECIO PROVEEDORES'!$A$2:$B$716,2,0) -> 1043.22 | E118: =+C118*D118 -> 234.7245 | G118: azucar | H118: 0.15 | I118: =+VLOOKUP(G118,'PRECIO PROVEEDORES'!$A$2:$B$716,2,0) -> 1352 | J118: =+H118*I118 -> 202.8 | L118: coco rallado | M118: 0.08 | N118: =+VLOOKUP(L118,'PRECIO PROVEEDORES'!$A$2:$B$716,2,0) -> 11721 | O118: =+M118*N118 -> 937.68
B119: bicarbonato de sodio | C119: 0.005 | D119: =+VLOOKUP(B119,'PRECIO PROVEEDORES'!$A$2:$B$716,2,0) -> 2517 | E119: =+C119*D119 -> 12.585 | G119: huevos | H119: 4 | I119: =+VLOOKUP(G119,'PRECIO PROVEEDORES'!$A$2:$B$716,2,0) -> 192 | J119: =+H119*I119 -> 768 | L119: Vinagre de alcohol | M119: 0.03 | N119: =+VLOOKUP(L119,'PRECIO PROVEEDORES'!$A$2:$B$716,2,0) -> 1037 | O119: =+M119*N119 -> 31.11
...

Sheet SUBRECETAS TUESTE  CP
B2: YOGURT GRIEGO rinde 6 porciones 150ml (1 LITRO yogurt) | G2: HUMMUS DE REMOLACHA | L2: PAN DE CHIPA | Q2: MERMELADA DE MORRON
C3: Kg/Lt/Uni | D3: $ | E3: Total $ | H3: Kg/Lt/Uni | I3: $ | J3: Total $ | M3: Kg/Lt/Uni | N3: $ | O3: Total $ | R3: Kg/Lt/Uni | S3: $ | T3: Total $
B4: Leche | C4: 1.5 | D4: =+VLOOKUP(B4,'PRECIO PROVEEDORES'!$A$2:$B$716,2,0) -> 1940 | E4: =+C4*D4 -> 2910 | G4: garbanzos | H4: 0.4 | I4: =+VLOOKUP(G4,'PRECIO PROVEEDORES'!$A$2:$B$716,2,0) -> 3330 | J4: =+H4*I4 -> 1332 | L4: Fecula de mandioca | M4: 1 | N4: =+VLOOKUP(L4,'PRECIO PROVEEDORES'!$A$2:$B$716,2,0) -> 4134 | O4: =+M4*N4 -> 4134 | Q4: Aji colorado | R4: 1 | S4: =+VLOOKUP(Q4,'PRECIO PROVEEDORES'!$A$2:$B$716,2,0) -> 4788 | T4: =+R4*S4 -> 4788
B5: leche en polvo | C5: 0.08 | D5: =+VLOOKUP(B5,'PRECIO PROVEEDORES'!$A$2:$B$716,2,0) -> 12915 | E5: =+C5*D5 -> 1033.2 | G5: polvo de remolacha | H5: 0.02 | I5: =+VLOOKUP(G5,'PRECIO PROVEEDORES'!$A$2:$B$716,2,0) -> 16900 | J5: =+H5*I5 -> 338 | L5: manteca tueste alyser | M5: 0.4 | N5: =+VLOOKUP(L5,'PRECIO PROVEEDORES'!$A$2:$B$716,2,0) -> 12206 | O5: =+M5*N5 -> 4882.4 | Q5: azucar | R5: 0.1 | S5: =+VLOOKUP(Q5,'PRECIO PROVEEDORES'!$A$2:$B$716,2,0) -> 1352 | T5: =+R5*S5 -> 135.2
B6: yogur dahi natural | C6: 0.4 | D6: =+VLOOKUP(B6,'PRECIO PROVEEDORES'!$A$2:$B$716,2,0) -> 8765 | E6: =+C6*D6 -> 3506 | G6: curry | H6: 0.01 | I6: =+VLOOKUP(G6,'PRECIO PROVEEDORES'!$A$2:$B$716,2,0) -> 5009.4 | J6: =+H6*I6 -> 50.094 | L6: huevos | M6: 6 | N6: =+VLOOKUP(L6,'PRECIO PROVEEDORES'!$A$2:$B$716,2,0) -> 192 | O6: =+M6*N6 -> 1152 | Q6: Pimienta negra en granos | R6: 0.005 | S6: =+VLOOKUP(Q6,'PRECIO PROVEEDORES'!$A$2:$B$716,2,0) -> 22269 | T6: =+R6*S6 -> 111.345
B7: porcion | C7: 0.15 | G7: jugo de limon | H7: 0.015 | I7: =+VLOOKUP(G7,'PRECIO PROVEEDORES'!$A$2:$B$716,2,0) -> 6125 | J7: =+H7*I7 -> 91.875 | L7: pategras | M7: 0.25 | N7: =+VLOOKUP(L7,'PRECIO PROVEEDORES'!$A$2:$B$716,2,0) -> 16000 | O7: =+M7*N7 -> 4000 | Q7: Pimienta negra en granos | R7: 0.005 | S7: =+VLOOKUP(Q7,'PRECIO PROVEEDORES'!$A$2:$B$716,2,0) -> 22269 | T7: =+R7*S7 -> 111.345
B8: rinde | C8: 1 | E8: =SUM(E4:E6) -> 7449.2 | G8: ajo | H8: 0.1 | I8: =+VLOOKUP(G8,'PRECIO PROVEEDORES'!$A$2:$B$716,2,0) -> 1800 | J8: =+H8*I8 -> 180 | L8: queso Reggianito | M8: 0.25 | N8: =+VLOOKUP(L8,'PRECIO PROVEEDORES'!$A$2:$B$716,2,0) -> 17376 | O8: =+M8*N8 -> 4344 | Q8: sal fina | R8: 0.005 | S8: =+VLOOKUP(Q8,'PRECIO PROVEEDORES'!$A$2:$B$716,2,0) -> 1633 | T8: =+R8*S8 -> 8.165
G9: sal fina | H9: 0.005 | I9: =+VLOOKUP(G9,'PRECIO PROVEEDORES'!$A$2:$B$716,2,0) -> 1633 | J9: =+H9*I9 -> 8.165 | L9: queso danbo tregar | M9: 0.5 | N9: =+VLOOKUP(L9,'PRECIO PROVEEDORES'!$A$2:$B$716,2,0) -> 10697 | O9: =+M9*N9 -> 5348.5
B10: rinde 6 porciones de 150gm c/u. de la receta sale de aprox. | G10: aceite de oliva | H10: 0.01 | I10: =+VLOOKUP(G10,'PRECIO PROVEEDORES'!$A$2:$B$716,2,0) -> 16595 | J10: =+H10*I10 -> 165.95 | L10: sal fina | M10: 0.01 | N10: =+VLOOKUP(L10,'PRECIO PROVEEDORES'!$A$2:$B$716,2,0) -> 1633 | O10: =+M10*N10 -> 16.33
B11: 970gm a 1000gm con un desperdicio de 700 gm de yogurt filtrado. | Q11: total receta 1.115kg | T11: =SUM(T4:T8) -> 5154.055
G12: rinde | J12: =SUM(J4:J10) -> 2166.084 | Q12: por kg | T12: =T11*1000/1115 -> 4622.4709
G13: x 1 kg | J13: =J12*1000/400 -> 5415.21 | L13: rinde 15 panes de 180grs | O13: =SUM(O4:O10) -> 23877.23
L14: por unidad | O14: =O13/15 -> 1591.8153
L15: por kg | O15: =O13*1000/2700 -> 8843.4185
B21: GRANOLA | G21: PESTO DE TOMATES | L21: CHERRYS CONFITADOS | Q21: MEDIALUNA 90 GRS
C22: Kg/Lt/Uni | D22: $ | E22: Total $ | H22: Kg/Lt/Uni | I22: $ | J22: Total $ | M22: Kg/Lt/Uni | N22: $ | O22: Total $ | R22: Kg/Lt/Uni | S22: $ | T22: Total $
B23: Almendras | C23: 0.25 | D23: =+VLOOKUP(B23,'PRECIO PROVEEDORES'!$A$2:$B$716,2,0) -> 25872 | E23: =+C23*D23 -> 6468 | G23: tomate seco | H23: 0.2 | I23: =+VLOOKUP(G23,'PRECIO PROVEEDORES'!$A$2:$B$716,2,0) -> 17587.35 | J23: =+H23*I23 -> 3517.47 | L23: Tomate cherry rojo | M23: 0.5 | N23: =+VLOOKUP(L23,'PRECIO PROVEEDORES'!$A$2:$B$716,2,0) -> 4095 | O23: =+M23*N23 -> 2047.5 | Q23: harina 0000 | R23: 1.8 | S23: =+VLOOKUP(Q23,'PRECIO PROVEEDORES'!$A$2:$B$716,2,0) -> 1043.22 | T23: =+R23*S23 -> 1877.796
B24: Nueces cuartos | C24: 0.25 | D24: =+VLOOKUP(B24,'PRECIO PROVEEDORES'!$A$2:$B$716,2,0) -> 27769.5 | E24: =+C24*D24 -> 6942.375 | G24: ajo | H24: 1 | I24: =+VLOOKUP(G24,'PRECIO PROVEEDORES'!$A$2:$B$716,2,0) -> 1800 | J24: =+H24*I24 -> 1800 | L24: sal fina | M24: 0.02 | N24: =+VLOOKUP(L24,'PRECIO PROVEEDORES'!$A$2:$B$716,2,0) -> 1633 | O24: =+M24*N24 -> 32.66 | Q24: harina 000 | R24: 0.2 | S24: =+VLOOKUP(Q24,'PRECIO PROVEEDORES'!$A$2:$B$716,2,0) -> 890 | T24: =+R24*S24 -> 178
B25: Mix de semillas | C25: 0.35 | D25: =+VLOOKUP(B25,'PRECIO PROVEEDORES'!$A$2:$B$716,2,0) -> 5952.89 | E25: =+C25*D25 -> 2083.5115 | G25: aceite de girasol | H25: 0.1 | I25: =+VLOOKUP(G25,'PRECIO PROVEEDORES'!$A$2:$B$716,2,0) -> 4299.01 | J25: =+H25*I25 -> 429.901 | L25: Hierbas frescas, Tomillo | M25: 0.1 | N25: =+VLOOKUP(L25,'PRECIO PROVEEDORES'!$A$2:$B$716,2,0) -> 3146 | O25: =+M25*N25 -> 314.6 | Q25: azucar | R25: 0.25 | S25: =+VLOOKUP(Q25,'PRECIO PROVEEDORES'!$A$2:$B$716,2,0) -> 1352 | T25: =+R25*S25 -> 338
B26: copos de maiz | C26: 0.4 | D26: =+VLOOKUP(B26,'PRECIO PROVEEDORES'!$A$2:$B$716,2,0) -> 4340 | E26: =+C26*D26 -> 1736 | G26: aceite de oliva | H26: 0.1 | I26: =+VLOOKUP(G26,'PRECIO PROVEEDORES'!$A$2:$B$716,2,0) -> 16595 | J26: =+H26*I26 -> 1659.5 | L26: aceite de girasol | M26: 0.02 | N26: =+VLOOKUP(L26,'PRECIO PROVEEDORES'!$A$2:$B$716,2,0) -> 4299.01 | O26: =+M26*N26 -> 85.9802 | Q26: levadura seca | R26: 0.02 | S26: =+VLOOKUP(Q26,'PRECIO PROVEEDORES'!$A$2:$B$716,2,0) -> 17780 | T26: =+R26*S26 -> 355.6
B27: coco rallado | C27: 0.15 | D27: =+VLOOKUP(B27,'PRECIO PROVEEDORES'!$A$2:$B$716,2,0) -> 11721 | E27: =+C27*D27 -> 1758.15 | G27: sal fina | H27: 0.01 | I27: =+VLOOKUP(G27,'PRECIO PROVEEDORES'!$A$2:$B$716,2,0) -> 1633 | J27: =+H27*I27 -> 16.33 | L27: ajo | M27: 0.3 | N27: =+VLOOKUP(L27,'PRECIO PROVEEDORES'!$A$2:$B$716,2,0) -> 1800 | O27: =+M27*N27 -> 540 | Q27: sal fina | R27: 0.04 | S27: =+VLOOKUP(Q27,'PRECIO PROVEEDORES'!$A$2:$B$716,2,0) -> 1633 | T27: =+R27*S27 -> 65.32
B28: Pasas de uva negra | C28: 0.35 | D28: =+VLOOKUP(B28,'PRECIO PROVEEDORES'!$A$2:$B$716,2,0) -> 6292 | E28: =+C28*D28 -> 2202.2 | L28: Pimienta negra en granos | M28: 0.002 | N28: =+VLOOKUP(L28,'PRECIO PROVEEDORES'!$A$2:$B$716,2,0) -> 22269 | O28: =+M28*N28 -> 44.538 | Q28: leche | R28: 0.5 | S28: =+VLOOKUP(Q28,'PRECIO PROVEEDORES'!$A$2:$B$716,2,0) -> 1940 | T28: =+R28*S28 -> 970
B29: miel | C29: 0.5 | D29: =+VLOOKUP(B29,'PRECIO PROVEEDORES'!$A$2:$B$716,2,0) -> 6062 | E29: =+C29*D29 -> 3031 | G29: rinde 200grs | J29: =SUM(J23:J27) -> 7423.201 | L29: x500 grs | O29: =SUM(O23:O28) -> 3065.2782 | Q29: huevos | R29: 6 | S29: =+VLOOKUP(Q29,'PRECIO PROVEEDORES'!$A$2:$B$716,2,0) -> 192 | T29: =+R29*S29 -> 1152
B30: Avena arrollada | C30: 0.4 | D30: =+VLOOKUP(B30,'PRECIO PROVEEDORES'!$A$2:$B$716,2,0) -> 2180 | E30: =+C30*D30 -> 872 | G30: por kg | J30: =J29*1000/200 -> 37116.005 | L30: por porcion | O30: =O29/10 -> 306.52782 | Q30: miel | R30: 0.06 | S30: =+VLOOKUP(Q30,'PRECIO PROVEEDORES'!$A$2:$B$716,2,0) -> 6062 | T30: =+R30*S30 -> 363.72
B31: naranja jugo | C31: 0.1 | D31: =+VLOOKUP(B31,'PRECIO PROVEEDORES'!$A$2:$B$716,2,0) -> 1440 | E31: =+C31*D31 -> 144 | L31: por kg | O31: =O29*2 -> 6130.5564 | Q31: manteca | R31: 0.57 | S31: =+VLOOKUP(Q31,'PRECIO PROVEEDORES'!$A$2:$B$716,2,0) -> 12000 | T31: =+R31*S31 -> 6840
B32: Aceite de girasol | C32: 0.03 | D32: =+VLOOKUP(B32,'PRECIO PROVEEDORES'!$A$2:$B$716,2,0) -> 4299.01 | E32: =+C32*D32 -> 128.9703
B33: mani tostado sin sal | C33: 0.25 | D33: =+VLOOKUP(B33,'PRECIO PROVEEDORES'!$A$2:$B$716,2,0) -> 5987 | E33: =+C33*D33 -> 1496.75 | Q33: rinde 42 unidades | T33: =SUM(T22:T31) -> 12140.436
Q34: por unidad | T34: =T33/42 -> 289.058
B35: rinde 60 porciones de 50grs (3 kilos) | E35: =SUM(E23:E33) -> 26862.957
B36: por kg | E36: =E35/3 -> 8954.3189
B40: PESTO ALBAHACA | G40: MEZCLA PANCAKES | L40: BONDIOLA BRASEADA | Q40: MEDIALUNA 50 GRAMOS
C41: Kg/Lt/Uni | D41: $ | E41: Total $ | H41: Kg/Lt/Uni | I41: $ | J41: Total $ | M41: Kg/Lt/Uni | N41: $ | O41: Total $ | R41: Kg/Lt/Uni | S41: $ | T41: Total $
B42: Hierbas frescas, Albahaca | C42: 1 | D42: =+VLOOKUP(B42,'PRECIO PROVEEDORES'!$A$2:$B$716,2,0) -> 4160 | E42: =+C42*D42 -> 4160 | G42: huevos | H42: 4 | I42: =+VLOOKUP(G42,'PRECIO PROVEEDORES'!$A$2:$B$716,2,0) -> 192 | J42: =+H42*I42 -> 768 | L42: Bondiola | M42: 5 | N42: =+VLOOKUP(L42,'PRECIO PROVEEDORES'!$A$2:$B$716,2,0) -> 7000 | O42: =+M42*N42 -> 35000 | Q42: harina 0000 | R42: 1.8 | S42: =+VLOOKUP(Q42,'PRECIO PROVEEDORES'!$A$2:$B$716,2,0) -> 1043.22 | T42: =+R42*S42 -> 1877.796
B43: ajo | C43: 0.25 | D43: =+VLOOKUP(B43,'PRECIO PROVEEDORES'!$A$2:$B$716,2,0) -> 1800 | E43: =+C43*D43 -> 450 | G43: leche | H43: 0.35 | I43: =+VLOOKUP(G43,'PRECIO PROVEEDORES'!$A$2:$B$716,2,0) -> 1940 | J43: =+H43*I43 -> 679 | L43: ajo | M43: 0.4 | N43: =+VLOOKUP(L43,'PRECIO PROVEEDORES'!$A$2:$B$716,2,0) -> 1800 | O43: =+M43*N43 -> 720 | Q43: harina 000 | R43: 0.2 | S43: =+VLOOKUP(Q43,'PRECIO PROVEEDORES'!$A$2:$B$716,2,0) -> 890 | T43: =+R43*S43 -> 178
B44: aceite de girasol | C44: 0.1 | D44: =+VLOOKUP(B44,'PRECIO PROVEEDORES'!$A$2:$B$716,2,0) -> 4299.01 | E44: =+C44*D44 -> 429.901 | G44: leche en polvo | H44: 0.15 | I44: =+VLOOKUP(G44,'PRECIO PROVEEDORES'!$A$2:$B$716,2,0) -> 12915 | J44: =+H44*I44 -> 1937.25 | L44: limon | M44: 1 | N44: =+VLOOKUP(L44,'PRECIO PROVEEDORES'!$A$2:$B$716,2,0) -> 3000 | O44: =+M44*N44 -> 3000 | Q44: azucar | R44: 0.25 | S44: =+VLOOKUP(Q44,'PRECIO PROVEEDORES'!$A$2:$B$716,2,0) -> 1352 | T44: =+R44*S44 -> 338
B45: sal fina | C45: 0.008 | D45: =+VLOOKUP(B45,'PRECIO PROVEEDORES'!$A$2:$B$716,2,0) -> 1633 | E45: =+C45*D45 -> 13.064 | G45: harina 000 | H45: 0.4 | I45: =+VLOOKUP(G45,'PRECIO PROVEEDORES'!$A$2:$B$716,2,0) -> 890 | J45: =+H45*I45 -> 356 | L45: sal fina | M45: 0.015 | N45: =+VLOOKUP(L45,'PRECIO PROVEEDORES'!$A$2:$B$716,2,0) -> 1633 | O45: =+M45*N45 -> 24.495 | Q45: levadura seca | R45: 0.02 | S45: =+VLOOKUP(Q45,'PRECIO PROVEEDORES'!$A$2:$B$716,2,0) -> 17780 | T45: =+R45*S45 -> 355.6
G46: levadura seca | H46: 0.01 | I46: =+VLOOKUP(G46,'PRECIO PROVEEDORES'!$A$2:$B$716,2,0) -> 17780 | J46: =+H46*I46 -> 177.8 | Q46: sal fina | R46: 0.04 | S46: =+VLOOKUP(Q46,'PRECIO PROVEEDORES'!$A$2:$B$716,2,0) -> 1633 | T46: =+R46*S46 -> 65.32
B47: por kg | E47: =SUM(E41:E45) -> 5052.965 | L47: rinde 31 porciones 160grs | O47: =SUM(O42:O46) -> 38744.495 | Q47: leche | R47: 0.5 | S47: =+VLOOKUP(Q47,'PRECIO PROVEEDORES'!$A$2:$B$716,2,0) -> 1940 | T47: =+R47*S47 -> 970
G48: rinde 10 porciones | J48: =SUM(J42:J46) -> 3918.05 | L48: por kg | O48: =O47/5 -> 7748.899 | Q48: huevos | R48: 6 | S48: =+VLOOKUP(Q48,'PRECIO PROVEEDORES'!$A$2:$B$716,2,0) -> 192 | T48: =+R48*S48 -> 1152
G49: por pancake (1) | J49: =J48/10 -> 391.805 | Q49: miel | R49: 0.06 | S49: =+VLOOKUP(Q49,'PRECIO PROVEEDORES'!$A$2:$B$716,2,0) -> 6062 | T49: =+R49*S49 -> 363.72
Q50: manteca | R50: 0.57 | S50: =+VLOOKUP(Q50,'PRECIO PROVEEDORES'!$A$2:$B$716,2,0) -> 12000 | T50: =+R50*S50 -> 6840
Q52: rinde 78 medialunas | T52: =SUM(T41:T50) -> 12140.436
Q53: por unidad | T53: =T52/78 -> 155.64662
B59: SALSA DE CHOCOLATE | G59: SALSA TERIYAKI | L59: CEBOLLAS ENCURTIDAS | Q59: CROISSANT 140 GRAMOS
C60: Kg/Lt/Uni | D60: $ | E60: Total $ | H60: Kg/Lt/Uni | I60: $ | J60: Total $ | M60: Kg/Lt/Uni | N60: $ | O60: Total $ | R60: Kg/Lt/Uni | S60: $ | T60: Total $
B61: cacao amargo | C61: 0.05 | D61: =+VLOOKUP(B61,'PRECIO PROVEEDORES'!$A$2:$B$716,2,0) -> 13205 | E61: =+C61*D61 -> 660.25 | G61: agua | H61: 0.4 | I61: =+VLOOKUP(G61,'PRECIO PROVEEDORES'!$A$2:$B$716,2,0) -> 0 | J61: =+H61*I61 -> 0 | L61: Cebolla Morada | M61: 0.65 | N61: =+VLOOKUP(L61,'PRECIO PROVEEDORES'!$A$2:$B$716,2,0) -> 2070 | O61: =+M61*N61 -> 1345.5 | Q61: harina 0000 | R61: 1 | S61: =+VLOOKUP(Q61,'PRECIO PROVEEDORES'!$A$2:$B$716,2,0) -> 1043.22 | T61: =+R61*S61 -> 1043.22
B62: leche | C62: 0.3 | D62: =+VLOOKUP(B62,'PRECIO PROVEEDORES'!$A$2:$B$716,2,0) -> 1940 | E62: =+C62*D62 -> 582 | G62: almidon de maiz | H62: 0.08 | I62: =+VLOOKUP(G62,'PRECIO PROVEEDORES'!$A$2:$B$716,2,0) -> 2191 | J62: =+H62*I62 -> 175.28 | L62: agua | M62: 0.3 | N62: =+VLOOKUP(L62,'PRECIO PROVEEDORES'!$A$2:$B$716,2,0) -> 0 | O62: =+M62*N62 -> 0 | Q62: harina 000 | R62: 0.25 | S62: =+VLOOKUP(Q62,'PRECIO PROVEEDORES'!$A$2:$B$716,2,0) -> 890 | T62: =+R62*S62 -> 222.5
B63: azucar | C63: 0.1 | D63: =+VLOOKUP(B63,'PRECIO PROVEEDORES'!$A$2:$B$716,2,0) -> 1352 | E63: =+C63*D63 -> 135.2 | G63: salsa de soja | H63: 0.6 | I63: =+VLOOKUP(G63,'PRECIO PROVEEDORES'!$A$2:$B$716,2,0) -> 1897 | J63: =+H63*I63 -> 1138.2 | L63: azucar | M63: 0.2 | N63: =+VLOOKUP(L63,'PRECIO PROVEEDORES'!$A$2:$B$716,2,0) -> 1352 | O63: =+M63*N63 -> 270.4 | Q63: azucar | R63: 0.15 | S63: =+VLOOKUP(Q63,'PRECIO PROVEEDORES'!$A$2:$B$716,2,0) -> 1352 | T63: =+R63*S63 -> 202.8
B64: manteca | C64: 0.015 | D64: =+VLOOKUP(B64,'PRECIO PROVEEDORES'!$A$2:$B$716,2,0) -> 12000 | E64: =+C64*D64 -> 180 | G64: azucar | H64: 0.18 | I64: =+VLOOKUP(G64,'PRECIO PROVEEDORES'!$A$2:$B$716,2,0) -> 1352 | J64: =+H64*I64 -> 243.36 | L64: vinagre de alcohol | M64: 0.1 | N64: =+VLOOKUP(L64,'PRECIO PROVEEDORES'!$A$2:$B$716,2,0) -> 1037 | O64: =+M64*N64 -> 103.7 | Q64: levadura seca | R64: 0.01 | S64: =+VLOOKUP(Q64,'PRECIO PROVEEDORES'!$A$2:$B$716,2,0) -> 17780 | T64: =+R64*S64 -> 177.8
B65: harina 0000 | C65: 0.03 | D65: =+VLOOKUP(B65,'PRECIO PROVEEDORES'!$A$2:$B$716,2,0) -> 1043.22 | E65: =+C65*D65 -> 31.2966 | G65: vinagre de alcohol | H65: 0.1 | I65: =+VLOOKUP(G65,'PRECIO PROVEEDORES'!$A$2:$B$716,2,0) -> 1037 | J65: =+H65*I65 -> 103.7 | L65: limon | M65: 0.05 | N65: =+VLOOKUP(L65,'PRECIO PROVEEDORES'!$A$2:$B$716,2,0) -> 3000 | O65: =+M65*N65 -> 150 | Q65: huevos | R65: 1 | S65: =+VLOOKUP(Q65,'PRECIO PROVEEDORES'!$A$2:$B$716,2,0) -> 192 | T65: =+R65*S65 -> 192
B66: sal fina | C66: 0.001 | D66: =+VLOOKUP(B66,'PRECIO PROVEEDORES'!$A$2:$B$716,2,0) -> 1633 | E66: =+C66*D66 -> 1.633 | G66: ajo | H66: 1 | I66: =+VLOOKUP(G66,'PRECIO PROVEEDORES'!$A$2:$B$716,2,0) -> 1800 | J66: =+H66*I66 -> 1800 | Q66: manteca | R66: 0.6 | S66: =+VLOOKUP(Q66,'PRECIO PROVEEDORES'!$A$2:$B$716,2,0) -> 12000 | T66: =+R66*S66 -> 7200
G67: Jengibre | H67: 0.004 | I67: =+VLOOKUP(G67,'PRECIO PROVEEDORES'!$A$2:$B$716,2,0) -> 8000 | J67: =+H67*I67 -> 32 | L67: rinde 785grs, 26 porciones | O67: =SUM(O61:O65) -> 1869.6
B68: rinde 500 grs | E68: =SUM(E61:E66) -> 1590.3796 | L68: por kg | O68: =O67*1000/785 -> 2381.6561 | Q68: rinde 19 unidades | T68: =SUM(T61:T66) -> 9038.32
B69: por kg | E69: =E68*2 -> 3180.7592 | G69: rinde 1,200 kg | J69: =SUM(J61:J67) -> 3492.54 | Q69: por unidad | T69: =T68/19 -> 475.70105
G70: por kg | J70: =J69*1000/1200 -> 2910.45
B78: PAPAS ASADAS | G78: PAN CIABATTA | L78: FRUTOS SECOS | Q78: MIX DE VEGETALES ASADOS
C79: Kg/Lt/Uni | D79: $ | E79: Total $ | H79: Kg/Lt/Uni | I79: $ | J79: Total $ | M79: Kg/Lt/Uni | N79: $ | O79: Total $ | R79: Kg/Lt/Uni | S79: $ | T79: Total $
B80: papa | C80: 1.5 | D80: =+VLOOKUP(B80,'PRECIO PROVEEDORES'!$A$2:$B$716,2,0) -> 1363.15 | E80: =+C80*D80 -> 2044.725 | G80: harina 000 | H80: 1 | I80: =+VLOOKUP(G80,'PRECIO PROVEEDORES'!$A$2:$B$716,2,0) -> 890 | J80: =+H80*I80 -> 890 | L80: Almendras | M80: 0.05 | N80: =+VLOOKUP(L80,'PRECIO PROVEEDORES'!$A$2:$B$716,2,0) -> 25872 | O80: =+M80*N80 -> 1293.6 | Q80: Aji colorado | R80: 0.15 | S80: =+VLOOKUP(Q80,'PRECIO PROVEEDORES'!$A$2:$B$716,2,0) -> 4788 | T80: =+R80*S80 -> 718.2
B81: Pimenton en polvo | C81: 0.04 | D81: =+VLOOKUP(B81,'PRECIO PROVEEDORES'!$A$2:$B$716,2,0) -> 8566.8 | E81: =+C81*D81 -> 342.672 | G81: sal fina | H81: 0.022 | I81: =+VLOOKUP(G81,'PRECIO PROVEEDORES'!$A$2:$B$716,2,0) -> 1633 | J81: =+H81*I81 -> 35.926 | L81: nueces cuartos | M81: 0.1 | N81: =+VLOOKUP(L81,'PRECIO PROVEEDORES'!$A$2:$B$716,2,0) -> 27769.5 | O81: =+M81*N81 -> 2776.95 | Q81: Zuchinni | R81: 0.3 | S81: =+VLOOKUP(Q81,'PRECIO PROVEEDORES'!$A$2:$B$716,2,0) -> 4095 | T81: =+R81*S81 -> 1228.5
B82: sal fina | C82: 0.02 | D82: =+VLOOKUP(B82,'PRECIO PROVEEDORES'!$A$2:$B$716,2,0) -> 1633 | E82: =+C82*D82 -> 32.66 | G82: agua | H82: 0.7 | I82: =+VLOOKUP(G82,'PRECIO PROVEEDORES'!$A$2:$B$716,2,0) -> 0 | J82: =+H82*I82 -> 0 | L82: mani tostado sin sal | M82: 0.1 | N82: =+VLOOKUP(L82,'PRECIO PROVEEDORES'!$A$2:$B$716,2,0) -> 5987 | O82: =+M82*N82 -> 598.7 | Q82: Berenjena | R82: 0.3 | S82: =+VLOOKUP(Q82,'PRECIO PROVEEDORES'!$A$2:$B$716,2,0) -> 2530 | T82: =+R82*S82 -> 759
B83: aceite de girasol | C83: 0.025 | D83: =+VLOOKUP(B83,'PRECIO PROVEEDORES'!$A$2:$B$716,2,0) -> 4299.01 | E83: =+C83*D83 -> 107.47525 | G83: levadura seca | H83: 0.01 | I83: =+VLOOKUP(G83,'PRECIO PROVEEDORES'!$A$2:$B$716,2,0) -> 17780 | J83: =+H83*I83 -> 177.8 | Q83: zanahoria | R83: 0.15 | S83: =+VLOOKUP(Q83,'PRECIO PROVEEDORES'!$A$2:$B$716,2,0) -> 1650 | T83: =+R83*S83 -> 247.5
G84: aceite de oliva | H84: 0.035 | I84: =+VLOOKUP(G84,'PRECIO PROVEEDORES'!$A$2:$B$716,2,0) -> 16595 | J84: =+H84*I84 -> 580.825 | L84: rinde 8 porciones de 30 grs | O84: =SUM(O80:O82) -> 4669.25 | Q84: cebolla morada | R84: 0.1 | S84: =+VLOOKUP(Q84,'PRECIO PROVEEDORES'!$A$2:$B$716,2,0) -> 2070 | T84: =+R84*S84 -> 207
B85: por 1,5 kg | E85: =SUM(E79:E83) -> 2527.5322 | L85: por kg | O85: =O84*1000/240 -> 19455.208 | Q85: Cebolla | R85: 0.1 | S85: =+VLOOKUP(Q85,'PRECIO PROVEEDORES'!$A$2:$B$716,2,0) -> 1092.5 | T85: =+R85*S85 -> 109.25
B86: por kg | E86: =E85*1000/1500 -> 1685.0215 | G86: rinde 10 panes de 100 grs | J86: =SUM(J80:J84) -> 1684.551
G87: por unidad | J87: =J86/10 -> 168.4551 | Q87: rinde 1,100 kg | T87: =SUM(T79:T85) -> 3269.45
Q88: por kg | T88: =T87*1000/1100 -> 2972.2273
B97: CHIPA CLASICO | G97: PASTA DE MANI | L97: MERMELADA | Q97: CEBOLLA CARAMELIZADA
C98: Kg/Lt/Uni | D98: $ | E98: Total $ | H98: Kg/Lt/Uni | I98: $ | J98: Total $ | M98: Kg/Lt/Uni | N98: $ | O98: Total $ | R98: Kg/Lt/Uni | S98: $ | T98: Total $
B99: Fecula de mandioca | C99: 1 | D99: =+VLOOKUP(B99,'PRECIO PROVEEDORES'!$A$2:$B$716,2,0) -> 4134 | E99: =+C99*D99 -> 4134 | G99: mani tostado sin sal | H99: 0.25 | I99: =+VLOOKUP(G99,'PRECIO PROVEEDORES'!$A$2:$B$716,2,0) -> 5987 | J99: =+H99*I99 -> 1496.75 | L99: frutillas congeladas | M99: 4 | N99: =+VLOOKUP(L99,'PRECIO PROVEEDORES'!$A$2:$B$716,2,0) -> 7173 | O99: =+M99*N99 -> 28692 | Q99: cebolla | R99: 1 | S99: =+VLOOKUP(Q99,'PRECIO PROVEEDORES'!$A$2:$B$716,2,0) -> 1092.5 | T99: =+R99*S99 -> 1092.5
B100: manteca tueste alyser | C100: 0.4 | D100: =+VLOOKUP(B100,'PRECIO PROVEEDORES'!$A$2:$B$716,2,0) -> 12206 | E100: =+C100*D100 -> 4882.4 | G100: aceite de girasol | H100: 0.01 | I100: =+VLOOKUP(G100,'PRECIO PROVEEDORES'!$A$2:$B$716,2,0) -> 4299.01 | J100: =+H100*I100 -> 42.9901 | L100: azucar | M100: 2 | N100: =+VLOOKUP(L100,'PRECIO PROVEEDORES'!$A$2:$B$716,2,0) -> 1352 | O100: =+M100*N100 -> 2704 | Q100: manteca tueste alyser | R100: 0.045 | S100: =+VLOOKUP(Q100,'PRECIO PROVEEDORES'!$A$2:$B$716,2,0) -> 12206 | T100: =+R100*S100 -> 549.27
B101: huevos | C101: 6 | D101: =+VLOOKUP(B101,'PRECIO PROVEEDORES'!$A$2:$B$716,2,0) -> 192 | E101: =+C101*D101 -> 1152 | L101: pectina | M101: 0.015 | N101: =+VLOOKUP(L101,'PRECIO PROVEEDORES'!$A$2:$B$716,2,0) -> 64600 | O101: =+M101*N101 -> 969 | Q101: azucar | R101: 0.03 | S101: =+VLOOKUP(Q101,'PRECIO PROVEEDORES'!$A$2:$B$716,2,0) -> 1352 | T101: =+R101*S101 -> 40.56
B102: pategras | C102: 0.25 | D102: =+VLOOKUP(B102,'PRECIO PROVEEDORES'!$A$2:$B$716,2,0) -> 16000 | E102: =+C102*D102 -> 4000 | G102: rinde 250 grs | J102: =SUM(J99:J100) -> 1539.7401 | L102: rinde 100 porciones de 40 grs | O102: =SUM(O99:O101) -> 32365 | Q102: sal fina | R102: 0.005 | S102: =+VLOOKUP(Q102,'PRECIO PROVEEDORES'!$A$2:$B$716,2,0) -> 1633 | T102: =+R102*S102 -> 8.165
B103: queso Reggianito | C103: 0.25 | D103: =+VLOOKUP(B103,'PRECIO PROVEEDORES'!$A$2:$B$716,2,0) -> 17376 | E103: =+C103*D103 -> 4344 | G103: por kg | J103: =J102*4 -> 6158.9604 | L103: por kg | O103: =O102/4 -> 8091.25
B104: queso danbo tregar | C104: 0.5 | D104: =+VLOOKUP(B104,'PRECIO PROVEEDORES'!$A$2:$B$716,2,0) -> 10697 | E104: =+C104*D104 -> 5348.5 | Q104: rinde 33 porciones de 30 grs | T104: =SUM(T98:T102) -> 1690.495
B105: sal fina | C105: 0.01 | D105: =+VLOOKUP(B105,'PRECIO PROVEEDORES'!$A$2:$B$716,2,0) -> 1633 | E105: =+C105*D105 -> 16.33
B107: rinde 30 unidades de 90 grs | E107: =SUM(E99:E105) -> 23877.23
B108: por unidad | E108: =E107/30 -> 795.90767
B109: por kg | E109: =E107*1000/2700 -> 8843.4185
B110: chipa venta publico $3300
B116: MASA ALFAJOR ALMENDRAS | G116: GALLETAS CASERAS | L116: COULIS FRUTOS ROJOS | Q116: TE FRUTOS ROJOS
C117: Kg/Lt/Uni | D117: $ | E117: Total $ | H117: Kg/Lt/Uni | I117: $ | J117: Total $ | M117: Kg/Lt/Uni | N117: $ | O117: Total $ | R117: Kg/Lt/Uni | S117: $ | T117: Total $
B118: manteca | C118: 0.3 | D118: =+VLOOKUP(B118,'PRECIO PROVEEDORES'!$A$2:$B$716,2,0) -> 12000 | E118: =+C118*D118 -> 3600 | G118: harina 0000 | H118: 1.12 | I118: =+VLOOKUP(G118,'PRECIO PROVEEDORES'!$A$2:$B$716,2,0) -> 1043.22 | J118: =+H118*I118 -> 1168.4064 | L118: Mix de frutos rojos congelados | M118: 1 | N118: =+VLOOKUP(L118,'PRECIO PROVEEDORES'!$A$2:$B$716,2,0) -> 12874.4 | O118: =+M118*N118 -> 12874.4 | Q118: te frutos rojos | R118: 0.025 | S118: =+VLOOKUP(Q118,'PRECIO PROVEEDORES'!$A$2:$B$716,2,0) -> 90016 | T118: =+R118*S118 -> 2250.4
B119: azucar | C119: 0.3 | D119: =+VLOOKUP(B119,'PRECIO PROVEEDORES'!$A$2:$B$716,2,0) -> 1352 | E119: =+C119*D119 -> 405.6 | G119: azucar | H119: 0.68 | I119: =+VLOOKUP(G119,'PRECIO PROVEEDORES'!$A$2:$B$716,2,0) -> 1352 | J119: =+H119*I119 -> 919.36 | L119: azucar | M119: 0.8 | N119: =+VLOOKUP(L119,'PRECIO PROVEEDORES'!$A$2:$B$716,2,0) -> 1352 | O119: =+M119*N119 -> 1081.6 | Q119: agua | R119: 1 | S119: =+VLOOKUP(Q119,'PRECIO PROVEEDORES'!$A$2:$B$716,2,0) -> 0 | T119: =+R119*S119 -> 0
B120: miel | C120: 0.055 | D120: =+VLOOKUP(B120,'PRECIO PROVEEDORES'!$A$2:$B$716,2,0) -> 6062 | E120: =+C120*D120 -> 333.41 | G120: bicarbonato de sodio | H120: 0.02 | I120: =+VLOOKUP(G120,'PRECIO PROVEEDORES'!$A$2:$B$716,2,0) -> 2517 | J120: =+H120*I120 -> 50.34 | L120: pectina | M120: 0.012 | N120: =+VLOOKUP(L120,'PRECIO PROVEEDORES'!$A$2:$B$716,2,0) -> 64600 | O120: =+M120*N120 -> 775.2
B121: huevos | C121: 2 | D121: =+VLOOKUP(B121,'PRECIO PROVEEDORES'!$A$2:$B$716,2,0) -> 192 | E121: =+C121*D121 -> 384 | G121: canela en polvo | H121: 0.01 | I121: =+VLOOKUP(G121,'PRECIO PROVEEDORES'!$A$2:$B$716,2,0) -> 10061.64 | J121: =+H121*I121 -> 100.6164 | Q121: rinde 1 litro | T121: =T118 -> 2250.4
B122: harina 0000 | C122: 0.48 | D122: =+VLOOKUP(B122,'PRECIO PROVEEDORES'!$A$2:$B$716,2,0) -> 1043.22 | E122: =+C122*D122 -> 500.7456 | G122: sal fina | H122: 0.01 | I122: =+VLOOKUP(G122,'PRECIO PROVEEDORES'!$A$2:$B$716,2,0) -> 1633 | J122: =+H122*I122 -> 16.33 | L122: rinde 1,800 kg | O122: =SUM(O118:O120) -> 14731.2
B123: almidon de maiz | C123: 0.135 | D123: =+VLOOKUP(B123,'PRECIO PROVEEDORES'!$A$2:$B$716,2,0) -> 2191 | E123: =+C123*D123 -> 295.785 | G123: manteca | H123: 0.4 | I123: =+VLOOKUP(G123,'PRECIO PROVEEDORES'!$A$2:$B$716,2,0) -> 12000 | J123: =+H123*I123 -> 4800 | L123: por kg | O123: =O122*1000/1800 -> 8184
B124: almendras | C124: 0.15 | D124: =+VLOOKUP(B124,'PRECIO PROVEEDORES'!$A$2:$B$716,2,0) -> 25872 | E124: =+C124*D124 -> 3880.8 | G124: leche | H124: 0.24 | I124: =+VLOOKUP(G124,'PRECIO PROVEEDORES'!$A$2:$B$716,2,0) -> 1940 | J124: =+H124*I124 -> 465.6
B125: bicarbonato de sodio | C125: 0.005 | D125: =+VLOOKUP(B125,'PRECIO PROVEEDORES'!$A$2:$B$716,2,0) -> 2517 | E125: =+C125*D125 -> 12.585 | G125: miel | H125: 0.1 | I125: =+VLOOKUP(G125,'PRECIO PROVEEDORES'!$A$2:$B$716,2,0) -> 6062 | J125: =+H125*I125 -> 606.2
B126: Polvo para hornear | C126: 0.007 | D126: =+VLOOKUP(B126,'PRECIO PROVEEDORES'!$A$2:$B$716,2,0) -> 6040 | E126: =+C126*D126 -> 42.28
B127: sal fina | C127: 0.002 | D127: =+VLOOKUP(B127,'PRECIO PROVEEDORES'!$A$2:$B$716,2,0) -> 1633 | E127: =+C127*D127 -> 3.266 | G127: rinde 2 kg | J127: =SUM(J118:J125) -> 8126.8528
G128: por kg | J128: =J127/2 -> 4063.4264
B129: rinde 38 tapitas | E129: =SUM(E118:E127) -> 9458.4716
B130: cada tapita | E130: =E129/38 -> 248.90715
B135: ALMIBAR LIMON | G135: HIBISCUS | L135: ALMIBAR DE JENGIBRE | Q135: PAN DE MOLDE BRIOCHE
C136: Kg/Lt/Uni | D136: $ | E136: Total $ | H136: Kg/Lt/Uni | I136: $ | J136: Total $ | M136: Kg/Lt/Uni | N136: $ | O136: Total $ | R136: Kg/Lt/Uni | S136: $ | T136: Total $
B137: limon | C137: 4 | D137: =+VLOOKUP(B137,'PRECIO PROVEEDORES'!$A$2:$B$716,2,0) -> 3000 | E137: =+C137*D137 -> 12000 | G137: te de hibiscus | H137: 0.025 | I137: =+VLOOKUP(G137,'PRECIO PROVEEDORES'!$A$2:$B$716,2,0) -> 25360 | J137: =+H137*I137 -> 634 | L137: jengibre | M137: 0.45 | N137: =+VLOOKUP(L137,'PRECIO PROVEEDORES'!$A$2:$B$716,2,0) -> 8000 | O137: =+M137*N137 -> 3600 | Q137: harina 000 | R137: 0.5 | S137: =+VLOOKUP(Q137,'PRECIO PROVEEDORES'!$A$2:$B$716,2,0) -> 890 | T137: =+R137*S137 -> 445
B138: azucar | C138: 0.5 | D138: =+VLOOKUP(B138,'PRECIO PROVEEDORES'!$A$2:$B$716,2,0) -> 1352 | E138: =+C138*D138 -> 676 | G138: agua | H138: 1 | I138: =+VLOOKUP(G138,'PRECIO PROVEEDORES'!$A$2:$B$716,2,0) -> 0 | J138: =+H138*I138 -> 0 | L138: agua | M138: 1 | N138: =+VLOOKUP(L138,'PRECIO PROVEEDORES'!$A$2:$B$716,2,0) -> 0 | O138: =+M138*N138 -> 0 | Q138: leche | R138: 0.28 | S138: =+VLOOKUP(Q138,'PRECIO PROVEEDORES'!$A$2:$B$716,2,0) -> 1940 | T138: =+R138*S138 -> 543.2
G139: rinde 1 litro | J139: =J137 -> 634 | Q139: levadura seca | R139: 0.008 | S139: =+VLOOKUP(Q139,'PRECIO PROVEEDORES'!$A$2:$B$716,2,0) -> 17780 | T139: =+R139*S139 -> 142.24
B140: rinde 1 litro | E140: =SUM(E136:E138) -> 12676 | L140: rinde 1 litro | O140: =O137 -> 3600 | Q140: huevos | R140: 1 | S140: =+VLOOKUP(Q140,'PRECIO PROVEEDORES'!$A$2:$B$716,2,0) -> 192 | T140: =+R140*S140 -> 192
...

Sheet PASTELERIA CP
B2: COOKIE DOBLE CHOCO 100 grs unidad | G2: MEDIALUNA 50 GRS | L2: MEDIALUNA 90 GRS
C3: Kg/Lt/Uni | D3: $ | E3: Total $ | H3: Kg/Lt/Uni | I3: $ | J3: Total $ | M3: Kg/Lt/Uni | N3: $ | O3: Total $
B4: manteca | C4: 0.225 | D4: =+VLOOKUP(B4,'PRECIO PROVEEDORES'!$A$2:$B$716,2,0) -> 12000 | E4: =+C4*D4 -> 2700 | G4: harina 0000 | H4: 1.8 | I4: =+VLOOKUP(G4,'PRECIO PROVEEDORES'!$A$2:$B$716,2,0) -> 1043.22 | J4: =+H4*I4 -> 1877.796 | L4: harina 0000 | M4: 1.8 | N4: =+VLOOKUP(L4,'PRECIO PROVEEDORES'!$A$2:$B$716,2,0) -> 1043.22 | O4: =+M4*N4 -> 1877.796
B5: azucar | C5: 0.2 | D5: =+VLOOKUP(B5,'PRECIO PROVEEDORES'!$A$2:$B$716,2,0) -> 1352 | E5: =+C5*D5 -> 270.4 | G5: harina 000 | H5: 0.2 | I5: =+VLOOKUP(G5,'PRECIO PROVEEDORES'!$A$2:$B$716,2,0) -> 890 | J5: =+H5*I5 -> 178 | L5: harina 000 | M5: 0.2 | N5: =+VLOOKUP(L5,'PRECIO PROVEEDORES'!$A$2:$B$716,2,0) -> 890 | O5: =+M5*N5 -> 178
B6: Azucar negro | C6: 0.2 | D6: =+VLOOKUP(B6,'PRECIO PROVEEDORES'!$A$2:$B$716,2,0) -> 1624.77 | E6: =+C6*D6 -> 324.954 | G6: azucar | H6: 0.16 | I6: =+VLOOKUP(G6,'PRECIO PROVEEDORES'!$A$2:$B$716,2,0) -> 1352 | J6: =+H6*I6 -> 216.32 | L6: azucar | M6: 0.25 | N6: =+VLOOKUP(L6,'PRECIO PROVEEDORES'!$A$2:$B$716,2,0) -> 1352 | O6: =+M6*N6 -> 338
B7: Huevos | C7: 2 | D7: =+VLOOKUP(B7,'PRECIO PROVEEDORES'!$A$2:$B$716,2,0) -> 192 | E7: =+C7*D7 -> 384 | G7: levadura seca | H7: 0.013 | I7: =+VLOOKUP(G7,'PRECIO PROVEEDORES'!$A$2:$B$716,2,0) -> 17780 | J7: =+H7*I7 -> 231.14 | L7: levadura seca | M7: 0.013 | N7: =+VLOOKUP(L7,'PRECIO PROVEEDORES'!$A$2:$B$716,2,0) -> 17780 | O7: =+M7*N7 -> 231.14
B8: harina 0000 | C8: 0.46 | D8: =+VLOOKUP(B8,'PRECIO PROVEEDORES'!$A$2:$B$716,2,0) -> 1043.22 | E8: =+C8*D8 -> 479.8812 | G8: sal fina | H8: 0.04 | I8: =+VLOOKUP(G8,'PRECIO PROVEEDORES'!$A$2:$B$716,2,0) -> 1633 | J8: =+H8*I8 -> 65.32 | L8: sal fina | M8: 0.04 | N8: =+VLOOKUP(L8,'PRECIO PROVEEDORES'!$A$2:$B$716,2,0) -> 1633 | O8: =+M8*N8 -> 65.32
B9: bicarbonato de sodio | C9: 0.005 | D9: =+VLOOKUP(B9,'PRECIO PROVEEDORES'!$A$2:$B$716,2,0) -> 2517 | E9: =+C9*D9 -> 12.585 | G9: leche | H9: 0.5 | I9: =+VLOOKUP(G9,'PRECIO PROVEEDORES'!$A$2:$B$716,2,0) -> 1940 | J9: =+H9*I9 -> 970 | L9: leche | M9: 0.5 | N9: =+VLOOKUP(L9,'PRECIO PROVEEDORES'!$A$2:$B$716,2,0) -> 1940 | O9: =+M9*N9 -> 970
B10: Polvo para hornear | C10: 0.007 | D10: =+VLOOKUP(B10,'PRECIO PROVEEDORES'!$A$2:$B$716,2,0) -> 6040 | E10: =+C10*D10 -> 42.28 | G10: huevos | H10: 6 | I10: =+VLOOKUP(G10,'PRECIO PROVEEDORES'!$A$2:$B$716,2,0) -> 192 | J10: =+H10*I10 -> 1152 | L10: huevos | M10: 6 | N10: =+VLOOKUP(L10,'PRECIO PROVEEDORES'!$A$2:$B$716,2,0) -> 192 | O10: =+M10*N10 -> 1152
B11: sal fina | C11: 0.003 | D11: =+VLOOKUP(B11,'PRECIO PROVEEDORES'!$A$2:$B$716,2,0) -> 1633 | E11: =+C11*D11 -> 4.899 | G11: miel | H11: 0.06 | I11: =+VLOOKUP(G11,'PRECIO PROVEEDORES'!$A$2:$B$716,2,0) -> 6062 | J11: =+H11*I11 -> 363.72 | L11: miel | M11: 0.06 | N11: =+VLOOKUP(L11,'PRECIO PROVEEDORES'!$A$2:$B$716,2,0) -> 6062 | O11: =+M11*N11 -> 363.72
B12: Fenix 83 ( con leche) | C12: 0.065 | D12: =+VLOOKUP(B12,'PRECIO PROVEEDORES'!$A$2:$B$716,2,0) -> 36068 | E12: =+C12*D12 -> 2344.42 | G12: manteca | H12: 1.07 | I12: =+VLOOKUP(G12,'PRECIO PROVEEDORES'!$A$2:$B$716,2,0) -> 12000 | J12: =+H12*I12 -> 12840 | L12: manteca | M12: 1.07 | N12: =+VLOOKUP(L12,'PRECIO PROVEEDORES'!$A$2:$B$716,2,0) -> 12000 | O12: =+M12*N12 -> 12840
B13: Fenix 86 (semi amargo) | C13: 0.065 | D13: =+VLOOKUP(B13,'PRECIO PROVEEDORES'!$A$2:$B$716,2,0) -> 39988 | E13: =+C13*D13 -> 2599.22
B14: Esencia de vainilla | C14: 0.005 | D14: =+VLOOKUP(B14,'PRECIO PROVEEDORES'!$A$2:$B$716,2,0) -> 2118 | E14: =+C14*D14 -> 10.59
B15: banio leche moldatte | C15: 0.065 | D15: =+VLOOKUP(B15,'PRECIO PROVEEDORES'!$A$2:$B$716,2,0) -> 10030 | E15: =+C15*D15 -> 651.95
B16: baniosemiamargo moldatte | C16: 0.065 | D16: =+VLOOKUP(B16,'PRECIO PROVEEDORES'!$A$2:$B$716,2,0) -> 12959 | E16: =+C16*D16 -> 842.335
B19: Costo Total de la materia prima | E19: =SUM(E4:E18) -> 10667.514 | G19: Costo Total de la materia prima | J19: =SUM(J4:J18) -> 17894.296 | L19: Costo Total de la materia prima | O19: =SUM(O4:O18) -> 18015.976
B20: Costo total de la preparación | E20: =SUM(E19) -> 10667.514 | G20: Costo total de la preparación | J20: =SUM(J19) -> 17894.296 | L20: Costo total de la preparación | O20: =SUM(O19) -> 18015.976
B21: Costo porción | E21: =+E20/14 -> 761.9653 | G21: Costo porción | J21: =+J20/70 -> 255.6328 | L21: Costo porción | O21: =+O20/40 -> 450.3994
B22: Porcentaje costo materia prima establecida | D22: 0.3 | F22: =E23-(E23*5%) -> 2412.8901 | G22: Porcentaje costo materia prima establecida | I22: 0.3 | K22: =J23-(J23*5%) -> 809.50387 | L22: Porcentaje costo materia prima establecida | N22: 0.3
B23: Precio potencial de venta | E23: =+E21*3.33333333333333 -> 2539.8843 | F23: =E23-(E23*10%) -> 2285.8959 | G23: Precio potencial de venta | J23: =+J21*3.33333333333333 -> 852.10933 | K23: =J23-(J23*10%) -> 766.8984 | L23: Precio potencial de venta | O23: =+O21*3.33333333333333 -> 1501.3313
B24: Precio de Venta | D24: 2286 | E24: 3400 | F24: =E23-(E23*15%) -> 2158.9017 | G24: Precio de Venta | H24: 900 | I24: 850 | J24: 916.66 | K24: =J23-(J23*15%) -> 724.29293 | L24: Precio de Venta | N24: 1350 | O24: 1510.41
E25: =+E24-E23 -> 860.11567 | F25: =E23-(E24*20%) -> 1859.8843 | J25: =+J24-J23 -> 64.550667 | K25: =J23-(J24*20%) -> 668.77733 | O25: =+O24-O23 -> 9.0786667
B26: Costo Real MP | E26: =E21/E24 -> 0.22410744 | G26: Costo Real MP | J26: =J21/J24 -> 0.27887417 | L26: Costo Real MP | O26: =O21/O24 -> 0.29819678
B29: CROISSANT 120 grs | G29: COOKIE DE FRAMBUESA Y CHOCO BLANCO 100 grs c/u | L29: KEYLIME PIE
C30: Kg/Lt/Uni | D30: $ | E30: Total $ | H30: Kg/Lt/Uni | I30: $ | J30: Total $ | M30: Kg/Lt/Uni | N30: $ | O30: Total $
B31: harina 0000 | C31: 2 | D31: =+VLOOKUP(B31,'PRECIO PROVEEDORES'!$A$2:$B$716,2,0) -> 1043.22 | E31: =+C31*D31 -> 2086.44 | G31: manteca | H31: 0.32 | I31: =+VLOOKUP(G31,'PRECIO PROVEEDORES'!$A$2:$B$716,2,0) -> 12000 | J31: =+H31*I31 -> 3840 | L31: lima | M31: 0.25 | N31: =+VLOOKUP(L31,'PRECIO PROVEEDORES'!$A$2:$B$716,2,0) -> 5400 | O31: =+M31*N31 -> 1350
B32: harina 000 | C32: 0.5 | D32: =+VLOOKUP(B32,'PRECIO PROVEEDORES'!$A$2:$B$716,2,0) -> 890 | E32: =+C32*D32 -> 445 | G32: azucar | H32: 0.4 | I32: =+VLOOKUP(G32,'PRECIO PROVEEDORES'!$A$2:$B$716,2,0) -> 1352 | J32: =+H32*I32 -> 540.8 | L32: leche condensada | M32: 0.88 | N32: =+VLOOKUP(L32,'PRECIO PROVEEDORES'!$A$2:$B$716,2,0) -> 12675 | O32: =+M32*N32 -> 11154
B33: azucar | C33: 0.25 | D33: =+VLOOKUP(B33,'PRECIO PROVEEDORES'!$A$2:$B$716,2,0) -> 1352 | E33: =+C33*D33 -> 338 | G33: huevos | H33: 2 | I33: =+VLOOKUP(G33,'PRECIO PROVEEDORES'!$A$2:$B$716,2,0) -> 192 | J33: =+H33*I33 -> 384 | L33: huevos | M33: 6 | N33: =+VLOOKUP(L33,'PRECIO PROVEEDORES'!$A$2:$B$716,2,0) -> 192 | O33: =+M33*N33 -> 1152
B34: levadura seca | C34: 0.016 | D34: =+VLOOKUP(B34,'PRECIO PROVEEDORES'!$A$2:$B$716,2,0) -> 17780 | E34: =+C34*D34 -> 284.48 | G34: harina 0000 | H34: 0.535 | I34: =+VLOOKUP(G34,'PRECIO PROVEEDORES'!$A$2:$B$716,2,0) -> 1043.22 | J34: =+H34*I34 -> 558.1227 | L34: crema richbettercream | M34: 0.12 | N34: =+VLOOKUP(L34,'PRECIO PROVEEDORES'!$A$2:$B$716,2,0) -> 7331 | O34: =+M34*N34 -> 879.72
B35: huevos | C35: 3 | D35: =+VLOOKUP(B35,'PRECIO PROVEEDORES'!$A$2:$B$716,2,0) -> 192 | E35: =+C35*D35 -> 576 | G35: Polvo para hornear | H35: 0.008 | I35: =+VLOOKUP(G35,'PRECIO PROVEEDORES'!$A$2:$B$716,2,0) -> 6040 | J35: =+H35*I35 -> 48.32 | L35: almendras | M35: 0.01 | N35: =+VLOOKUP(L35,'PRECIO PROVEEDORES'!$A$2:$B$716,2,0) -> 25872 | O35: =+M35*N35 -> 258.72
B36: manteca | C36: 0.7 | D36: =+VLOOKUP(B36,'PRECIO PROVEEDORES'!$A$2:$B$716,2,0) -> 12000 | E36: =+C36*D36 -> 8400 | G36: Esencia de vainilla | H36: 0.01 | I36: =+VLOOKUP(G36,'PRECIO PROVEEDORES'!$A$2:$B$716,2,0) -> 2118 | J36: =+H36*I36 -> 21.18 | L36: galletas caseras | M36: 0.5 | N36: 3883.2156 | O36: 1941.6078
B37: sal fina | C37: 0.044 | D37: =+VLOOKUP(B37,'PRECIO PROVEEDORES'!$A$2:$B$716,2,0) -> 1633 | E37: =+C37*D37 -> 71.852 | G37: Fenix 90 blanco | H37: 0.06 | I37: =+VLOOKUP(G37,'PRECIO PROVEEDORES'!$A$2:$B$716,2,0) -> 34892 | J37: =+H37*I37 -> 2093.52 | L37: Manteca | M37: 0.2 | N37: 11625 | O37: 2325
G38: frambuesa congelada | H38: 0.12 | I38: =+VLOOKUP(G38,'PRECIO PROVEEDORES'!$A$2:$B$716,2,0) -> 24829 | J38: =+H38*I38 -> 2979.48
G39: banio blanco moldatte | H39: 0.06 | I39: =+VLOOKUP(G39,'PRECIO PROVEEDORES'!$A$2:$B$716,2,0) -> 9506 | J39: =+H39*I39 -> 570.36
B46: Costo Total de la materia prima | E46: =SUM(E31:E45) -> 12201.772 | G46: Costo Total de la materia prima | J46: =SUM(J31:J45) -> 11035.783 | L46: Costo Total de la materia prima | O46: =SUM(O31:O45) -> 19061.048
B47: Costo total de la preparación | E47: =SUM(E46) -> 12201.772 | G47: Costo total de la preparación | J47: =SUM(J46) -> 11035.783 | L47: Costo total de la preparación | O47: =SUM(O46) -> 19061.048
B48: Costo porción | E48: =+E47/32 -> 381.30538 | G48: Costo porción | J48: =+J47/16 -> 689.73642 | L48: Costo porción | O48: =+O47 -> 19061.048
B49: Porcentaje costo materia prima establecida | D49: 0.3 | G49: Porcentaje costo materia prima establecida | I49: 0.3 | L49: Porcentaje costo materia prima establecida | N49: 0.3
B50: Precio potencial de venta | E50: =+E48*3.33333333333333 -> 1271.0179 | G50: Precio potencial de venta | J50: =+J48*3.33333333333333 -> 2299.1214 | L50: Precio potencial de venta | O50: =+O48*3.33333333333333 -> 63536.826 | Q50: =45000/8 -> 5625
B51: Precio de Venta | D51: 1950 | E51: 2055.55 | F51: d | G51: Precio de Venta | I51: 2070 | J51: 3366.66 | L51: Precio de Venta | N51: =57184/8 -> 7148 | O51: 66000
E52: =+E51-E50 -> 784.53208 | J52: =+J51-J50 -> 1067.5386 | O52: =+O51-O50 -> 2463.174
B53: Costo Real MP | E53: =E48/E51 -> 0.18550041 | G53: Costo Real MP | J53: =J48/J51 -> 0.20487261 | L53: Costo Real MP | O53: =O48/O51 -> 0.28880375
B56: COOKIE RED VELVET CON FROSTING | G56: COOKIE DE AVENA Y FRUTOS SECOS | L56: PAN DE CHOCOLATE
C57: Kg/Lt/Uni | D57: $ | E57: Total $ | H57: Kg/Lt/Uni | I57: $ | J57: Total $ | M57: Kg/Lt/Uni | N57: $ | O57: Total $
B58: manteca | C58: 0.225 | D58: =+VLOOKUP(B58,'PRECIO PROVEEDORES'!$A$2:$B$716,2,0) -> 12000 | E58: =+C58*D58 -> 2700 | G58: manteca | H58: 0.275 | I58: =+VLOOKUP(G58,'PRECIO PROVEEDORES'!$A$2:$B$716,2,0) -> 12000 | J58: =+H58*I58 -> 3300 | L58: harina 0000 | M58: 1.8 | N58: =+VLOOKUP(L58,'PRECIO PROVEEDORES'!$A$2:$B$716,2,0) -> 1043.22 | O58: =+M58*N58 -> 1877.796
B59: azucar | C59: 0.2 | D59: =+VLOOKUP(B59,'PRECIO PROVEEDORES'!$A$2:$B$716,2,0) -> 1352 | E59: =+C59*D59 -> 270.4 | G59: azucar | H59: 0.4 | I59: =+VLOOKUP(G59,'PRECIO PROVEEDORES'!$A$2:$B$716,2,0) -> 1352 | J59: =+H59*I59 -> 540.8 | L59: harina 000 | M59: 0.2 | N59: =+VLOOKUP(L59,'PRECIO PROVEEDORES'!$A$2:$B$716,2,0) -> 890 | O59: =+M59*N59 -> 178
B60: Azucar negro | C60: 0.2 | D60: =+VLOOKUP(B60,'PRECIO PROVEEDORES'!$A$2:$B$716,2,0) -> 1624.77 | E60: =+C60*D60 -> 324.954 | G60: azucar negro | H60: 0.125 | I60: =+VLOOKUP(G60,'PRECIO PROVEEDORES'!$A$2:$B$716,2,0) -> 1624.77 | J60: =+H60*I60 -> 203.09625 | L60: azucar | M60: 0.35 | N60: =+VLOOKUP(L60,'PRECIO PROVEEDORES'!$A$2:$B$716,2,0) -> 1352 | O60: =+M60*N60 -> 473.2
B61: colorante comestible en pasta | C61: 0.004 | D61: =+VLOOKUP(B61,'PRECIO PROVEEDORES'!$A$2:$B$716,2,0) -> 93400 | E61: =+C61*D61 -> 373.6 | G61: huevos | H61: 2 | I61: =+VLOOKUP(G61,'PRECIO PROVEEDORES'!$A$2:$B$716,2,0) -> 192 | J61: =+H61*I61 -> 384 | L61: levadura seca | M61: 0.02 | N61: =+VLOOKUP(L61,'PRECIO PROVEEDORES'!$A$2:$B$716,2,0) -> 17780 | O61: =+M61*N61 -> 355.6
B62: esencia de vainilla | C62: 0.005 | D62: =+VLOOKUP(B62,'PRECIO PROVEEDORES'!$A$2:$B$716,2,0) -> 2118 | E62: =+C62*D62 -> 10.59 | G62: harina 0000 | H62: 0.33 | I62: =+VLOOKUP(G62,'PRECIO PROVEEDORES'!$A$2:$B$716,2,0) -> 1043.22 | J62: =+H62*I62 -> 344.2626 | L62: sal fina | M62: 0.04 | N62: =+VLOOKUP(L62,'PRECIO PROVEEDORES'!$A$2:$B$716,2,0) -> 1633 | O62: =+M62*N62 -> 65.32
B63: harina 0000 | C63: 0.42 | D63: =+VLOOKUP(B63,'PRECIO PROVEEDORES'!$A$2:$B$716,2,0) -> 1043.22 | E63: =+C63*D63 -> 438.1524 | G63: polvo para hornear | H63: 0.008 | I63: =+VLOOKUP(G63,'PRECIO PROVEEDORES'!$A$2:$B$716,2,0) -> 6040 | J63: =+H63*I63 -> 48.32 | L63: leche | M63: 0.5 | N63: =+VLOOKUP(L63,'PRECIO PROVEEDORES'!$A$2:$B$716,2,0) -> 1940 | O63: =+M63*N63 -> 970
B64: Cacao amargo | C64: 0.02 | D64: =+VLOOKUP(B64,'PRECIO PROVEEDORES'!$A$2:$B$716,2,0) -> 13205 | E64: =+C64*D64 -> 264.1 | G64: Avena arrollada | H64: 0.4 | I64: =+VLOOKUP(G64,'PRECIO PROVEEDORES'!$A$2:$B$716,2,0) -> 2180 | J64: =+H64*I64 -> 872 | L64: huevos | M64: 6 | N64: =+VLOOKUP(L64,'PRECIO PROVEEDORES'!$A$2:$B$716,2,0) -> 192 | O64: =+M64*N64 -> 1152
B65: bicarbonato de sodio | C65: 0.004 | D65: =+VLOOKUP(B65,'PRECIO PROVEEDORES'!$A$2:$B$716,2,0) -> 2517 | E65: =+C65*D65 -> 10.068 | G65: leche | H65: 0.025 | I65: =+VLOOKUP(G65,'PRECIO PROVEEDORES'!$A$2:$B$716,2,0) -> 1940 | J65: =+H65*I65 -> 48.5 | L65: miel | M65: 0.06 | N65: =+VLOOKUP(L65,'PRECIO PROVEEDORES'!$A$2:$B$716,2,0) -> 6062 | O65: =+M65*N65 -> 363.72
B66: queso crema milkaut | C66: 0.084 | D66: =+VLOOKUP(B66,'PRECIO PROVEEDORES'!$A$2:$B$716,2,0) -> 15314 | E66: =+C66*D66 -> 1286.376 | G66: Pasas de uva negra | H66: 0.075 | I66: =+VLOOKUP(G66,'PRECIO PROVEEDORES'!$A$2:$B$716,2,0) -> 6292 | J66: =+H66*I66 -> 471.9 | L66: manteca | M66: 0.72 | N66: =+VLOOKUP(L66,'PRECIO PROVEEDORES'!$A$2:$B$716,2,0) -> 12000 | O66: =+M66*N66 -> 8640
B67: azucar impalpable | C67: 0.042 | D67: =+VLOOKUP(B67,'PRECIO PROVEEDORES'!$A$2:$B$716,2,0) -> 1684 | E67: =+C67*D67 -> 70.728 | G67: Nueces cuartos | H67: 0.075 | I67: =+VLOOKUP(G67,'PRECIO PROVEEDORES'!$A$2:$B$716,2,0) -> 27769.5 | J67: =+H67*I67 -> 2082.7125 | L67: ba;o alpino semiamargo | M67: 0.3 | N67: =+VLOOKUP(L67,'PRECIO PROVEEDORES'!$A$2:$B$716,2,0) -> 9056 | O67: =+M67*N67 -> 2716.8
B68: almidon de maiz | C68: 0.007 | D68: =+VLOOKUP(B68,'PRECIO PROVEEDORES'!$A$2:$B$716,2,0) -> 2191 | E68: =+C68*D68 -> 15.337 | G68: mani tostado sin sal | H68: 0.075 | I68: =+VLOOKUP(G68,'PRECIO PROVEEDORES'!$A$2:$B$716,2,0) -> 5987 | J68: =+H68*I68 -> 449.025 | L68: cacao amargo | M68: 0.04 | N68: =+VLOOKUP(L68,'PRECIO PROVEEDORES'!$A$2:$B$716,2,0) -> 13205 | O68: =+M68*N68 -> 528.2
B69: huevos | C69: 2 | D69: =+VLOOKUP(B69,'PRECIO PROVEEDORES'!$A$2:$B$716,2,0) -> 192 | E69: =+C69*D69 -> 384 | L69: azucar impalpable | M69: 0.1 | N69: =+VLOOKUP(L69,'PRECIO PROVEEDORES'!$A$2:$B$716,2,0) -> 1684 | O69: =+M69*N69 -> 168.4
B70: Fenix 90 blanco | C70: 0.075 | D70: =+VLOOKUP(B70,'PRECIO PROVEEDORES'!$A$2:$B$716,2,0) -> 34892 | E70: =+C70*D70 -> 2616.9 | L70: almidon de maiz | M70: 0.015 | N70: =+VLOOKUP(L70,'PRECIO PROVEEDORES'!$A$2:$B$716,2,0) -> 2191 | O70: =+M70*N70 -> 32.865
B71: leche | C71: 0.02 | D71: =+VLOOKUP(B71,'PRECIO PROVEEDORES'!$A$2:$B$716,2,0) -> 1940 | E71: =+C71*D71 -> 38.8
B72: polvo para hornear | C72: 0.008 | D72: =+VLOOKUP(B72,'PRECIO PROVEEDORES'!$A$2:$B$716,2,0) -> 6040 | E72: =+C72*D72 -> 48.32
B73: banio blanco moldatte | C73: 0.075 | D73: =+VLOOKUP(B73,'PRECIO PROVEEDORES'!$A$2:$B$716,2,0) -> 9506 | E73: =+C73*D73 -> 712.95
B75: Costo Total de la materia prima | E75: =SUM(E58:E72) -> 8852.3254 | G75: Costo Total de la materia prima | J75: =SUM(J58:J72) -> 8744.6164 | L75: Costo Total de la materia prima | O75: =SUM(O58:O72) -> 17521.901
B76: Costo total de la preparación | E76: =SUM(E75) -> 8852.3254 | G76: Costo total de la preparación | J76: =SUM(J75) -> 8744.6164 | L76: Costo total de la preparación | O76: =SUM(O75) -> 17521.901
B77: Costo porción | E77: =+E76/14 -> 632.30896 | G77: Costo porción | J77: =+J76/18 -> 485.81202 | L77: Costo porción | O77: =+O76/30 -> 584.06337
B78: Porcentaje costo materia prima establecida | D78: 0.3 | G78: Porcentaje costo materia prima establecida | I78: 0.3 | L78: Porcentaje costo materia prima establecida | N78: 0.3
B79: Precio potencial de venta | E79: =+E77*3.33333333333333 -> 2107.6965 | G79: Precio potencial de venta | J79: =+J77*3.33333333333333 -> 1619.3734 | L79: Precio potencial de venta | O79: =+O77*3.33333333333333 -> 1946.8779
B80: Precio de Venta | D80: 3550 | E80: 3666.66 | G80: Precio de Venta | I80: 3150 | J80: 3000 | L80: Precio de Venta | O80: 2800
E81: =+E80-E79 -> 1558.9635 | J81: =+J80-J79 -> 1380.6266 | O81: =+O80-O79 -> 853.12211
B82: Costo Real MP | E82: =E77/E80 -> 0.17244821 | G82: Costo Real MP | J82: =J77/J80 -> 0.16193734 | L82: Costo Real MP | O82: =O77/O80 -> 0.20859406
B85: ALFAJOR DE ALMENDRAS | G85: ALFACOOKIE CON DDL | L85: TORTA CHOCO Y DULCE DE LECHE
C86: Kg/Lt/Uni | D86: $ | E86: Total $ | H86: Kg/Lt/Uni | I86: $ | J86: Total $ | M86: Kg/Lt/Uni | N86: $ | O86: Total $
B87: tapitas alfajor de almendras | C87: 2 | D87: =+VLOOKUP(B87,'PRECIO PROVEEDORES'!$A$2:$B$716,2,0) -> 248.90715 | E87: =+C87*D87 -> 497.81429 | G87: dulce de leche | H87: 0.16 | I87: =+VLOOKUP(G87,'PRECIO PROVEEDORES'!$A$2:$B$716,2,0) -> 3356 | J87: =+H87*I87 -> 536.96 | L87: leche | M87: 0.32 | N87: =+VLOOKUP(L87,'PRECIO PROVEEDORES'!$A$2:$B$716,2,0) -> 1940 | O87: =+M87*N87 -> 620.8
B88: Dulce de leche | C88: 0.035 | D88: =+VLOOKUP(B88,'PRECIO PROVEEDORES'!$A$2:$B$716,2,0) -> 3356 | E88: =+C88*D88 -> 117.46 | G88: manteca | H88: 0.45 | I88: =+VLOOKUP(G88,'PRECIO PROVEEDORES'!$A$2:$B$716,2,0) -> 12000 | J88: =+H88*I88 -> 5400 | L88: manteca | M88: 0.145 | N88: =+VLOOKUP(L88,'PRECIO PROVEEDORES'!$A$2:$B$716,2,0) -> 12000 | O88: =+M88*N88 -> 1740
B89: Chips alpino con leche | C89: 0.02 | D89: =+VLOOKUP(B89,'PRECIO PROVEEDORES'!$A$2:$B$716,2,0) -> 9561 | E89: =+C89*D89 -> 191.22 | G89: azucar | H89: 0.4 | I89: =+VLOOKUP(G89,'PRECIO PROVEEDORES'!$A$2:$B$716,2,0) -> 1352 | J89: =+H89*I89 -> 540.8 | L89: huevos | M89: 4 | N89: =+VLOOKUP(L89,'PRECIO PROVEEDORES'!$A$2:$B$716,2,0) -> 192 | O89: =+M89*N89 -> 768
B90: Almendras | C90: 0.005 | D90: =+VLOOKUP(B90,'PRECIO PROVEEDORES'!$A$2:$B$716,2,0) -> 25872 | E90: =+C90*D90 -> 129.36 | G90: azucar negro | H90: 0.4 | I90: =+VLOOKUP(G90,'PRECIO PROVEEDORES'!$A$2:$B$716,2,0) -> 1624.77 | J90: =+H90*I90 -> 649.908 | L90: azucar | M90: 0.45 | N90: =+VLOOKUP(L90,'PRECIO PROVEEDORES'!$A$2:$B$716,2,0) -> 1352 | O90: =+M90*N90 -> 608.4
G91: huevos | H91: 4 | I91: =+VLOOKUP(G91,'PRECIO PROVEEDORES'!$A$2:$B$716,2,0) -> 192 | J91: =+H91*I91 -> 768 | L91: harina 0000 | M91: 0.31 | N91: =+VLOOKUP(L91,'PRECIO PROVEEDORES'!$A$2:$B$716,2,0) -> 1043.22 | O91: =+M91*N91 -> 323.3982
G92: harina 0000 | H92: 0.92 | I92: =+VLOOKUP(G92,'PRECIO PROVEEDORES'!$A$2:$B$716,2,0) -> 1043.22 | J92: =+H92*I92 -> 959.7624 | L92: cacao amargo | M92: 0.06 | N92: =+VLOOKUP(L92,'PRECIO PROVEEDORES'!$A$2:$B$716,2,0) -> 13205 | O92: =+M92*N92 -> 792.3
G93: bicarbonato de sodio | H93: 0.01 | I93: =+VLOOKUP(G93,'PRECIO PROVEEDORES'!$A$2:$B$716,2,0) -> 2517 | J93: =+H93*I93 -> 25.17 | L93: bicarbonato de sodio | M93: 0.005 | N93: =+VLOOKUP(L93,'PRECIO PROVEEDORES'!$A$2:$B$716,2,0) -> 2517 | O93: =+M93*N93 -> 12.585
G94: polvo para hornear | H94: 0.014 | I94: =+VLOOKUP(G94,'PRECIO PROVEEDORES'!$A$2:$B$716,2,0) -> 6040 | J94: =+H94*I94 -> 84.56 | L94: cafe instantaneo | M94: 0.005 | N94: =+VLOOKUP(L94,'PRECIO PROVEEDORES'!$A$2:$B$716,2,0) -> 36376.47 | O94: =+M94*N94 -> 181.88235
G95: sal fina | H95: 0.014 | I95: =+VLOOKUP(G95,'PRECIO PROVEEDORES'!$A$2:$B$716,2,0) -> 1633 | J95: =+H95*I95 -> 22.862 | L95: dulce de leche | M95: 0.6 | N95: =+VLOOKUP(L95,'PRECIO PROVEEDORES'!$A$2:$B$716,2,0) -> 3356 | O95: =+M95*N95 -> 2013.6
G96: Fenix 83 ( con leche) | H96: 0.25 | I96: =+VLOOKUP(G96,'PRECIO PROVEEDORES'!$A$2:$B$716,2,0) -> 36068 | J96: =+H96*I96 -> 9017 | L96: Crema de leche | M96: 0.2 | N96: =+VLOOKUP(L96,'PRECIO PROVEEDORES'!$A$2:$B$716,2,0) -> 10203 | O96: =+M96*N96 -> 2040.6
G97: Fenix 86 (semi amargo) | H97: 0.25 | I97: =+VLOOKUP(G97,'PRECIO PROVEEDORES'!$A$2:$B$716,2,0) -> 39988 | J97: =+H97*I97 -> 9997 | L97: Fenix 86 (semi amargo) | M97: 0.2 | N97: =+VLOOKUP(L97,'PRECIO PROVEEDORES'!$A$2:$B$716,2,0) -> 39988 | O97: =+M97*N97 -> 7997.6
G98: esencia de vainilla | H98: 0.01 | I98: =+VLOOKUP(G98,'PRECIO PROVEEDORES'!$A$2:$B$716,2,0) -> 2118 | J98: =+H98*I98 -> 21.18 | L98: Chips alpino con leche | M98: 0.05 | N98: =+VLOOKUP(L98,'PRECIO PROVEEDORES'!$A$2:$B$716,2,0) -> 9561 | O98: =+M98*N98 -> 478.05
B102: Costo Total de la materia prima | E102: =SUM(E87:E101) -> 935.85429 | G102: Costo Total de la materia prima | J102: =SUM(J87:J101) -> 28023.202 | L102: Costo Total de la materia prima | O102: =SUM(O87:O101) -> 17577.216
B103: Costo total de la preparación | E103: =SUM(E102) -> 935.85429 | G103: Costo total de la preparación | J103: =SUM(J102) -> 28023.202 | L103: Costo total de la preparación | O103: =SUM(O102) -> 17577.216
B104: Costo porción | E104: =+E103 -> 935.85429 | G104: Costo porción | J104: =+J103/29 -> 966.31732 | L104: Costo porción | O104: =+O103 -> 17577.216
B105: Porcentaje costo materia prima establecida | D105: 0.3 | G105: Porcentaje costo materia prima establecida | I105: 0.3 | L105: Porcentaje costo materia prima establecida | N105: 0.3
B106: Precio potencial de venta | E106: =+E104*3.33333333333333 -> 3119.5143 | G106: Precio potencial de venta | J106: =+J104*3.33333333333333 -> 3221.0577 | L106: Precio potencial de venta | O106: =+O104*3.33333333333333 -> 58590.718
B107: Precio de Venta | D107: 3750 | E107: 3850 | G107: Precio de Venta | I107: 3833 | J107: 4000 | L107: Precio de Venta a tueste | O107: 53226
E108: =+E107-E106 -> 730.48568 | J108: =+J107-J106 -> 778.94225 | O108: =+O107-O106 -> -5364.7185
B109: Costo Real MP | E109: =E104/E107 -> 0.24307904 | G109: Costo Real MP | J109: =J104/J107 -> 0.24157933 | L109: Costo Real MP | O109: =O104/O107 -> 0.33023739
B112: CARROT CAKE | G112: CHEESECAKE FRUTOS ROJOS | L112: BUDIN CHOCOLATE, BANANA Y NUEZ
C113: Kg/Lt/Uni | D113: $ | E113: Total $ | H113: Kg/Lt/Uni | I113: $ | J113: Total $ | M113: Kg/Lt/Uni | N113: $ | O113: Total $
B114: zanahoria | C114: 0.4 | D114: =+VLOOKUP(B114,'PRECIO PROVEEDORES'!$A$2:$B$716,2,0) -> 1650 | E114: =+C114*D114 -> 660 | G114: galletas caseras | H114: 0.3 | I114: =+VLOOKUP(G114,'PRECIO PROVEEDORES'!$A$2:$B$716,2,0) -> 4063.4264 | J114: =+H114*I114 -> 1219.0279 | L114: banana | M114: 0.27 | N114: =+VLOOKUP(L114,'PRECIO PROVEEDORES'!$A$2:$B$716,2,0) -> 3360 | O114: =+M114*N114 -> 907.2
B115: coco rallado | C115: 0.06 | D115: =+VLOOKUP(B115,'PRECIO PROVEEDORES'!$A$2:$B$716,2,0) -> 11721 | E115: =+C115*D115 -> 703.26 | G115: manteca | H115: 0.06 | I115: =+VLOOKUP(G115,'PRECIO PROVEEDORES'!$A$2:$B$716,2,0) -> 12000 | J115: =+H115*I115 -> 720 | L115: manzana verde | M115: 0.155 | N115: =+VLOOKUP(L115,'PRECIO PROVEEDORES'!$A$2:$B$716,2,0) -> 2850 | O115: =+M115*N115 -> 441.75
B116: azucar | C116: 0.3 | D116: =+VLOOKUP(B116,'PRECIO PROVEEDORES'!$A$2:$B$716,2,0) -> 1352 | E116: =+C116*D116 -> 405.6 | G116: queso crema | H116: 0.8 | I116: =+VLOOKUP(G116,'PRECIO PROVEEDORES'!$A$2:$B$716,2,0) -> 6600 | J116: =+H116*I116 -> 5280 | L116: azucar | M116: 0.25 | N116: =+VLOOKUP(L116,'PRECIO PROVEEDORES'!$A$2:$B$716,2,0) -> 1352 | O116: =+M116*N116 -> 338
B117: esencia de vainilla | C117: 0.005 | D117: =+VLOOKUP(B117,'PRECIO PROVEEDORES'!$A$2:$B$716,2,0) -> 2118 | E117: =+C117*D117 -> 10.59 | G117: crema de leche | H117: 0.15 | I117: =+VLOOKUP(G117,'PRECIO PROVEEDORES'!$A$2:$B$716,2,0) -> 10203 | J117: =+H117*I117 -> 1530.45 | L117: aceite de girasol | M117: 0.085 | N117: =+VLOOKUP(L117,'PRECIO PROVEEDORES'!$A$2:$B$716,2,0) -> 4299.01 | O117: =+M117*N117 -> 365.41585
B118: harina 0000 | C118: 0.225 | D118: =+VLOOKUP(B118,'PRECIO PROVEEDORES'!$A$2:$B$716,2,0) -> 1043.22 | E118: =+C118*D118 -> 234.7245 | G118: azucar | H118: 0.15 | I118: =+VLOOKUP(G118,'PRECIO PROVEEDORES'!$A$2:$B$716,2,0) -> 1352 | J118: =+H118*I118 -> 202.8 | L118: coco rallado | M118: 0.08 | N118: =+VLOOKUP(L118,'PRECIO PROVEEDORES'!$A$2:$B$716,2,0) -> 11721 | O118: =+M118*N118 -> 937.68
B119: bicarbonato de sodio | C119: 0.005 | D119: =+VLOOKUP(B119,'PRECIO PROVEEDORES'!$A$2:$B$716,2,0) -> 2517 | E119: =+C119*D119 -> 12.585 | G119: huevos | H119: 4 | I119: =+VLOOKUP(G119,'PRECIO PROVEEDORES'!$A$2:$B$716,2,0) -> 192 | J119: =+H119*I119 -> 768 | L119: Vinagre de alcohol | M119: 0.03 | N119: =+VLOOKUP(L119,'PRECIO PROVEEDORES'!$A$2:$B$716,2,0) -> 1037 | O119: =+M119*N119 -> 31.11
B120: polvo para hornear | C120: 0.004 | D120: =+VLOOKUP(B120,'PRECIO PROVEEDORES'!$A$2:$B$716,2,0) -> 6040 | E120: =+C120*D120 -> 24.16 | G120: almidon de maiz | H120: 0.02 | I120: =+VLOOKUP(G120,'PRECIO PROVEEDORES'!$A$2:$B$716,2,0) -> 2191 | J120: =+H120*I120 -> 43.82 | L120: esencia de vainilla | M120: 0.025 | N120: =+VLOOKUP(L120,'PRECIO PROVEEDORES'!$A$2:$B$716,2,0) -> 2118 | O120: =+M120*N120 -> 52.95
B121: canela en polvo | C121: 0.004 | D121: =+VLOOKUP(B121,'PRECIO PROVEEDORES'!$A$2:$B$716,2,0) -> 10061.64 | E121: =+C121*D121 -> 40.24656 | G121: Coulis de frutos rojos | H121: 0.5 | I121: =+VLOOKUP(G121,'PRECIO PROVEEDORES'!$A$2:$B$716,2,0) -> 8184 | J121: =+H121*I121 -> 4092 | L121: sal fina | M121: 0.01 | N121: =+VLOOKUP(L121,'PRECIO PROVEEDORES'!$A$2:$B$716,2,0) -> 1633 | O121: =+M121*N121 -> 16.33
...

Sheet TUESTE AL PÚBLICO
B2: PRODUCTO | C2: COMPRA TUESTE | D2: COSTO ENVÍO | E2: VENTA EN TUESTE | F2: % RENTABILIDAD | H2: ESCALA DE RENTABILIDAD
H3: 0% a 40%
B4: COOKIE DOBLE CHOCO | C4: ='PASTELERIA CP'!D24 -> 2286 | E4: 5100 | F4: =((E4-C4)/E4)*1 -> 0.55176471 | H4: 40% a 45%
B5: ALFAJOR DE CHOCO Y DDL | C5: ='PASTELERIA CP'!E641 -> 3429 | E5: 6500 | F5: =((E5-C5)/E5)*1 -> 0.47246154 | H5: 45% a 60%
B6: MEDIALUNA 90 GRS | C6: ='PASTELERIA CP'!N24 -> 1350 | E6: 3100 | F6: =((E6-C6)/E6)*1 -> 0.56451613 | H6: más de 60%
B7: CROISSANT 140 grs | C7: ='PASTELERIA PARA TUESTE'!E51 -> 1307 | E7: 4800 | F7: =((E7-C7)/E7)*1 -> 0.72770833
B8: COOKIE DE FRAMBUESA Y CHOCO BLANCO | C8: ='PASTELERIA CP'!I51 -> 2070 | E8: 5000 | F8: =((E8-C8)/E8)*1 -> 0.586
B9: KEYLIME PIE | C9: ='PASTELERIA CP'!N51 -> 7148 | E9: 12500 | F9: =((E9-C9)/E9)*1 -> 0.42816
B10: COOKIE RED VELVET | C10: ='PASTELERIA CP'!N476 -> 2473 | E10: 5100 | F10: =((E10-C10)/E10)*1 -> 0.51509804
B11: ALFAJOR DE FRAMBUESA Y DDL | C11: ='PASTELERIA CP'!I641 -> 4329 | E11: 7500 | F11: =((E11-C11)/E11)*1 -> 0.4228
B12: PAN DE CHOCOLATE Y FRAMBUESA | C12: ='PASTELERIA PARA TUESTE'!O80 -> 4600 | F12: =((E12-C12)/E12)*1 -> #DIV/0!
B13: ALFAJOR DE ALMENDRAS | C13: ='PASTELERIA PARA TUESTE'!E107 -> 2565 | F13: =((E13-C13)/E13)*1 -> #DIV/0!
B14: PASTAFROLA | C14: ='PASTELERIA CP'!O641 -> 1314.625 | E14: 4800 | F14: =((E14-C14)/E14)*1 -> 0.72611979
B15: TORTA BRUCE | C15: ='PASTELERIA CP'!E331 -> 8141.25 | E15: 15000 | F15: =((E15-C15)/E15)*1 -> 0.45725
B16: CARROT CAKE | C16: ='PASTELERIA CP'!D136 -> 2711.25 | E16: 10000 | F16: =((E16-C16)/E16)*1 -> 0.728875
B17: CHEESECAKE FRUTOS ROJOS | C17: ='PASTELERIA CP'!I136 -> 5224.25 | E17: 11500 | F17: =((E17-C17)/E17)*1 -> 0.54571739
B18: BUDIN CHOCOLATE, BANANA Y NUEZ | C18: ='PASTELERIA CP'!N136 -> 3279.6667 | E18: 6500 | F18: =((E18-C18)/E18)*1 -> 0.4954359
B19: BUDIN LIMON Y AMAPOLAS | C19: ='PASTELERIA CP'!D163 -> 1989 | E19: 6500 | F19: =((E19-C19)/E19)*1 -> 0.694
B20: COOKIES ESPECIALES | C20: ='PASTELERIA CP'!D668 -> 2776 | E20: 5500 | F20: =((E20-C20)/E20)*1 -> 0.49527273
B21: TORTA ESPECIAL CUMPLE | C21: ='PASTELERIA CP'!S588 -> 6595.25 | E21: 14000 | F21: =((E21-C21)/E21)*1 -> 0.52891071
B22: TORTA TUESTE | C22: ='PASTELERIA PARA TUESTE'!E190 -> 88393 | F22: =((E22-C22)/E22)*1 -> #DIV/0!
B23: ROLL CANELA | C23: ='PASTELERIA CP'!I163 -> 2401 | E23: 5600 | F23: =((E23-C23)/E23)*1 -> 0.57125
B24: BOLA DE FRAILE CON PASTELERA | C24: ='PASTELERIA CP'!I190 -> 2011 | E24: 3600 | F24: =((E24-C24)/E24)*1 -> 0.44138889
B25: BOLA DE FRAILE CON DDL | C25: ='PASTELERIA CP'!N217 -> 1545 | E25: 3600 | F25: =((E25-C25)/E25)*1 -> 0.57083333
B26: BUDIN DE NARANJA | C26: ='PASTELERIA PARA TUESTE'!I218 -> 2434.4444 | E26: 6500 | F26: =((E26-C26)/E26)*1 -> 0.62547009
B27: DANESAS DE MANZANA | C27: ='PASTELERIA PARA TUESTE'!N218 -> 3390 | E27: 7000 | F27: =((E27-C27)/E27)*1 -> 0.51571429
B28: MARQUISE | C28: ='PASTELERIA CP'!N331 -> 6515.25 | E28: 13000 | F28: =((E28-C28)/E28)*1 -> 0.49882692
B29: CHOCOTORTA | C29: ='PASTELERIA CP'!I331 -> 6902.75 | E29: 13500 | F29: =((E29-C29)/E29)*1 -> 0.48868519
B30: COOKIE CLASICA | C30: ='PASTELERIA CP'!I587 -> 2299 | E30: 5000 | F30: =((E30-C30)/E30)*1 -> 0.5402
B31: ALFAJOR PISTACHO SIN TACC | C31: 3803.91 | E31: 6800 | F31: =((E31-C31)/E31)*1 -> 0.44060147
B32: ALFAJOR MAR DEL PLATA SIN TACC | C32: 3000 | E32: 6300 | F32: =((E32-C32)/E32)*1 -> 0.52380952
B33: COOKIE NEW YORK SIN TACC | C33: 4180 | E33: 6600 | F33: =((E33-C33)/E33)*1 -> 0.36666667
B34: PAN SIN TACC X 2 RODAJAS | C34: 622.22 | E34: 2500 | F34: =((E34-C34)/E34)*1 -> 0.751112
B35: LATA GASEOSA | C35: 1083 | E35: 3800 | F35: =((E35-C35)/E35)*1 -> 0.715
B36: COOKIE NUTELLA Y CHOCO | C36: 3708 | E36: 6500 | F36: =((E36-C36)/E36)*1 -> 0.42953846
B37: TORTA ARGENTINA | C37: ='PASTELERIA CP'!N722 -> 9347 | E37: 17000 | F37: =((E37-C37)/E37)*1 -> 0.45017647
B38: PASTELITO BATATA | C38: ='PASTELERIA CP'!J749 -> 1602 | E38: 3200 | F38: =((E38-C38)/E38)*1 -> 0.499375
B39: PASTELITO MEMBRILLO | C39: ='PASTELERIA CP'!E749 -> 1710 | E39: 3200 | F39: =((E39-C39)/E39)*1 -> 0.465625
B40: COOKIE FRAMBUESA ESPECIAL | C40: ='PASTELERIA CP'!N588 -> 2113 | E40: 5800 | F40: =((E40-C40)/E40)*1 -> 0.63568966
B41: COOKIE DOBLE CHOCO ESPECIAL | C41: ='PASTELERIA CP'!D776 -> 2323 | E41: 5600 | F41: =((E41-C41)/E41)*1 -> 0.58517857
B42: FOSFORITO | C42: 1400 | E42: 4000 | F42: =((E42-C42)/E42)*1 -> 0.65
B43: BUDIN MARMOLADO | C43: ='PASTELERIA CP'!I776 -> 3213.5556 | E43: 6500 | F43: =((E43-C43)/E43)*1 -> 0.50560684
B44: COOKIE 3 CHOCO | C44: ='PASTELERIA CP'!N776 -> 1775 | E44: 5000 | F44: =((E44-C44)/E44)*1 -> 0.645
B45: COOKIE PISTACHO | C45: ='PASTELERIA CP'!D803 -> 3861 | E45: 6600 | F45: =((E45-C45)/E45)*1 -> 0.415
B46: COOKIE OREO | C46: ='PASTELERIA CP'!I803 -> 2054 | E46: 5500 | F46: =((E46-C46)/E46)*1 -> 0.62654545
B47: COOKIE DULCE DE LECHE | C47: ='PASTELERIA CP'!N803 -> 1322 | E47: 4800 | F47: =((E47-C47)/E47)*1 -> 0.72458333
B48: ALFAJOR MANI | C48: ='PASTELERIA CP'!D830 -> 3681 | E48: 6600 | F48: =((E48-C48)/E48)*1 -> 0.44227273
B49: ALFAJOR PISTACHO | C49: ='PASTELERIA CP'!I830 -> 7350 | E49: 10000 | F49: =((E49-C49)/E49)*1 -> 0.265
B50: ALFAJOR BLANCO | C50: ='PASTELERIA CP'!N830 -> 4317 | E50: 7500 | F50: =((E50-C50)/E50)*1 -> 0.4244
F51: =((E51-C51)/E51)*1 -> #DIV/0!
F52: =((E52-C52)/E52)*1 -> #DIV/0!
F53: =((E53-C53)/E53)*1 -> #DIV/0!
F54: =((E54-C54)/E54)*1 -> #DIV/0!
F55: =((E55-C55)/E55)*1 -> #DIV/0!
B56: CATERING | F56: =((E56-C56)/E56)*1 -> #DIV/0!
